Workbook

Sheet Search Term
C1: Rank | E1: Share | G1: Clicks | I1: Impressions | K1: CTR | M1: CPC | O1: Spend | Q1: Orders | S1: CR | U1: Sales | W1: ACOS | Y1: ROAS
A2: Customer Search Term | B2: Orders Diff | C2: march | D2: april | E2: march | F2: april | G2: march | H2: april | I2: march | J2: april | K2: march | L2: april | M2: march | N2: april | O2: march | P2: april | Q2: march | R2: april | S2: march | T2: april | U2: march | V2: april | W2: march | X2: april | Y2: march | Z2: april | AA2: Order
A3: ergoyou height adjustable table desk | B3: =R3-Q3 -> 7 | C3: 1 | D3: 1 | E3: 0.7167 | F3: 0.9352 | G3: 225 | H3: 239 | I3: 82822 | J3: 78901 | K3: 0.0027166695 | L3: 0.0030291124 | M3: 30.880178 | N3: 40.547364 | O3: 6948.04 | P3: 9690.82 | Q3: 8 | R3: 15 | S3: 0.035555556 | T3: 0.062761506 | U3: 174788.11 | V3: 301906.77 | W3: 0.039751216 | X3: 0.032098717 | Y3: 25.156463 | Z3: 31.153893 | AA3: 23
A4: height adjustable table | B4: =R4-Q4 -> -5 | C4: 3.5909091 | D4: 3 | E4: 0.089009091 | F4: 0.088259091 | G4: 1899 | H4: 1871 | I4: 376351 | J4: 382541 | K4: 0.0050458216 | L4: 0.004890979 | M4: 32.633017 | N4: 33.552181 | O4: 61970.1 | P4: 62776.13 | Q4: 13 | R4: 8 | S4: 0.0068457083 | T4: 0.0042757883 | U4: 277203.39 | V4: 161271.17 | W4: 0.22355463 | X4: 0.38925823 | Y4: 4.4731796 | Z4: 2.5689887 | AA4: 21
A5: standing desk | B5: =R5-Q5 -> -2 | C5: 2.5714286 | D5: 2 | E5: 0.088228571 | F5: 0.1029625 | G5: 896 | H5: 1002 | I5: 75450 | J5: 76373 | K5: 0.011875414 | L5: 0.01311982 | M5: 35.397991 | N5: 39.378463 | O5: 31716.6 | P5: 39457.22 | Q5: 10 | R5: 8 | S5: 0.011160714 | T5: 0.0079840319 | U5: 197033.9 | V5: 181779.65 | W5: 0.16097027 | X5: 0.21706071 | Y5: 6.2123273 | Z5: 4.607006 | AA5: 18
A6: ergo you height adjustable table | B6: =R6-Q6 -> 2 | C6: 1 | D6: 1 | E6: 0.7718 | F6: 0.9792 | G6: 137 | H6: 188 | I6: 42720 | J6: 57695 | K6: 0.0032069288 | L6: 0.0032585146 | M6: 42.78854 | N6: 48.150638 | O6: 5862.03 | P6: 9052.32 | Q6: 6 | R6: 8 | S6: 0.04379562 | T6: 0.042553191 | U6: 124490.67 | V6: 182456.77 | W6: 0.047088107 | X6: 0.049613506 | Y6: 21.236785 | Z6: 20.155802 | AA6: 14
A7: electric height adjustable table | B7: =R7-Q7 -> -7 | C7: 2 | D7: 1.8888889 | E7: 0.3606 | F7: 0.46673333 | G7: 240 | H7: 167 | I7: 146492 | J7: 111057 | K7: 0.0016383147 | L7: 0.0015037323 | M7: 51.771583 | N7: 60.21994 | O7: 12425.18 | P7: 10056.73 | Q7: 8 | R7: 1 | S7: 0.033333333 | T7: 0.005988024 | U7: 172988.98 | V7: 26186.44 | W7: 0.071826425 | X7: 0.38404342 | Y7: 13.922453 | Z7: 2.6038722 | AA7: 9
A8: height adjustable desk | B8: =R8-Q8 -> 5 | C8: 4.2857143 | D8: 3.1818182 | E8: 0.075271429 | F8: 0.094468182 | G8: 474 | H8: 562 | I8: 46858 | J8: 93202 | K8: 0.010115669 | L8: 0.0060299135 | M8: 31.184135 | N8: 34.807064 | O8: 14781.28 | P8: 19561.57 | Q8: 2 | R8: 7 | S8: 0.0042194093 | T8: 0.012455516 | U8: 38983.05 | V8: 142710.99 | W8: 0.37917197 | X8: 0.13707122 | Y8: 2.6373257 | Z8: 7.2954773 | AA8: 9
A9: sit stand desk | B9: =R9-Q9 -> -3 | C9: 4 | D9: 4 | E9: 0.0532 | F9: 0.058433333 | G9: 387 | H9: 357 | I9: 123296 | J9: 160508 | K9: 0.003138788 | L9: 0.0022241882 | M9: 43.605917 | N9: 50.885602 | O9: 16875.49 | P9: 18166.16 | Q9: 6 | R9: 3 | S9: 0.015503876 | T9: 0.0084033613 | U9: 106864.41 | V9: 63220.34 | W9: 0.15791497 | X9: 0.28734676 | Y9: 6.3325219 | Z9: 3.4801158 | AA9: 9
A10: b08lgjgzj1 | B10: =R10-Q10 -> 7 | C10: 2 | D10: 2 | E10: 0.1384 | F10: 0.3433 | G10: 119 | H10: 408 | I10: 10353 | J10: 23914 | K10: 0.011494253 | L10: 0.017061136 | M10: 28.933613 | N10: 42.711495 | O10: 3443.1 | P10: 17426.29 | Q10: 0 | R10: 7 | S10: 0 | T10: 0.017156863 | U10: 0 | V10: 98045.78 | W10: 0 | X10: 0.17773626 | Y10: 0 | Z10: 5.626314 | AA10: 7
A11: adjustable table | B11: =R11-Q11 -> -3 | C11: 16 | D11: 9.8888889 | E11: 0.20725556 | F11: 0.24098889 | G11: 867 | H11: 653 | I11: 29737 | J11: 18291 | K11: 0.029155597 | L11: 0.035700618 | M11: 10.977612 | N11: 9.9665697 | O11: 9517.59 | P11: 6508.17 | Q11: 4 | R11: 1 | S11: 0.0046136101 | T11: 0.0015313936 | U11: 72118.64 | V11: 25338.98 | W11: 0.13197129 | X11: 0.2568442 | Y11: 7.5774056 | Z11: 3.8934109 | AA11: 5
A12: b0cnxslf8j | B12: =R12-Q12 -> -3 | C12: 1 | D12: 1 | E12: 0.9794 | F12: 0.9909 | G12: 168 | H12: 103 | I12: 37374 | J12: 31738 | K12: 0.0044951035 | L12: 0.0032453211 | M12: 41.000714 | N12: 75.62 | O12: 6888.12 | P12: 7788.86 | Q12: 4 | R12: 1 | S12: 0.023809524 | T12: 0.0097087379 | U12: 74150.86 | V12: 12541.52 | W12: 0.092893326 | X12: 0.62104593 | Y12: 10.765036 | Z12: 1.6101869 | AA12: 5
A13: ergoyou | B13: =R13-Q13 -> -5 | C13: 1 | D13: 1.2 | E13: 0.9035 | F13: 0.79886 | G13: 59 | H13: 38 | I13: 1637 | J13: 944 | K13: 0.036041539 | L13: 0.040254237 | M13: 14.088983 | N13: 11.913684 | O13: 831.25 | P13: 452.72 | Q13: 5 | R13: 0 | S13: 0.084745763 | T13: 0 | U13: 64829.66 | V13: 0 | W13: 0.012822063 | X13: 0 | Y13: 77.990568 | Z13: 0 | AA13: 5
A14: sit stand desk electric | B14: =R14-Q14 -> -5 | C14: 2.2 | D14: 1.6666667 | E14: 0.3251 | F14: 0.302 | G14: 178 | H14: 112 | I14: 65959 | J14: 25303 | K14: 0.0026986461 | L14: 0.0044263526 | M14: 51.345337 | N14: 53.620357 | O14: 9139.47 | P14: 6005.48 | Q14: 5 | R14: 0 | S14: 0.028089888 | T14: 0 | U14: 98389.83 | V14: 0 | W14: 0.092890393 | X14: 0 | Y14: 10.765376 | Z14: 0 | AA14: 5
... A113: Grand Total | B113: =R113-Q113 -> -12 | C113: 9.2603661 | D113: 11.132872 | E113: 0.3995709 | F113: 0.36391616 | G113: 13981 | H113: 14792 | I113: 1790080 | J113: 1776198 | K113: 0.0078102655 | L113: 0.0083279004 | M113: 26.885124 | N113: 28.301501 | O113: 375880.92 | P113: 418635.81 | Q113: 139 | R113: 127 | S113: 0.0099420642 | T113: 0.008585722 | U113: 2506936.4 | V113: 2198656.7 | W113: 0.14993636 | X113: 0.19040527 | Y113: 6.6694962 | Z113: 5.2519555 | AA113: 266

Sheet Monthly
A1: Month | B1: Amt Spent | C1: Imp | D1: CTR | E1: Clicks | F1: CPC | G1: Paid Orders | H1: CR | I1: Paid Revenue | J1: Paid ACOS | K1: Paid AOV | L1: ROAS | M1: Total Orders | N1: Total Sale | O1: Total AOV | P1: TACOS | Q1: ROI | R1: Organic Orders | S1: Organic Sale | T1: Organic AOV | U1: Sessions | V1: Session % | W1: Buy Box % | X1: Organic to Paid Orders | Y1: Organic Orders Contribution | Z1: Organic Sales Contribution | AA1: B2b Unit | AB1: B2b Unit
A2: Nov | B2: =SUMIFS('Campaign - Dump'!$Q:$Q,'Campaign - Dump'!$A:$A,Monthly!$A2) -> 163075.05 | C2: =SUMIFS('Campaign - Dump'!$N:$N,'Campaign - Dump'!$A:$A,Monthly!$A2) -> 4056219 | D2: =IFERROR(E2/C2,0) -> 0.0031948472 | E2: =SUMIFS('Campaign - Dump'!$O:$O,'Campaign - Dump'!$A:$A,Monthly!$A2) -> 12959 | F2: =IFERROR(B2/E2,0) -> 12.583922 | G2: =SUMIFS('Campaign - Dump'!$T:$T,'Campaign - Dump'!$A:$A,Monthly!$A2) -> 49 | H2: =IFERROR(G2/E2,0) -> 0.003781156 | I2: =SUMIFS('Campaign - Dump'!$U:$U,'Campaign - Dump'!$A:$A,Monthly!$A2) -> 843788.92 | J2: =IFERROR(B2/I2,0) -> 0.19326522 | K2: =IFERROR(I2/G2,0) -> 17220.182 | L2: =IFERROR(I2/B2,0) -> 5.1742368 | M2: =SUMIFS('Business - Dump'!$W:$W,'Business - Dump'!$A:$A,Monthly!$A2) -> 107 | N2: =SUMIFS('Business - Dump'!$U:$U,'Business - Dump'!$A:$A,Monthly!$A2)/1.18 -> 1838959.3 | O2: =IFERROR(N2/M2,0) -> 17186.536 | P2: =IFERROR(B2/N2,0) -> 0.0886779 | Q2: =IFERROR(N2/B2,0) -> 11.276767 | R2: =IFERROR(M2-G2,0) -> 58 | S2: =IFERROR(N2-I2,0) -> 995170.4 | T2: =IFERROR(S2/R2,0) -> 17158.11 | U2: =SUMIFS('Business - Dump'!$G:$G,'Business - Dump'!$A:$A,Monthly!$A2) -> 24301 | V2: =IFERROR(M2/U2,0) -> 0.004403111 | W2: =AVERAGEIFS('Business - Dump'!$O:$O,'Business - Dump'!$A:$A,Monthly!$A2) -> 0.83806087 | X2: =R2/G2 -> 1.1836735 | Y2: =IFERROR(R2/M2,0) -> 0.54205607 | Z2: =IFERROR(S2/N2,0) -> 0.54115955 | AA2: =SUMIFS('Business - Dump'!$R:$R,'Business - Dump'!$A:$A,Monthly!$A2) -> 8 | AB2: =SUMIFS('Business - Dump'!$V:$V,'Business - Dump'!$A:$A,Monthly!$A2) -> 195598
A3: Dec | B3: =SUMIFS('Campaign - Dump'!$Q:$Q,'Campaign - Dump'!$A:$A,Monthly!$A3) -> 260856.05 | C3: =SUMIFS('Campaign - Dump'!$N:$N,'Campaign - Dump'!$A:$A,Monthly!$A3) -> 4473747 | D3: =IFERROR(E3/C3,0) -> 0.0038187229 | E3: =SUMIFS('Campaign - Dump'!$O:$O,'Campaign - Dump'!$A:$A,Monthly!$A3) -> 17084 | F3: =IFERROR(B3/E3,0) -> 15.269027 | G3: =SUMIFS('Campaign - Dump'!$T:$T,'Campaign - Dump'!$A:$A,Monthly!$A3) -> 140 | H3: =IFERROR(G3/E3,0) -> 0.0081948022 | I3: =SUMIFS('Campaign - Dump'!$U:$U,'Campaign - Dump'!$A:$A,Monthly!$A3) -> 2470927.7 | J3: =IFERROR(B3/I3,0) -> 0.10557009 | K3: =IFERROR(I3/G3,0) -> 17649.484 | L3: =IFERROR(I3/B3,0) -> 9.4723803 | M3: =SUMIFS('Business - Dump'!$W:$W,'Business - Dump'!$A:$A,Monthly!$A3) -> 214 | N3: =SUMIFS('Business - Dump'!$U:$U,'Business - Dump'!$A:$A,Monthly!$A3)/1.18 -> 3610176.3 | O3: =IFERROR(N3/M3,0) -> 16869.983 | P3: =IFERROR(B3/N3,0) -> 0.072255765 | Q3: =IFERROR(N3/B3,0) -> 13.839726 | R3: =IFERROR(M3-G3,0) -> 74 | S3: =IFERROR(N3-I3,0) -> 1139248.6 | T3: =IFERROR(S3/R3,0) -> 15395.251 | U3: =SUMIFS('Business - Dump'!$G:$G,'Business - Dump'!$A:$A,Monthly!$A3) -> 31525 | V3: =IFERROR(M3/U3,0) -> 0.0067882633 | W3: =AVERAGEIFS('Business - Dump'!$O:$O,'Business - Dump'!$A:$A,Monthly!$A3) -> 0.872525 | X3: =R3/G3 -> 0.52857143 | Y3: =IFERROR(R3/M3,0) -> 0.34579439 | Z3: =IFERROR(S3/N3,0) -> 0.31556591 | AA3: =SUMIFS('Business - Dump'!$R:$R,'Business - Dump'!$A:$A,Monthly!$A3) -> 18 | AB3: =SUMIFS('Business - Dump'!$V:$V,'Business - Dump'!$A:$A,Monthly!$A3) -> 396598
A4: Jan | B4: =SUMIFS('Campaign - Dump'!$Q:$Q,'Campaign - Dump'!$A:$A,Monthly!$A4) -> 269951.38 | C4: =SUMIFS('Campaign - Dump'!$N:$N,'Campaign - Dump'!$A:$A,Monthly!$A4) -> 3237665 | D4: =IFERROR(E4/C4,0) -> 0.0041446536 | E4: =SUMIFS('Campaign - Dump'!$O:$O,'Campaign - Dump'!$A:$A,Monthly!$A4) -> 13419 | F4: =IFERROR(B4/E4,0) -> 20.117101 | G4: =SUMIFS('Campaign - Dump'!$T:$T,'Campaign - Dump'!$A:$A,Monthly!$A4) -> 82 | H4: =IFERROR(G4/E4,0) -> 0.0061107385 | I4: =SUMIFS('Campaign - Dump'!$U:$U,'Campaign - Dump'!$A:$A,Monthly!$A4) -> 1526285 | J4: =IFERROR(B4/I4,0) -> 0.17686827 | K4: =IFERROR(I4/G4,0) -> 18613.231 | L4: =IFERROR(I4/B4,0) -> 5.6539255 | M4: =SUMIFS('Business - Dump'!$W:$W,'Business - Dump'!$A:$A,Monthly!$A4) -> 156 | N4: =SUMIFS('Business - Dump'!$U:$U,'Business - Dump'!$A:$A,Monthly!$A4)/1.18 -> 2496815.5 | O4: =IFERROR(N4/M4,0) -> 16005.228 | P4: =IFERROR(B4/N4,0) -> 0.10811827 | Q4: =IFERROR(N4/B4,0) -> 9.2491304 | R4: =IFERROR(M4-G4,0) -> 74 | S4: =IFERROR(N4-I4,0) -> 970530.53 | T4: =IFERROR(S4/R4,0) -> 13115.277 | U4: =SUMIFS('Business - Dump'!$G:$G,'Business - Dump'!$A:$A,Monthly!$A4) -> 26612 | V4: =IFERROR(M4/U4,0) -> 0.0058620171 | W4: =AVERAGEIFS('Business - Dump'!$O:$O,'Business - Dump'!$A:$A,Monthly!$A4) -> 0.8818 | X4: =R4/G4 -> 0.90243902 | Y4: =IFERROR(R4/M4,0) -> 0.47435897 | Z4: =IFERROR(S4/N4,0) -> 0.38870735 | AA4: =SUMIFS('Business - Dump'!$R:$R,'Business - Dump'!$A:$A,Monthly!$A4) -> 16 | AB4: =SUMIFS('Business - Dump'!$V:$V,'Business - Dump'!$A:$A,Monthly!$A4) -> 265894.4
A5: Feb | B5: =SUMIFS('Campaign - Dump'!$Q:$Q,'Campaign - Dump'!$A:$A,Monthly!$A5) -> 363205.24 | C5: =SUMIFS('Campaign - Dump'!$N:$N,'Campaign - Dump'!$A:$A,Monthly!$A5) -> 3415714 | D5: =IFERROR(E5/C5,0) -> 0.0046774993 | E5: =SUMIFS('Campaign - Dump'!$O:$O,'Campaign - Dump'!$A:$A,Monthly!$A5) -> 15977 | F5: =IFERROR(B5/E5,0) -> 22.733006 | G5: =SUMIFS('Campaign - Dump'!$T:$T,'Campaign - Dump'!$A:$A,Monthly!$A5) -> 123 | H5: =IFERROR(G5/E5,0) -> 0.0076985667 | I5: =SUMIFS('Campaign - Dump'!$U:$U,'Campaign - Dump'!$A:$A,Monthly!$A5) -> 2203105.7 | J5: =IFERROR(B5/I5,0) -> 0.16486056 | K5: =IFERROR(I5/G5,0) -> 17911.429 | L5: =IFERROR(I5/B5,0) -> 6.0657322 | M5: =SUMIFS('Business - Dump'!$W:$W,'Business - Dump'!$A:$A,Monthly!$A5) -> 228 | N5: =SUMIFS('Business - Dump'!$U:$U,'Business - Dump'!$A:$A,Monthly!$A5)/1.18 -> 3525611.6 | O5: =IFERROR(N5/M5,0) -> 15463.209 | P5: =IFERROR(B5/N5,0) -> 0.10301907 | Q5: =IFERROR(N5/B5,0) -> 9.7069404 | R5: =IFERROR(M5-G5,0) -> 105 | S5: =IFERROR(N5-I5,0) -> 1322505.9 | T5: =IFERROR(S5/R5,0) -> 12595.294 | U5: =SUMIFS('Business - Dump'!$G:$G,'Business - Dump'!$A:$A,Monthly!$A5) -> 31719 | V5: =IFERROR(M5/U5,0) -> 0.0071881207 | W5: =AVERAGEIFS('Business - Dump'!$O:$O,'Business - Dump'!$A:$A,Monthly!$A5) -> 0.88219459 | X5: =R5/G5 -> 0.85365854 | Y5: =IFERROR(R5/M5,0) -> 0.46052632 | Z5: =IFERROR(S5/N5,0) -> 0.37511389 | AA5: =SUMIFS('Business - Dump'!$R:$R,'Business - Dump'!$A:$A,Monthly!$A5) -> 17 | AB5: =SUMIFS('Business - Dump'!$V:$V,'Business - Dump'!$A:$A,Monthly!$A5) -> 369473.29
A6: Mar | B6: =SUMIFS('Campaign - Dump'!$Q:$Q,'Campaign - Dump'!$A:$A,Monthly!$A6) -> 554591.97 | C6: =SUMIFS('Campaign - Dump'!$N:$N,'Campaign - Dump'!$A:$A,Monthly!$A6) -> 5184404 | D6: =IFERROR(E6/C6,0) -> 0.0047162605 | E6: =SUMIFS('Campaign - Dump'!$O:$O,'Campaign - Dump'!$A:$A,Monthly!$A6) -> 24451 | F6: =IFERROR(B6/E6,0) -> 22.68177 | G6: =SUMIFS('Campaign - Dump'!$T:$T,'Campaign - Dump'!$A:$A,Monthly!$A6) -> 196 | H6: =IFERROR(G6/E6,0) -> 0.0080160321 | I6: =SUMIFS('Campaign - Dump'!$U:$U,'Campaign - Dump'!$A:$A,Monthly!$A6) -> 3582316.4 | J6: =IFERROR(B6/I6,0) -> 0.15481379 | K6: =IFERROR(I6/G6,0) -> 18277.124 | L6: =IFERROR(I6/B6,0) -> 6.459373 | M6: =SUMIFS('Business - Dump'!$W:$W,'Business - Dump'!$A:$A,Monthly!$A6) -> 307 | N6: =SUMIFS('Business - Dump'!$U:$U,'Business - Dump'!$A:$A,Monthly!$A6)/1.18 -> 5105004 | O6: =IFERROR(N6/M6,0) -> 16628.678 | P6: =IFERROR(B6/N6,0) -> 0.10863693 | Q6: =IFERROR(N6/B6,0) -> 9.2049728 | R6: =IFERROR(M6-G6,0) -> 111 | S6: =IFERROR(N6-I6,0) -> 1522687.6 | T6: =IFERROR(S6/R6,0) -> 13717.906 | U6: =SUMIFS('Business - Dump'!$G:$G,'Business - Dump'!$A:$A,Monthly!$A6) -> 44385 | V6: =IFERROR(M6/U6,0) -> 0.0069167512 | W6: =AVERAGEIFS('Business - Dump'!$O:$O,'Business - Dump'!$A:$A,Monthly!$A6) -> 0.89423729 | X6: =R6/G6 -> 0.56632653 | Y6: =IFERROR(R6/M6,0) -> 0.36156352 | Z6: =IFERROR(S6/N6,0) -> 0.29827354 | AA6: =SUMIFS('Business - Dump'!$R:$R,'Business - Dump'!$A:$A,Monthly!$A6) -> 44 | AB6: =SUMIFS('Business - Dump'!$V:$V,'Business - Dump'!$A:$A,Monthly!$A6) -> 750380.73
A7: Apr | B7: =SUMIFS('Campaign - Dump'!$Q:$Q,'Campaign - Dump'!$A:$A,Monthly!$A7) -> 636539.97 | C7: =SUMIFS('Campaign - Dump'!$N:$N,'Campaign - Dump'!$A:$A,Monthly!$A7) -> 5671901 | D7: =IFERROR(E7/C7,0) -> 0.0044567068 | E7: =SUMIFS('Campaign - Dump'!$O:$O,'Campaign - Dump'!$A:$A,Monthly!$A7) -> 25278 | F7: =IFERROR(B7/E7,0) -> 25.18158 | G7: =SUMIFS('Campaign - Dump'!$T:$T,'Campaign - Dump'!$A:$A,Monthly!$A7) -> 192 | H7: =IFERROR(G7/E7,0) -> 0.0075955376 | I7: =SUMIFS('Campaign - Dump'!$U:$U,'Campaign - Dump'!$A:$A,Monthly!$A7) -> 3539616 | J7: =IFERROR(B7/I7,0) -> 0.17983306 | K7: =IFERROR(I7/G7,0) -> 18435.5 | L7: =IFERROR(I7/B7,0) -> 5.5607128 | M7: =SUMIFS('Business - Dump'!$W:$W,'Business - Dump'!$A:$A,Monthly!$A7) -> 280 | N7: =SUMIFS('Business - Dump'!$U:$U,'Business - Dump'!$A:$A,Monthly!$A7)/1.18 -> 4575649.8 | O7: =IFERROR(N7/M7,0) -> 16341.607 | P7: =IFERROR(B7/N7,0) -> 0.13911466 | Q7: =IFERROR(N7/B7,0) -> 7.1883151 | R7: =IFERROR(M7-G7,0) -> 88 | S7: =IFERROR(N7-I7,0) -> 1036033.9 | T7: =IFERROR(S7/R7,0) -> 11773.112 | U7: =SUMIFS('Business - Dump'!$G:$G,'Business - Dump'!$A:$A,Monthly!$A7) -> 46985 | V7: =IFERROR(M7/U7,0) -> 0.0059593487 | W7: =AVERAGEIFS('Business - Dump'!$O:$O,'Business - Dump'!$A:$A,Monthly!$A7) -> 0.87324717 | X7: =R7/G7 -> 0.45833333 | Y7: =IFERROR(R7/M7,0) -> 0.31428571 | Z7: =IFERROR(S7/N7,0) -> 0.22642333 | AA7: =SUMIFS('Business - Dump'!$R:$R,'Business - Dump'!$A:$A,Monthly!$A7) -> 40 | AB7: =SUMIFS('Business - Dump'!$V:$V,'Business - Dump'!$A:$A,Monthly!$A7) -> 838656.66
A8: May | B8: =SUMIFS('Campaign - Dump'!$Q:$Q,'Campaign - Dump'!$A:$A,Monthly!$A8) -> 915205.63 | C8: =SUMIFS('Campaign - Dump'!$N:$N,'Campaign - Dump'!$A:$A,Monthly!$A8) -> 6851490 | D8: =IFERROR(E8/C8,0) -> 0.0042012759 | E8: =SUMIFS('Campaign - Dump'!$O:$O,'Campaign - Dump'!$A:$A,Monthly!$A8) -> 28785 | F8: =IFERROR(B8/E8,0) -> 31.794533 | G8: =SUMIFS('Campaign - Dump'!$T:$T,'Campaign - Dump'!$A:$A,Monthly!$A8) -> 286 | H8: =IFERROR(G8/E8,0) -> 0.0099357304 | I8: =SUMIFS('Campaign - Dump'!$U:$U,'Campaign - Dump'!$A:$A,Monthly!$A8) -> 5240245.7 | J8: =IFERROR(B8/I8,0) -> 0.17464937 | K8: =IFERROR(I8/G8,0) -> 18322.538 | L8: =IFERROR(I8/B8,0) -> 5.7257578 | M8: =SUMIFS('Business - Dump'!$W:$W,'Business - Dump'!$A:$A,Monthly!$A8) -> 390 | N8: =SUMIFS('Business - Dump'!$U:$U,'Business - Dump'!$A:$A,Monthly!$A8)/1.18 -> 6681635.1 | O8: =IFERROR(N8/M8,0) -> 17132.398 | P8: =IFERROR(B8/N8,0) -> 0.1369733 | Q8: =IFERROR(N8/B8,0) -> 7.3006927 | R8: =IFERROR(M8-G8,0) -> 104 | S8: =IFERROR(N8-I8,0) -> 1441389.3 | T8: =IFERROR(S8/R8,0) -> 13859.513 | U8: =SUMIFS('Business - Dump'!$G:$G,'Business - Dump'!$A:$A,Monthly!$A8) -> 70627 | V8: =IFERROR(M8/U8,0) -> 0.0055219675 | W8: =AVERAGEIFS('Business - Dump'!$O:$O,'Business - Dump'!$A:$A,Monthly!$A8) -> 0.87631429 | X8: =R8/G8 -> 0.36363636 | Y8: =IFERROR(R8/M8,0) -> 0.26666667 | Z8: =IFERROR(S8/N8,0) -> 0.21572404 | AA8: =SUMIFS('Business - Dump'!$R:$R,'Business - Dump'!$A:$A,Monthly!$A8) -> 39 | AB8: =SUMIFS('Business - Dump'!$V:$V,'Business - Dump'!$A:$A,Monthly!$A8) -> 881601.36
A9: June | B9: =SUMIFS('Campaign - Dump'!$Q:$Q,'Campaign - Dump'!$A:$A,Monthly!$A9) -> 712488.04 | C9: =SUMIFS('Campaign - Dump'!$N:$N,'Campaign - Dump'!$A:$A,Monthly!$A9) -> 7449125 | D9: =IFERROR(E9/C9,0) -> 0.0035045727 | E9: =SUMIFS('Campaign - Dump'!$O:$O,'Campaign - Dump'!$A:$A,Monthly!$A9) -> 26106 | F9: =IFERROR(B9/E9,0) -> 27.292118 | G9: =SUMIFS('Campaign - Dump'!$T:$T,'Campaign - Dump'!$A:$A,Monthly!$A9) -> 220 | H9: =IFERROR(G9/E9,0) -> 0.0084271815 | I9: =SUMIFS('Campaign - Dump'!$U:$U,'Campaign - Dump'!$A:$A,Monthly!$A9) -> 3790348 | J9: =IFERROR(B9/I9,0) -> 0.18797431 | K9: =IFERROR(I9/G9,0) -> 17228.855 | L9: =IFERROR(I9/B9,0) -> 5.319876 | M9: =SUMIFS('Business - Dump'!$W:$W,'Business - Dump'!$A:$A,Monthly!$A9) -> 313 | N9: =SUMIFS('Business - Dump'!$U:$U,'Business - Dump'!$A:$A,Monthly!$A9)/1.18 -> 5290499 | O9: =IFERROR(N9/M9,0) -> 16902.553 | P9: =IFERROR(B9/N9,0) -> 0.13467313 | Q9: =IFERROR(N9/B9,0) -> 7.4253865 | R9: =IFERROR(M9-G9,0) -> 93 | S9: =IFERROR(N9-I9,0) -> 1500151 | T9: =IFERROR(S9/R9,0) -> 16130.656 | U9: =SUMIFS('Business - Dump'!$G:$G,'Business - Dump'!$A:$A,Monthly!$A9) -> 61268 | V9: =IFERROR(M9/U9,0) -> 0.0051087027 | W9: =AVERAGEIFS('Business - Dump'!$O:$O,'Business - Dump'!$A:$A,Monthly!$A9) -> 0.89095385 | X9: =R9/G9 -> 0.42272727 | Y9: =IFERROR(R9/M9,0) -> 0.2971246 | Z9: =IFERROR(S9/N9,0) -> 0.28355567 | AA9: =SUMIFS('Business - Dump'!$R:$R,'Business - Dump'!$A:$A,Monthly!$A9) -> 33 | AB9: =SUMIFS('Business - Dump'!$V:$V,'Business - Dump'!$A:$A,Monthly!$A9) -> 745221.97
A10: July | B10: =SUMIFS('Campaign - Dump'!$Q:$Q,'Campaign - Dump'!$A:$A,Monthly!$A10) -> 868070.3 | C10: =SUMIFS('Campaign - Dump'!$N:$N,'Campaign - Dump'!$A:$A,Monthly!$A10) -> 8194079 | D10: =IFERROR(E10/C10,0) -> 0.0035996724 | E10: =SUMIFS('Campaign - Dump'!$O:$O,'Campaign - Dump'!$A:$A,Monthly!$A10) -> 29496 | F10: =IFERROR(B10/E10,0) -> 29.430102 | G10: =SUMIFS('Campaign - Dump'!$T:$T,'Campaign - Dump'!$A:$A,Monthly!$A10) -> 279 | H10: =IFERROR(G10/E10,0) -> 0.0094589097 | I10: =SUMIFS('Campaign - Dump'!$U:$U,'Campaign - Dump'!$A:$A,Monthly!$A10) -> 5182218.6 | J10: =IFERROR(B10/I10,0) -> 0.16750939 | K10: =IFERROR(I10/G10,0) -> 18574.26 | L10: =IFERROR(I10/B10,0) -> 5.9698145 | M10: =SUMIFS('Business - Dump'!$W:$W,'Business - Dump'!$A:$A,Monthly!$A10) -> 411 | N10: =SUMIFS('Business - Dump'!$U:$U,'Business - Dump'!$A:$A,Monthly!$A10)/1.18 -> 7060713 | O10: =IFERROR(N10/M10,0) -> 17179.35 | P10: =IFERROR(B10/N10,0) -> 0.12294372 | Q10: =IFERROR(N10/B10,0) -> 8.1338033 | R10: =IFERROR(M10-G10,0) -> 132 | S10: =IFERROR(N10-I10,0) -> 1878494.4 | T10: =IFERROR(S10/R10,0) -> 14231.018 | U10: =SUMIFS('Business - Dump'!$G:$G,'Business - Dump'!$A:$A,Monthly!$A10) -> 65802 | V10: =IFERROR(M10/U10,0) -> 0.0062460108 | W10: =AVERAGEIFS('Business - Dump'!$O:$O,'Business - Dump'!$A:$A,Monthly!$A10) -> 0.83938409 | X10: =R10/G10 -> 0.47311828 | Y10: =IFERROR(R10/M10,0) -> 0.32116788 | Z10: =IFERROR(S10/N10,0) -> 0.26604882 | AA10: =SUMIFS('Business - Dump'!$R:$R,'Business - Dump'!$A:$A,Monthly!$A10) -> 31 | AB10: =SUMIFS('Business - Dump'!$V:$V,'Business - Dump'!$A:$A,Monthly!$A10) -> 623427.68
A11: August | B11: =SUMIFS('Campaign - Dump'!$Q:$Q,'Campaign - Dump'!$A:$A,Monthly!$A11) -> 831575.61 | C11: =SUMIFS('Campaign - Dump'!$N:$N,'Campaign - Dump'!$A:$A,Monthly!$A11) -> 7860313 | D11: =IFERROR(E11/C11,0) -> 0.0040125629 | E11: =SUMIFS('Campaign - Dump'!$O:$O,'Campaign - Dump'!$A:$A,Monthly!$A11) -> 31540 | F11: =IFERROR(B11/E11,0) -> 26.365745 | G11: =SUMIFS('Campaign - Dump'!$T:$T,'Campaign - Dump'!$A:$A,Monthly!$A11) -> 228 | H11: =IFERROR(G11/E11,0) -> 0.0072289157 | I11: =SUMIFS('Campaign - Dump'!$U:$U,'Campaign - Dump'!$A:$A,Monthly!$A11) -> 3896020.5 | J11: =IFERROR(B11/I11,0) -> 0.21344231 | K11: =IFERROR(I11/G11,0) -> 17087.809 | L11: =IFERROR(I11/B11,0) -> 4.6851068 | M11: =SUMIFS('Business - Dump'!$W:$W,'Business - Dump'!$A:$A,Monthly!$A11) -> 386 | N11: =SUMIFS('Business - Dump'!$U:$U,'Business - Dump'!$A:$A,Monthly!$A11)/1.18 -> 5948601.1 | O11: =IFERROR(N11/M11,0) -> 15410.884 | P11: =IFERROR(B11/N11,0) -> 0.13979347 | Q11: =IFERROR(N11/B11,0) -> 7.1534097 | R11: =IFERROR(M11-G11,0) -> 158 | S11: =IFERROR(N11-I11,0) -> 2052580.5 | T11: =IFERROR(S11/R11,0) -> 12991.016 | U11: =SUMIFS('Business - Dump'!$G:$G,'Business - Dump'!$A:$A,Monthly!$A11) -> 69611 | V11: =IFERROR(M11/U11,0) -> 0.0055451006 | W11: =AVERAGEIFS('Business - Dump'!$O:$O,'Business - Dump'!$A:$A,Monthly!$A11) -> 0.85197889 | X11: =R11/G11 -> 0.69298246 | Y11: =IFERROR(R11/M11,0) -> 0.40932642 | Z11: =IFERROR(S11/N11,0) -> 0.34505264 | AA11: =SUMIFS('Business - Dump'!$R:$R,'Business - Dump'!$A:$A,Monthly!$A11) -> 25 | AB11: =SUMIFS('Business - Dump'!$V:$V,'Business - Dump'!$A:$A,Monthly!$A11) -> 522851.94
A12: September | B12: =SUMIFS('Campaign - Dump'!$Q:$Q,'Campaign - Dump'!$A:$A,Monthly!$A12) -> 1390822.2 | C12: =SUMIFS('Campaign - Dump'!$N:$N,'Campaign - Dump'!$A:$A,Monthly!$A12) -> 14814452 | D12: =IFERROR(E12/C12,0) -> 0.0037431017 | E12: =SUMIFS('Campaign - Dump'!$O:$O,'Campaign - Dump'!$A:$A,Monthly!$A12) -> 55452 | F12: =IFERROR(B12/E12,0) -> 25.081552 | G12: =SUMIFS('Campaign - Dump'!$T:$T,'Campaign - Dump'!$A:$A,Monthly!$A12) -> 480 | H12: =IFERROR(G12/E12,0) -> 0.008656135 | I12: =SUMIFS('Campaign - Dump'!$U:$U,'Campaign - Dump'!$A:$A,Monthly!$A12) -> 7678468.1 | J12: =IFERROR(B12/I12,0) -> 0.18113277 | K12: =IFERROR(I12/G12,0) -> 15996.809 | L12: =IFERROR(I12/B12,0) -> 5.5208121 | M12: =SUMIFS('Business - Dump'!$W:$W,'Business - Dump'!$A:$A,Monthly!$A12) -> 683 | N12: =SUMIFS('Business - Dump'!$U:$U,'Business - Dump'!$A:$A,Monthly!$A12)/1.18 -> 10270914 | O12: =IFERROR(N12/M12,0) -> 15037.941 | P12: =IFERROR(B12/N12,0) -> 0.13541368 | Q12: =IFERROR(N12/B12,0) -> 7.3847784 | R12: =IFERROR(M12-G12,0) -> 203 | S12: =IFERROR(N12-I12,0) -> 2592445.8 | T12: =IFERROR(S12/R12,0) -> 12770.669 | U12: =SUMIFS('Business - Dump'!$G:$G,'Business - Dump'!$A:$A,Monthly!$A12) -> 92124 | V12: =IFERROR(M12/U12,0) -> 0.0074139204 | W12: =AVERAGEIFS('Business - Dump'!$O:$O,'Business - Dump'!$A:$A,Monthly!$A12) -> 0.89220123 | X12: =R12/G12 -> 0.42291667 | Y12: =IFERROR(R12/M12,0) -> 0.29721816 | Z12: =IFERROR(S12/N12,0) -> 0.25240654 | AA12: =SUMIFS('Business - Dump'!$R:$R,'Business - Dump'!$A:$A,Monthly!$A12) -> 54 | AB12: =SUMIFS('Business - Dump'!$V:$V,'Business - Dump'!$A:$A,Monthly!$A12) -> 940608.38
A13: October | B13: =SUMIFS('Campaign - Dump'!$Q:$Q,'Campaign - Dump'!$A:$A,Monthly!$A13) -> 1281599.9 | C13: =SUMIFS('Campaign - Dump'!$N:$N,'Campaign - Dump'!$A:$A,Monthly!$A13) -> 8094986 | D13: =IFERROR(E13/C13,0) -> 0.0036366956 | E13: =SUMIFS('Campaign - Dump'!$O:$O,'Campaign - Dump'!$A:$A,Monthly!$A13) -> 29439 | F13: =IFERROR(B13/E13,0) -> 43.534084 | G13: =SUMIFS('Campaign - Dump'!$T:$T,'Campaign - Dump'!$A:$A,Monthly!$A13) -> 348 | H13: =IFERROR(G13/E13,0) -> 0.011821054 | I13: =SUMIFS('Campaign - Dump'!$U:$U,'Campaign - Dump'!$A:$A,Monthly!$A13) -> 5884150.9 | J13: =IFERROR(B13/I13,0) -> 0.21780541 | K13: =IFERROR(I13/G13,0) -> 16908.48 | L13: =IFERROR(I13/B13,0) -> 4.5912542 | M13: =SUMIFS('Business - Dump'!$W:$W,'Business - Dump'!$A:$A,Monthly!$A13) -> 590 | N13: =SUMIFS('Business - Dump'!$U:$U,'Business - Dump'!$A:$A,Monthly!$A13)/1.18 -> 8563706.4 | O13: =IFERROR(N13/M13,0) -> 14514.757 | P13: =IFERROR(B13/N13,0) -> 0.14965481 | Q13: =IFERROR(N13/B13,0) -> 6.6820437 | R13: =IFERROR(M13-G13,0) -> 242 | S13: =IFERROR(N13-I13,0) -> 2679555.5 | T13: =IFERROR(S13/R13,0) -> 11072.543 | U13: =SUMIFS('Business - Dump'!$G:$G,'Business - Dump'!$A:$A,Monthly!$A13) -> 72627 | V13: =IFERROR(M13/U13,0) -> 0.0081237006 | W13: =AVERAGEIFS('Business - Dump'!$O:$O,'Business - Dump'!$A:$A,Monthly!$A13) -> 0.86028936 | X13: =R13/G13 -> 0.6954023 | Y13: =IFERROR(R13/M13,0) -> 0.41016949 | Z13: =IFERROR(S13/N13,0) -> 0.3128967 | AA13: =SUMIFS('Business - Dump'!$R:$R,'Business - Dump'!$A:$A,Monthly!$A13) -> 34 | AB13: =SUMIFS('Business - Dump'!$V:$V,'Business - Dump'!$A:$A,Monthly!$A13) -> 548954.95
... A15: December | B15: =SUMIFS('Campaign - Dump'!$Q:$Q,'Campaign - Dump'!$A:$A,Monthly!$A15) -> 660076.26 | C15: =SUMIFS('Campaign - Dump'!$N:$N,'Campaign - Dump'!$A:$A,Monthly!$A15) -> 7845997 | D15: =IFERROR(E15/C15,0) -> 0.0046747405 | E15: =SUMIFS('Campaign - Dump'!$O:$O,'Campaign - Dump'!$A:$A,Monthly!$A15) -> 36678 | F15: =IFERROR(B15/E15,0) -> 17.996517 | G15: =SUMIFS('Campaign - Dump'!$T:$T,'Campaign - Dump'!$A:$A,Monthly!$A15) -> 301 | H15: =IFERROR(G15/E15,0) -> 0.0082065543 | I15: =SUMIFS('Campaign - Dump'!$U:$U,'Campaign - Dump'!$A:$A,Monthly!$A15) -> 2744575.4 | J15: =IFERROR(B15/I15,0) -> 0.24050214 | K15: =IFERROR(I15/G15,0) -> 9118.1908 | L15: =IFERROR(I15/B15,0) -> 4.1579672 | M15: =SUMIFS('Business - Dump'!$W:$W,'Business - Dump'!$A:$A,Monthly!$A15) -> 471 | N15: =SUMIFS('Business - Dump'!$U:$U,'Business - Dump'!$A:$A,Monthly!$A15)/1.18 -> 4159256 | O15: =IFERROR(N15/M15,0) -> 8830.6921 | P15: =IFERROR(B15/N15,0) -> 0.15870056 | Q15: =IFERROR(N15/B15,0) -> 6.301175 | R15: =IFERROR(M15-G15,0) -> 170 | S15: =IFERROR(N15-I15,0) -> 1414680.6 | T15: =IFERROR(S15/R15,0) -> 8321.6504 | U15: =SUMIFS('Business - Dump'!$G:$G,'Business - Dump'!$A:$A,Monthly!$A15) -> 68314 | V15: =IFERROR(M15/U15,0) -> 0.0068946336 | W15: =AVERAGEIFS('Business - Dump'!$O:$O,'Business - Dump'!$A:$A,Monthly!$A15) -> 0.88491684 | X15: =R15/G15 -> 0.56478405 | Y15: =IFERROR(R15/M15,0) -> 0.36093418 | Z15: =IFERROR(S15/N15,0) -> 0.34012827 | AA15: =SUMIFS('Business - Dump'!$R:$R,'Business - Dump'!$A:$A,Monthly!$A15) -> 35 | AB15: =SUMIFS('Business - Dump'!$V:$V,'Business - Dump'!$A:$A,Monthly!$A15) -> 473397.68
A16: 45658 | B16: =SUMIFS('Campaign - Dump'!$Q:$Q,'Campaign - Dump'!$A:$A,Monthly!$A16) -> 743314.92 | C16: =SUMIFS('Campaign - Dump'!$N:$N,'Campaign - Dump'!$A:$A,Monthly!$A16) -> 6106324 | D16: =IFERROR(E16/C16,0) -> 0.0051885553 | E16: =SUMIFS('Campaign - Dump'!$O:$O,'Campaign - Dump'!$A:$A,Monthly!$A16) -> 31683 | F16: =IFERROR(B16/E16,0) -> 23.461002 | G16: =SUMIFS('Campaign - Dump'!$T:$T,'Campaign - Dump'!$A:$A,Monthly!$A16) -> 292 | H16: =IFERROR(G16/E16,0) -> 0.009216299 | I16: =SUMIFS('Campaign - Dump'!$U:$U,'Campaign - Dump'!$A:$A,Monthly!$A16) -> 3410399.2 | J16: =IFERROR(B16/I16,0) -> 0.2179554 | K16: =IFERROR(I16/G16,0) -> 11679.449 | L16: =IFERROR(I16/B16,0) -> 4.5880946 | M16: =SUMIFS('Business - Dump'!$W:$W,'Business - Dump'!$A:$A,Monthly!$A16) -> 428 | N16: =SUMIFS('Business - Dump'!$U:$U,'Business - Dump'!$A:$A,Monthly!$A16)/1.18 -> 5082627.8 | O16: =IFERROR(N16/M16,0) -> 11875.299 | P16: =IFERROR(B16/N16,0) -> 0.14624618 | Q16: =IFERROR(N16/B16,0) -> 6.8377852 | R16: =IFERROR(M16-G16,0) -> 136 | S16: =IFERROR(N16-I16,0) -> 1672228.6 | T16: =IFERROR(S16/R16,0) -> 12295.799 | U16: =SUMIFS('Business - Dump'!$G:$G,'Business - Dump'!$A:$A,Monthly!$A16) -> 59954 | V16: =IFERROR(M16/U16,0) -> 0.0071388064 | W16: =AVERAGEIFS('Business - Dump'!$O:$O,'Business - Dump'!$A:$A,Monthly!$A16) -> 0.88701348 | X16: =R16/G16 -> 0.46575342 | Y16: =IFERROR(R16/M16,0) -> 0.31775701 | Z16: =IFERROR(S16/N16,0) -> 0.32900867 | AA16: =SUMIFS('Business - Dump'!$R:$R,'Business - Dump'!$A:$A,Monthly!$A16) -> 50 | AB16: =SUMIFS('Business - Dump'!$V:$V,'Business - Dump'!$A:$A,Monthly!$A16) -> 563631.61
A17: 45689 | B17: =SUMIFS('Campaign - Dump'!$Q:$Q,'Campaign - Dump'!$A:$A,Monthly!$A17) -> 645642.5 | C17: =SUMIFS('Campaign - Dump'!$N:$N,'Campaign - Dump'!$A:$A,Monthly!$A17) -> 6128191 | D17: =IFERROR(E17/C17,0) -> 0.0051989241 | E17: =SUMIFS('Campaign - Dump'!$O:$O,'Campaign - Dump'!$A:$A,Monthly!$A17) -> 31860 | F17: =IFERROR(B17/E17,0) -> 20.264987 | G17: =SUMIFS('Campaign - Dump'!$T:$T,'Campaign - Dump'!$A:$A,Monthly!$A17) -> 345 | H17: =IFERROR(G17/E17,0) -> 0.010828625 | I17: =SUMIFS('Campaign - Dump'!$U:$U,'Campaign - Dump'!$A:$A,Monthly!$A17) -> 2448692.5 | J17: =IFERROR(B17/I17,0) -> 0.26366827 | K17: =IFERROR(I17/G17,0) -> 7097.6594 | L17: =IFERROR(I17/B17,0) -> 3.7926445 | M17: =SUMIFS('Business - Dump'!$W:$W,'Business - Dump'!$A:$A,Monthly!$A17) -> 478 | N17: =SUMIFS('Business - Dump'!$U:$U,'Business - Dump'!$A:$A,Monthly!$A17)/1.18 -> 3545813 | O17: =IFERROR(N17/M17,0) -> 7418.0188 | P17: =IFERROR(B17/N17,0) -> 0.18208589 | Q17: =IFERROR(N17/B17,0) -> 5.4919138 | R17: =IFERROR(M17-G17,0) -> 133 | S17: =IFERROR(N17-I17,0) -> 1097120.5 | T17: =IFERROR(S17/R17,0) -> 8249.0262 | U17: =SUMIFS('Business - Dump'!$G:$G,'Business - Dump'!$A:$A,Monthly!$A17) -> 59264 | V17: =IFERROR(M17/U17,0) -> 0.0080656048 | W17: =AVERAGEIFS('Business - Dump'!$O:$O,'Business - Dump'!$A:$A,Monthly!$A17) -> 0.89536705 | X17: =R17/G17 -> 0.38550725 | Y17: =IFERROR(R17/M17,0) -> 0.27824268 | Z17: =IFERROR(S17/N17,0) -> 0.30941296 | AA17: =SUMIFS('Business - Dump'!$R:$R,'Business - Dump'!$A:$A,Monthly!$A17) -> 54 | AB17: =SUMIFS('Business - Dump'!$V:$V,'Business - Dump'!$A:$A,Monthly!$A17) -> 541480.81
A18: 45717 | B18: =SUMIFS('Campaign - Dump'!$Q:$Q,'Campaign - Dump'!$A:$A,Monthly!$A18) -> 845513.7 | C18: =SUMIFS('Campaign - Dump'!$N:$N,'Campaign - Dump'!$A:$A,Monthly!$A18) -> 11643879 | D18: =IFERROR(E18/C18,0) -> 0.0044048895 | E18: =SUMIFS('Campaign - Dump'!$O:$O,'Campaign - Dump'!$A:$A,Monthly!$A18) -> 51290 | F18: =IFERROR(B18/E18,0) -> 16.484962 | G18: =SUMIFS('Campaign - Dump'!$T:$T,'Campaign - Dump'!$A:$A,Monthly!$A18) -> 458 | H18: =IFERROR(G18/E18,0) -> 0.0089296159 | I18: =SUMIFS('Campaign - Dump'!$U:$U,'Campaign - Dump'!$A:$A,Monthly!$A18) -> 3495437.8 | J18: =IFERROR(B18/I18,0) -> 0.24189064 | K18: =IFERROR(I18/G18,0) -> 7631.9603 | L18: =IFERROR(I18/B18,0) -> 4.1340995 | M18: =SUMIFS('Business - Dump'!$W:$W,'Business - Dump'!$A:$A,Monthly!$A18) -> 626 | N18: =SUMIFS('Business - Dump'!$U:$U,'Business - Dump'!$A:$A,Monthly!$A18)/1.18 -> 5083935.1 | O18: =IFERROR(N18/M18,0) -> 8121.3021 | P18: =IFERROR(B18/N18,0) -> 0.16631088 | Q18: =IFERROR(N18/B18,0) -> 6.0128359 | R18: =IFERROR(M18-G18,0) -> 168 | S18: =IFERROR(N18-I18,0) -> 1588497.3 | T18: =IFERROR(S18/R18,0) -> 9455.341 | U18: =SUMIFS('Business - Dump'!$G:$G,'Business - Dump'!$A:$A,Monthly!$A18) -> 76596 | V18: =IFERROR(M18/U18,0) -> 0.0081727505 | W18: =AVERAGEIFS('Business - Dump'!$O:$O,'Business - Dump'!$A:$A,Monthly!$A18) -> 0.88509149 | X18: =R18/G18 -> 0.36681223 | Y18: =IFERROR(R18/M18,0) -> 0.26837061 | Z18: =IFERROR(S18/N18,0) -> 0.31245428 | AA18: =SUMIFS('Business - Dump'!$R:$R,'Business - Dump'!$A:$A,Monthly!$A18) -> 49 | AB18: =SUMIFS('Business - Dump'!$V:$V,'Business - Dump'!$A:$A,Monthly!$A18) -> 571076.99
A19: 45772 | B19: =SUMIFS('Campaign - Dump'!$Q:$Q,'Campaign - Dump'!$A:$A,Monthly!$A19) -> 733459.69 | C19: =SUMIFS('Campaign - Dump'!$N:$N,'Campaign - Dump'!$A:$A,Monthly!$A19) -> 9553651 | D19: =IFERROR(E19/C19,0) -> 0.004356345 | E19: =SUMIFS('Campaign - Dump'!$O:$O,'Campaign - Dump'!$A:$A,Monthly!$A19) -> 41619 | F19: =IFERROR(B19/E19,0) -> 17.623193 | G19: =SUMIFS('Campaign - Dump'!$T:$T,'Campaign - Dump'!$A:$A,Monthly!$A19) -> 285 | H19: =IFERROR(G19/E19,0) -> 0.0068478339 | I19: =SUMIFS('Campaign - Dump'!$U:$U,'Campaign - Dump'!$A:$A,Monthly!$A19) -> 2820948.6 | J19: =IFERROR(B19/I19,0) -> 0.26000463 | K19: =IFERROR(I19/G19,0) -> 9898.0651 | L19: =IFERROR(I19/B19,0) -> 3.8460853 | M19: =SUMIFS('Business - Dump'!$W:$W,'Business - Dump'!$A:$A,Monthly!$A19) -> 433 | N19: =SUMIFS('Business - Dump'!$U:$U,'Business - Dump'!$A:$A,Monthly!$A19)/1.18 -> 4434956.3 | O19: =IFERROR(N19/M19,0) -> 10242.393 | P19: =IFERROR(B19/N19,0) -> 0.16538149 | Q19: =IFERROR(N19/B19,0) -> 6.0466258 | R19: =IFERROR(M19-G19,0) -> 148 | S19: =IFERROR(N19-I19,0) -> 1614007.8 | T19: =IFERROR(S19/R19,0) -> 10905.458 | U19: =SUMIFS('Business - Dump'!$G:$G,'Business - Dump'!$A:$A,Monthly!$A19) -> 65083 | V19: =IFERROR(M19/U19,0) -> 0.006653043 | W19: =AVERAGEIFS('Business - Dump'!$O:$O,'Business - Dump'!$A:$A,Monthly!$A19) -> 0.88995604 | X19: =R19/G19 -> 0.51929825 | Y19: =IFERROR(R19/M19,0) -> 0.34180139 | Z19: =IFERROR(S19/N19,0) -> 0.36392867 | AA19: =SUMIFS('Business - Dump'!$R:$R,'Business - Dump'!$A:$A,Monthly!$A19) -> 41 | AB19: =SUMIFS('Business - Dump'!$V:$V,'Business - Dump'!$A:$A,Monthly!$A19) -> 633049.26
A20: ='Portfolio Wise '!A470 -> 25_May | B20: ='Portfolio Wise '!F470 -> 900000 | C20: ='Portfolio Wise '!C470 -> 11739457 | D20: ='Portfolio Wise '!E470 -> 0.0042133451 | E20: ='Portfolio Wise '!D470 -> 49462.385 | F20: ='Portfolio Wise '!G470 -> 18.195645 | G20: ='Portfolio Wise '!H470 -> 351.28683 | H20: ='Portfolio Wise '!I470 -> 0.0071021006 | I20: ='Portfolio Wise '!J470 -> 3484490.2 | J20: ='Portfolio Wise '!K470 -> 0.25828743 | K20: ='Portfolio Wise '!M470 -> 9919.2166 | L20: ='Portfolio Wise '!L470 -> 3.8716558 | M20: ='Portfolio Wise '!Q470 -> 457.76315 | N20: ='Portfolio Wise '!R470 -> 2786957.7 | O20: ='Portfolio Wise '!S470 -> 6088.2089 | P20: ='Portfolio Wise '!T470 -> 0.32293278 | Q20: ='Portfolio Wise '!U470 -> 3.0966196 | R20: ='Portfolio Wise '!N470 -> 106.47631 | S20: ='Portfolio Wise '!O470 -> 955427.94 | T20: ='Portfolio Wise '!P470 -> 8973.1501 | X20: =R20/G20 -> 0.30310363 | Y20: =IFERROR(R20/M20,0) -> 0.23260132 | Z20: =IFERROR(S20/N20,0) -> 0.34282112

Sheet Qtr - Report 
A1: Q | B1: Amt Spent | C1: Imp | D1: CTR | E1: Clicks | F1: CPC | G1: Paid Orders | H1: CR | I1: Paid Revenue | J1: Paid ACOS | K1: Paid AOV | L1: ROAS | M1: Total Orders | N1: Total Sale | O1: Total AOV | P1: TACOS | Q1: ROI | R1: Organic Orders | S1: Organic Sale | T1: Organic AOV | U1: Sessions | V1: Session %
A2: Q1 | B2: =SUM(Monthly!B4:B6) -> 1187748.6 | C2: =SUM(Monthly!C4:C6) -> 11837783 | D2: =IFERROR(E2/C2,0) -> 0.0045487402 | E2: =SUM(Monthly!E4:E6) -> 53847 | F2: =IFERROR(B2/E2,0) -> 22.057841 | G2: =SUM(Monthly!G4:G6) -> 401 | H2: =IFERROR(G2/E2,0) -> 0.0074470258 | I2: =SUM(Monthly!I4:I6) -> 7311707.1 | J2: =IFERROR(B2/I2,0) -> 0.16244477 | K2: =IFERROR(I2/G2,0) -> 18233.683 | L2: =IFERROR(I2/B2,0) -> 6.1559383 | M2: =SUM(Monthly!M4:M6) -> 691 | N2: =SUM(Monthly!N4:N6) -> 11127431 | O2: =IFERROR(N2/M2,0) -> 16103.374 | P2: =IFERROR(B2/N2,0) -> 0.10674059 | Q2: =IFERROR(N2/B2,0) -> 9.3685071 | R2: =IFERROR(M2-G2,0) -> 290 | S2: =IFERROR(N2-I2,0) -> 3815724.1 | T2: =IFERROR(S2/R2,0) -> 13157.669 | U2: =SUM(Monthly!U4:U6) -> 102716 | V2: =IFERROR(M2/U2,0) -> 0.0067272869
A3: Q2 | B3: =SUM(Monthly!B6:B8) -> 2106337.6 | C3: =SUM(Monthly!C6:C8) -> 17707795 | D3: =IFERROR(E3/C3,0) -> 0.0045273282 | E3: =SUM(Monthly!E7:E9) -> 80169 | F3: =IFERROR(B3/E3,0) -> 26.273716 | G3: =SUM(Monthly!G7:G9) -> 698 | H3: =IFERROR(G3/E3,0) -> 0.0087066073 | I3: =SUM(Monthly!I6:I8) -> 12362178 | J3: =IFERROR(B3/I3,0) -> 0.17038564 | K3: =IFERROR(I3/G3,0) -> 17710.857 | L3: =IFERROR(I3/B3,0) -> 5.8690393 | M3: =SUM(Monthly!M7:M9) -> 983 | N3: =SUM(Monthly!N7:N9) -> 16547784 | O3: =IFERROR(N3/M3,0) -> 16833.961 | P3: =IFERROR(B3/N3,0) -> 0.1272882 | Q3: =IFERROR(N3/B3,0) -> 7.856188 | R3: =IFERROR(M3-G3,0) -> 285 | S3: =IFERROR(N3-I3,0) -> 4185605.9 | T3: =IFERROR(S3/R3,0) -> 14686.336 | U3: =SUM(Monthly!U6:U8) -> 161997 | V3: =IFERROR(M3/U3,0) -> 0.0060680136
A4: Q3 | B4: =SUM(Monthly!B10:B12) -> 3090468.1 | C4: =SUM(Monthly!C7:C9) -> 19972516 | D4: =IFERROR(E4/C4,0) -> 0.0058324149 | E4: =SUM(Monthly!E10:E12) -> 116488 | F4: =IFERROR(B4/E4,0) -> 26.530356 | G4: =SUM(Monthly!G10:G12) -> 987 | H4: =IFERROR(G4/E4,0) -> 0.0084729758 | I4: =SUM(Monthly!I7:I9) -> 12570210 | J4: =IFERROR(B4/I4,0) -> 0.24585653 | K4: =IFERROR(I4/G4,0) -> 12735.775 | L4: =IFERROR(I4/B4,0) -> 4.0674128 | M4: =SUM(Monthly!M10:M12) -> 1480 | N4: =SUM(Monthly!N10:N12) -> 23280228 | O4: =IFERROR(N4/M4,0) -> 15729.884 | P4: =IFERROR(B4/N4,0) -> 0.13275077 | Q4: =IFERROR(N4/B4,0) -> 7.5329131 | R4: =IFERROR(M4-G4,0) -> 493 | S4: =IFERROR(N4-I4,0) -> 10710018 | T4: =IFERROR(S4/R4,0) -> 21724.175 | U4: =SUM(Monthly!U7:U9) -> 178880 | V4: =IFERROR(M4/U4,0) -> 0.008273703
A8: Month | B8: Amt Spent | C8: Imp | D8: CTR | E8: Clicks | F8: CPC | G8: Paid Orders | H8: CR | I8: Paid Revenue | J8: Paid ACOS | K8: Paid AOV | L8: ROAS | M8: Total Orders | N8: Total Sale | O8: Total AOV | P8: TACOS | Q8: ROI | R8: Organic Orders | S8: Organic Sale | T8: Organic AOV | U8: Sessions | V8: Session %
A9: Jan | B9: 269951.38 | C9: 3237665 | D9: 0.0041446536 | E9: 13419 | F9: 20.117101 | G9: 82 | H9: 0.0061107385 | I9: 1526285 | J9: 0.17686827 | K9: 18613.231 | L9: 5.6539255 | M9: 156 | N9: 2496815.5 | O9: 16005.228 | P9: 0.10811827 | Q9: 9.2491304 | R9: 74 | S9: 970530.53 | T9: 13115.277 | U9: 26612 | V9: 0.0058620171
A10: Feb | B10: 363205.24 | C10: 3415714 | D10: 0.0046774993 | E10: 15977 | F10: 22.733006 | G10: 123 | H10: 0.0076985667 | I10: 2203105.7 | J10: 0.16486056 | K10: 17911.429 | L10: 6.0657322 | M10: 228 | N10: 3525611.6 | O10: 15463.209 | P10: 0.10301907 | Q10: 9.7069404 | R10: 105 | S10: 1322505.9 | T10: 12595.294 | U10: 31719 | V10: 0.0071881207
A11: Mar | B11: 554591.97 | C11: 5184404 | D11: 0.0047162605 | E11: 24451 | F11: 22.68177 | G11: 196 | H11: 0.0080160321 | I11: 3582316.4 | J11: 0.15481379 | K11: 18277.124 | L11: 6.459373 | M11: 307 | N11: 5105004 | O11: 16628.678 | P11: 0.10863693 | Q11: 9.2049728 | R11: 111 | S11: 1522687.6 | T11: 13717.906 | U11: 44385 | V11: 0.0069167512
A12: Apr | B12: 636539.97 | C12: 5671901 | D12: 0.0044567068 | E12: 25278 | F12: 25.18158 | G12: 192 | H12: 0.0075955376 | I12: 3539616 | J12: 0.17983306 | K12: 18435.5 | L12: 5.5607128 | M12: 280 | N12: 4575649.8 | O12: 16341.607 | P12: 0.13911466 | Q12: 7.1883151 | R12: 88 | S12: 1036033.9 | T12: 11773.112 | U12: 46985 | V12: 0.0059593487
A13: May | B13: 915205.63 | C13: 6851490 | D13: 0.0042012759 | E13: 28785 | F13: 31.794533 | G13: 286 | H13: 0.0099357304 | I13: 5240245.7 | J13: 0.17464937 | K13: 18322.538 | L13: 5.7257578 | M13: 390 | N13: 6681635.1 | O13: 17132.398 | P13: 0.1369733 | Q13: 7.3006927 | R13: 104 | S13: 1441389.3 | T13: 13859.513 | U13: 70627 | V13: 0.0055219675
A14: June | B14: 712488.04 | C14: 7449125 | D14: 0.0035045727 | E14: 26106 | F14: 27.292118 | G14: 220 | H14: 0.0084271815 | I14: 3790348 | J14: 0.18797431 | K14: 17228.855 | L14: 5.319876 | M14: 313 | N14: 5290499 | O14: 16902.553 | P14: 0.13467313 | Q14: 7.4253865 | R14: 93 | S14: 1500151 | T14: 16130.656 | U14: 61268 | V14: 0.0051087027
A15: July | B15: 868070.3 | C15: 8194079 | D15: 0.0035996724 | E15: 29496 | F15: 29.430102 | G15: 279 | H15: 0.0094589097 | I15: 5182218.6 | J15: 0.16750939 | K15: 18574.26 | L15: 5.9698145 | M15: 411 | N15: 7060713 | O15: 17179.35 | P15: 0.12294372 | Q15: 8.1338033 | R15: 132 | S15: 1878494.4 | T15: 14231.018 | U15: 65802 | V15: 0.0062460108
A16: August | B16: 831575.61 | C16: 7860313 | D16: 0.0040125629 | E16: 31540 | F16: 26.365745 | G16: 228 | H16: 0.0072289157 | I16: 3896020.5 | J16: 0.21344231 | K16: 17087.809 | L16: 4.6851068 | M16: 386 | N16: 5948601.1 | O16: 15410.884 | P16: 0.13979347 | Q16: 7.1534097 | R16: 158 | S16: 2052580.5 | T16: 12991.016 | U16: 69611 | V16: 0.0055451006
A17: September | B17: 1390822.2 | C17: 14814452 | D17: 0.0037431017 | E17: 55452 | F17: 25.081552 | G17: 480 | H17: 0.008656135 | I17: 7678468.1 | J17: 0.18113277 | K17: 15996.809 | L17: 5.5208121 | M17: 683 | N17: 10270914 | O17: 15037.941 | P17: 0.13541368 | Q17: 7.3847784 | R17: 203 | S17: 2592445.8 | T17: 12770.669 | U17: 92124 | V17: 0.0074139204

Sheet B2B 
A1: Month | B1: Order | C1: Order | D1: Order B2B | E1: Sales - B2B
A2: Nov | B2: 107 | C2: 2169972 | D2: =SUMIFS('Business - Dump'!$R:$R,'Business - Dump'!$A:$A,'B2B '!$A2) -> 8 | E2: 195598
A3: Dec | B3: 214 | C3: 4260008 | D3: =SUMIFS('Business - Dump'!$R:$R,'Business - Dump'!$A:$A,'B2B '!$A3) -> 18 | E3: 396598
A4: Jan | B4: 156 | C4: 2946242.3 | D4: =SUMIFS('Business - Dump'!$R:$R,'Business - Dump'!$A:$A,'B2B '!$A4) -> 16 | E4: 265894.4
A5: Feb | B5: 228 | C5: 4160221.7 | D5: =SUMIFS('Business - Dump'!$R:$R,'Business - Dump'!$A:$A,'B2B '!$A5) -> 17 | E5: 369473.29
A6: Mar | B6: 307 | C6: 6023904.7 | D6: =SUMIFS('Business - Dump'!$R:$R,'Business - Dump'!$A:$A,'B2B '!$A6) -> 44 | E6: 750380.73
A7: Apr | B7: =SUMIFS('Business - Dump'!$W:$W,'Business - Dump'!$A:$A,'B2B '!$A7)-D7 -> 255 | C7: =SUMIFS('Business - Dump'!$U:$U,'Business - Dump'!$A:$A,'B2B '!$A7)-E7 -> 4560610.2 | D7: =SUMIFS('Business - Dump'!$X:$X,'Business - Dump'!$A:$A,'B2B '!$A7) -> 25 | E7: =SUMIFS('Business - Dump'!$V:$V,'Business - Dump'!$A:$A,'B2B '!$A7) -> 838656.66
A8: May | B8: =SUMIFS('Business - Dump'!$W:$W,'Business - Dump'!$A:$A,'B2B '!$A8)-D8 -> 354 | C8: =SUMIFS('Business - Dump'!$U:$U,'Business - Dump'!$A:$A,'B2B '!$A8)-E8 -> 7002728 | D8: =SUMIFS('Business - Dump'!$X:$X,'Business - Dump'!$A:$A,'B2B '!$A8) -> 36 | E8: =SUMIFS('Business - Dump'!$V:$V,'Business - Dump'!$A:$A,'B2B '!$A8) -> 881601.36
A9: June | B9: =SUMIFS('Business - Dump'!$W:$W,'Business - Dump'!$A:$A,'B2B '!$A9)-D9 -> 282 | C9: =SUMIFS('Business - Dump'!$U:$U,'Business - Dump'!$A:$A,'B2B '!$A9)-E9 -> 5497566.9 | D9: =SUMIFS('Business - Dump'!$X:$X,'Business - Dump'!$A:$A,'B2B '!$A9) -> 31 | E9: =SUMIFS('Business - Dump'!$V:$V,'Business - Dump'!$A:$A,'B2B '!$A9) -> 745221.97
A10: July | B10: =SUMIFS('Business - Dump'!$W:$W,'Business - Dump'!$A:$A,'B2B '!$A10)-D10 -> 380 | C10: =SUMIFS('Business - Dump'!$U:$U,'Business - Dump'!$A:$A,'B2B '!$A10)-E10 -> 7708213.7 | D10: =SUMIFS('Business - Dump'!$X:$X,'Business - Dump'!$A:$A,'B2B '!$A10) -> 31 | E10: =SUMIFS('Business - Dump'!$V:$V,'Business - Dump'!$A:$A,'B2B '!$A10) -> 623427.68
A11: August | B11: =SUMIFS('Business - Dump'!$W:$W,'Business - Dump'!$A:$A,'B2B '!$A11)-D11 -> 361 | C11: =SUMIFS('Business - Dump'!$U:$U,'Business - Dump'!$A:$A,'B2B '!$A11)-E11 -> 6496497.3 | D11: =SUMIFS('Business - Dump'!$X:$X,'Business - Dump'!$A:$A,'B2B '!$A11) -> 25 | E11: =SUMIFS('Business - Dump'!$V:$V,'Business - Dump'!$A:$A,'B2B '!$A11) -> 522851.94
A12: September | B12: =SUMIFS('Business - Dump'!$W:$W,'Business - Dump'!$A:$A,'B2B '!$A12)-D12 -> 631 | C12: =SUMIFS('Business - Dump'!$U:$U,'Business - Dump'!$A:$A,'B2B '!$A12)-E12 -> 11179070 | D12: =SUMIFS('Business - Dump'!$X:$X,'Business - Dump'!$A:$A,'B2B '!$A12) -> 52 | E12: =SUMIFS('Business - Dump'!$V:$V,'Business - Dump'!$A:$A,'B2B '!$A12) -> 940608.38
A13: October | B13: =SUMIFS('Business - Dump'!$W:$W,'Business - Dump'!$A:$A,'B2B '!$A13)-D13 -> 558 | C13: =SUMIFS('Business - Dump'!$U:$U,'Business - Dump'!$A:$A,'B2B '!$A13)-E13 -> 9556218.7 | D13: =SUMIFS('Business - Dump'!$X:$X,'Business - Dump'!$A:$A,'B2B '!$A13) -> 32 | E13: =SUMIFS('Business - Dump'!$V:$V,'Business - Dump'!$A:$A,'B2B '!$A13) -> 548954.95
A14: November | B14: =SUMIFS('Business - Dump'!$W:$W,'Business - Dump'!$A:$A,'B2B '!$A14)-D14 -> 349 | C14: =SUMIFS('Business - Dump'!$U:$U,'Business - Dump'!$A:$A,'B2B '!$A14)-E14 -> 4378557.4 | D14: =SUMIFS('Business - Dump'!$X:$X,'Business - Dump'!$A:$A,'B2B '!$A14) -> 30 | E14: =SUMIFS('Business - Dump'!$V:$V,'Business - Dump'!$A:$A,'B2B '!$A14) -> 562434.45
A15: December | B15: =SUMIFS('Business - Dump'!$W:$W,'Business - Dump'!$A:$A,'B2B '!$A15)-D15 -> 441 | C15: =SUMIFS('Business - Dump'!$U:$U,'Business - Dump'!$A:$A,'B2B '!$A15)-E15 -> 4434524.4 | D15: =SUMIFS('Business - Dump'!$X:$X,'Business - Dump'!$A:$A,'B2B '!$A15) -> 30 | E15: =SUMIFS('Business - Dump'!$V:$V,'Business - Dump'!$A:$A,'B2B '!$A15) -> 473397.68
A16: Total | B16: =SUM(B2:B11) -> 2644 | C16: =SUM(C2:C11) -> 50825965 | D16: =SUM(D2:D11) -> 251 | E16: =SUM(E2:E11) -> 5589704

Sheet Portfolio Wise 
A1: Month | B1: Portfolios | C1: Impressions | D1: Clicks | E1: CTR | F1: Spend | G1: CPC | H1: Orders | I1: CR | J1: Sales | K1: ACOS | L1: ROAS | M1: Paid AOV | N1: Organic Orders | O1: Organic Sale | P1: Organic AOV | Q1: Total Orders | R1: Total Sale | S1: Total AOV | T1: TACOS | U1: ROI | V1: Sessions | W1: Session % | X1: Organic Orders Cont | Y1: Organic Sales Contribution | Z1: Paid Order Cont | AA1: Paid sales Cont | AB1: Buy Box | AC1: Spend in % | AD1: Paid To Organic Orders
A2: Nov | B2: Sales Day | C2: =SUMIFS('Campaign - Dump'!$N:$N,'Campaign - Dump'!$J:$J,'Portfolio Wise '!$B2,'Campaign - Dump'!$A:$A,'Portfolio Wise '!$A2) -> 4053615 | D2: =SUMIFS('Campaign - Dump'!$O:$O,'Campaign - Dump'!$J:$J,'Portfolio Wise '!$B2,'Campaign - Dump'!$A:$A,'Portfolio Wise '!$A2) -> 12939 | E2: =IFERROR(D2/C2,0) -> 0.0031919657 | F2: =SUMIFS('Campaign - Dump'!$Q:$Q,'Campaign - Dump'!$J:$J,'Portfolio Wise '!$B2,'Campaign - Dump'!$A:$A,'Portfolio Wise '!$A2) -> 162935.35 | G2: =IFERROR(F2/D2,0) -> 12.592577 | H2: =SUMIFS('Campaign - Dump'!$T:$T,'Campaign - Dump'!$J:$J,'Portfolio Wise '!$B2,'Campaign - Dump'!$A:$A,'Portfolio Wise '!$A2) -> 49 | I2: =IFERROR(H2/D2,0) -> 0.0037870005 | J2: =SUMIFS('Campaign - Dump'!$U:$U,'Campaign - Dump'!$J:$J,'Portfolio Wise '!$B2,'Campaign - Dump'!$A:$A,'Portfolio Wise '!$A2) -> 843788.92 | K2: =IFERROR(F2/J2,0) -> 0.19309966 | L2: =IFERROR(J2/F2,0) -> 5.1786731 | M2: =IFERROR(J2/H2,0) -> 17220.182 | N2: 0 | O2: 0 | P2: =IFERROR(O2/N2,0) -> 0 | Q2: =SUMIFS('Business - Dump'!$W:$W,'Business - Dump'!$B:$B,'Portfolio Wise '!$B2,'Business - Dump'!$A:$A,'Portfolio Wise '!$A2) -> 0 | R2: =SUMIFS('Business - Dump'!$U:$U,'Business - Dump'!$B:$B,'Portfolio Wise '!$B2,'Business - Dump'!$A:$A,'Portfolio Wise '!$A2)/1.18 -> 0 | S2: =IFERROR(R2/Q2,0) -> 0 | T2: =IFERROR(F2/R2,0) -> 0 | U2: =IFERROR(R2/F2,0) -> 0 | V2: =SUMIFS('Business - Dump'!$G:$G,'Business - Dump'!$B:$B,'Portfolio Wise '!$B2,'Business - Dump'!$A:$A,'Portfolio Wise '!$A2) -> 0 | W2: =IFERROR(Q2/V2,0) -> 0 | X2: =IFERROR(N2/Q2,0) -> 0 | Y2: =IFERROR(O2/R2,0) -> 0 | Z2: =IFERROR(H2/Q2,0) -> 0 | AA2: =IFERROR(O2/R2,0) -> 0 | AB2: =IFERROR(AVERAGEIFS('Business - Dump'!$O:$O,'Business - Dump'!$B:$B,'Portfolio Wise '!$B2,'Business - Dump'!$A:$A,'Portfolio Wise '!$A2),0) -> 0 | AC2: =F2/SUMIFS('Campaign - Dump'!$Q:$Q,'Campaign - Dump'!$A:$A,'Portfolio Wise '!$A2) -> 0.99914334 | AD2: =IFERROR(N2/H2,0) -> 0
A3: Nov | B3: Standing Table | C3: =SUMIFS('Campaign - Dump'!$N:$N,'Campaign - Dump'!$J:$J,'Portfolio Wise '!$B3,'Campaign - Dump'!$A:$A,'Portfolio Wise '!$A3) -> 0 | D3: =SUMIFS('Campaign - Dump'!$O:$O,'Campaign - Dump'!$J:$J,'Portfolio Wise '!$B3,'Campaign - Dump'!$A:$A,'Portfolio Wise '!$A3) -> 0 | E3: =IFERROR(D3/C3,0) -> 0 | F3: =SUMIFS('Campaign - Dump'!$Q:$Q,'Campaign - Dump'!$J:$J,'Portfolio Wise '!$B3,'Campaign - Dump'!$A:$A,'Portfolio Wise '!$A3) -> 0 | G3: =IFERROR(F3/D3,0) -> 0 | H3: =SUMIFS('Campaign - Dump'!$T:$T,'Campaign - Dump'!$J:$J,'Portfolio Wise '!$B3,'Campaign - Dump'!$A:$A,'Portfolio Wise '!$A3) -> 0 | I3: =IFERROR(H3/D3,0) -> 0 | J3: =SUMIFS('Campaign - Dump'!$U:$U,'Campaign - Dump'!$J:$J,'Portfolio Wise '!$B3,'Campaign - Dump'!$A:$A,'Portfolio Wise '!$A3) -> 0 | K3: =IFERROR(F3/J3,0) -> 0 | L3: =IFERROR(J3/F3,0) -> 0 | M3: =IFERROR(J3/H3,0) -> 0 | N3: =IFERROR(Q3-H3,0) -> 0 | O3: =IFERROR(R3-J3,0) -> 0 | P3: =IFERROR(O3/N3,0) -> 0 | Q3: =SUMIFS('Business - Dump'!$W:$W,'Business - Dump'!$B:$B,'Portfolio Wise '!$B3,'Business - Dump'!$A:$A,'Portfolio Wise '!$A3) -> 0 | R3: =SUMIFS('Business - Dump'!$U:$U,'Business - Dump'!$B:$B,'Portfolio Wise '!$B3,'Business - Dump'!$A:$A,'Portfolio Wise '!$A3)/1.18 -> 0 | S3: =IFERROR(R3/Q3,0) -> 0 | T3: =IFERROR(F3/R3,0) -> 0 | U3: =IFERROR(R3/F3,0) -> 0 | V3: =SUMIFS('Business - Dump'!$G:$G,'Business - Dump'!$B:$B,'Portfolio Wise '!$B3,'Business - Dump'!$A:$A,'Portfolio Wise '!$A3) -> 0 | W3: =IFERROR(Q3/V3,0) -> 0 | X3: =IFERROR(N3/Q3,0) -> 0 | Y3: =IFERROR(O3/R3,0) -> 0 | Z3: =IFERROR(H3/Q3,0) -> 0 | AA3: =IFERROR(O3/R3,0) -> 0 | AB3: =IFERROR(AVERAGEIFS('Business - Dump'!$O:$O,'Business - Dump'!$B:$B,'Portfolio Wise '!$B3,'Business - Dump'!$A:$A,'Portfolio Wise '!$A3),0) -> 0 | AC3: =F3/SUMIFS('Campaign - Dump'!$Q:$Q,'Campaign - Dump'!$A:$A,'Portfolio Wise '!$A3) -> 0 | AD3: =IFERROR(N3/H3,0) -> 0
A4: Nov | B4: TABLE TOP | C4: =SUMIFS('Campaign - Dump'!$N:$N,'Campaign - Dump'!$J:$J,'Portfolio Wise '!$B4,'Campaign - Dump'!$A:$A,'Portfolio Wise '!$A4) -> 1245 | D4: =SUMIFS('Campaign - Dump'!$O:$O,'Campaign - Dump'!$J:$J,'Portfolio Wise '!$B4,'Campaign - Dump'!$A:$A,'Portfolio Wise '!$A4) -> 14 | E4: =IFERROR(D4/C4,0) -> 0.01124498 | F4: =SUMIFS('Campaign - Dump'!$Q:$Q,'Campaign - Dump'!$J:$J,'Portfolio Wise '!$B4,'Campaign - Dump'!$A:$A,'Portfolio Wise '!$A4) -> 88.59 | G4: =IFERROR(F4/D4,0) -> 6.3278571 | H4: =SUMIFS('Campaign - Dump'!$T:$T,'Campaign - Dump'!$J:$J,'Portfolio Wise '!$B4,'Campaign - Dump'!$A:$A,'Portfolio Wise '!$A4) -> 0 | I4: =IFERROR(H4/D4,0) -> 0 | J4: =SUMIFS('Campaign - Dump'!$U:$U,'Campaign - Dump'!$J:$J,'Portfolio Wise '!$B4,'Campaign - Dump'!$A:$A,'Portfolio Wise '!$A4) -> 0 | K4: =IFERROR(F4/J4,0) -> 0 | L4: =IFERROR(J4/F4,0) -> 0 | M4: =IFERROR(J4/H4,0) -> 0 | N4: =IFERROR(Q4-H4,0) -> 2 | O4: =IFERROR(R4-J4,0) -> 10000 | P4: =IFERROR(O4/N4,0) -> 5000 | Q4: =SUMIFS('Business - Dump'!$W:$W,'Business - Dump'!$B:$B,'Portfolio Wise '!$B4,'Business - Dump'!$A:$A,'Portfolio Wise '!$A4) -> 2 | R4: =SUMIFS('Business - Dump'!$U:$U,'Business - Dump'!$B:$B,'Portfolio Wise '!$B4,'Business - Dump'!$A:$A,'Portfolio Wise '!$A4)/1.18 -> 10000 | S4: =IFERROR(R4/Q4,0) -> 5000 | T4: =IFERROR(F4/R4,0) -> 0.008859 | U4: =IFERROR(R4/F4,0) -> 112.87956 | V4: =SUMIFS('Business - Dump'!$G:$G,'Business - Dump'!$B:$B,'Portfolio Wise '!$B4,'Business - Dump'!$A:$A,'Portfolio Wise '!$A4) -> 1637 | W4: =IFERROR(Q4/V4,0) -> 0.0012217471 | X4: =IFERROR(N4/Q4,0) -> 1 | Y4: =IFERROR(O4/R4,0) -> 1 | Z4: =IFERROR(H4/Q4,0) -> 0 | AA4: =IFERROR(O4/R4,0) -> 1 | AB4: =IFERROR(AVERAGEIFS('Business - Dump'!$O:$O,'Business - Dump'!$B:$B,'Portfolio Wise '!$B4,'Business - Dump'!$A:$A,'Portfolio Wise '!$A4),0) -> 0.7159 | AC4: =F4/SUMIFS('Campaign - Dump'!$Q:$Q,'Campaign - Dump'!$A:$A,'Portfolio Wise '!$A4) -> 0.00054324681 | AD4: =IFERROR(N4/H4,0) -> 0
A5: Nov | B5: Brand | C5: =SUMIFS('Campaign - Dump'!$N:$N,'Campaign - Dump'!$J:$J,'Portfolio Wise '!$B5,'Campaign - Dump'!$A:$A,'Portfolio Wise '!$A5) -> 563 | D5: =SUMIFS('Campaign - Dump'!$O:$O,'Campaign - Dump'!$J:$J,'Portfolio Wise '!$B5,'Campaign - Dump'!$A:$A,'Portfolio Wise '!$A5) -> 2 | E5: =IFERROR(D5/C5,0) -> 0.0035523979 | F5: =SUMIFS('Campaign - Dump'!$Q:$Q,'Campaign - Dump'!$J:$J,'Portfolio Wise '!$B5,'Campaign - Dump'!$A:$A,'Portfolio Wise '!$A5) -> 20.01 | G5: =IFERROR(F5/D5,0) -> 10.005 | H5: =SUMIFS('Campaign - Dump'!$T:$T,'Campaign - Dump'!$J:$J,'Portfolio Wise '!$B5,'Campaign - Dump'!$A:$A,'Portfolio Wise '!$A5) -> 0 | I5: =IFERROR(H5/D5,0) -> 0 | J5: =SUMIFS('Campaign - Dump'!$U:$U,'Campaign - Dump'!$J:$J,'Portfolio Wise '!$B5,'Campaign - Dump'!$A:$A,'Portfolio Wise '!$A5) -> 0 | K5: =IFERROR(F5/J5,0) -> 0 | L5: =IFERROR(J5/F5,0) -> 0 | M5: =IFERROR(J5/H5,0) -> 0 | N5: 0 | O5: 0 | P5: =IFERROR(O5/N5,0) -> 0 | Q5: =SUMIFS('Business - Dump'!$W:$W,'Business - Dump'!$B:$B,'Portfolio Wise '!$B5,'Business - Dump'!$A:$A,'Portfolio Wise '!$A5) -> 0 | R5: =SUMIFS('Business - Dump'!$U:$U,'Business - Dump'!$B:$B,'Portfolio Wise '!$B5,'Business - Dump'!$A:$A,'Portfolio Wise '!$A5)/1.18 -> 0 | S5: =IFERROR(R5/Q5,0) -> 0 | T5: =IFERROR(F5/R5,0) -> 0 | U5: =IFERROR(R5/F5,0) -> 0 | V5: =SUMIFS('Business - Dump'!$G:$G,'Business - Dump'!$B:$B,'Portfolio Wise '!$B5,'Business - Dump'!$A:$A,'Portfolio Wise '!$A5) -> 0 | W5: =IFERROR(Q5/V5,0) -> 0 | X5: =IFERROR(N5/Q5,0) -> 0 | Y5: =IFERROR(O5/R5,0) -> 0 | Z5: =IFERROR(H5/Q5,0) -> 0 | AA5: =IFERROR(O5/R5,0) -> 0 | AB5: =IFERROR(AVERAGEIFS('Business - Dump'!$O:$O,'Business - Dump'!$B:$B,'Portfolio Wise '!$B5,'Business - Dump'!$A:$A,'Portfolio Wise '!$A5),0) -> 0 | AC5: =F5/SUMIFS('Campaign - Dump'!$Q:$Q,'Campaign - Dump'!$A:$A,'Portfolio Wise '!$A5) -> 0.00012270424 | AD5: =IFERROR(N5/H5,0) -> 0
A6: Nov | B6: Standing Table - SM3 | C6: =SUMIFS('Campaign - Dump'!$N:$N,'Campaign - Dump'!$J:$J,'Portfolio Wise '!$B6,'Campaign - Dump'!$A:$A,'Portfolio Wise '!$A6) -> 67 | D6: =SUMIFS('Campaign - Dump'!$O:$O,'Campaign - Dump'!$J:$J,'Portfolio Wise '!$B6,'Campaign - Dump'!$A:$A,'Portfolio Wise '!$A6) -> 0 | E6: =IFERROR(D6/C6,0) -> 0 | F6: =SUMIFS('Campaign - Dump'!$Q:$Q,'Campaign - Dump'!$J:$J,'Portfolio Wise '!$B6,'Campaign - Dump'!$A:$A,'Portfolio Wise '!$A6) -> 0 | G6: =IFERROR(F6/D6,0) -> 0 | H6: =SUMIFS('Campaign - Dump'!$T:$T,'Campaign - Dump'!$J:$J,'Portfolio Wise '!$B6,'Campaign - Dump'!$A:$A,'Portfolio Wise '!$A6) -> 0 | I6: =IFERROR(H6/D6,0) -> 0 | J6: =SUMIFS('Campaign - Dump'!$U:$U,'Campaign - Dump'!$J:$J,'Portfolio Wise '!$B6,'Campaign - Dump'!$A:$A,'Portfolio Wise '!$A6) -> 0 | K6: =IFERROR(F6/J6,0) -> 0 | L6: =IFERROR(J6/F6,0) -> 0 | M6: =IFERROR(J6/H6,0) -> 0 | N6: =IFERROR(Q6-H6,0) -> 34 | O6: =IFERROR(R6-J6,0) -> 654067.8 | P6: =IFERROR(O6/N6,0) -> 19237.288 | Q6: =SUMIFS('Business - Dump'!$W:$W,'Business - Dump'!$B:$B,'Portfolio Wise '!$B6,'Business - Dump'!$A:$A,'Portfolio Wise '!$A6) -> 34 | R6: =SUMIFS('Business - Dump'!$U:$U,'Business - Dump'!$B:$B,'Portfolio Wise '!$B6,'Business - Dump'!$A:$A,'Portfolio Wise '!$A6)/1.18 -> 654067.8 | S6: =IFERROR(R6/Q6,0) -> 19237.288 | T6: =IFERROR(F6/R6,0) -> 0 | U6: =IFERROR(R6/F6,0) -> 0 | V6: =SUMIFS('Business - Dump'!$G:$G,'Business - Dump'!$B:$B,'Portfolio Wise '!$B6,'Business - Dump'!$A:$A,'Portfolio Wise '!$A6) -> 7626 | W6: =IFERROR(Q6/V6,0) -> 0.0044584317 | X6: =IFERROR(N6/Q6,0) -> 1 | Y6: =IFERROR(O6/R6,0) -> 1 | Z6: =IFERROR(H6/Q6,0) -> 0 | AA6: =IFERROR(O6/R6,0) -> 1 | AB6: =IFERROR(AVERAGEIFS('Business - Dump'!$O:$O,'Business - Dump'!$B:$B,'Portfolio Wise '!$B6,'Business - Dump'!$A:$A,'Portfolio Wise '!$A6),0) -> 0.925275 | AC6: =F6/SUMIFS('Campaign - Dump'!$Q:$Q,'Campaign - Dump'!$A:$A,'Portfolio Wise '!$A6) -> 0 | AD6: =IFERROR(N6/H6,0) -> 0
A7: Nov | B7: Standing Table - E2 | C7: =SUMIFS('Campaign - Dump'!$N:$N,'Campaign - Dump'!$J:$J,'Portfolio Wise '!$B7,'Campaign - Dump'!$A:$A,'Portfolio Wise '!$A7) -> 729 | D7: =SUMIFS('Campaign - Dump'!$O:$O,'Campaign - Dump'!$J:$J,'Portfolio Wise '!$B7,'Campaign - Dump'!$A:$A,'Portfolio Wise '!$A7) -> 4 | E7: =IFERROR(D7/C7,0) -> 0.0054869684 | F7: =SUMIFS('Campaign - Dump'!$Q:$Q,'Campaign - Dump'!$J:$J,'Portfolio Wise '!$B7,'Campaign - Dump'!$A:$A,'Portfolio Wise '!$A7) -> 31.1 | G7: =IFERROR(F7/D7,0) -> 7.775 | H7: =SUMIFS('Campaign - Dump'!$T:$T,'Campaign - Dump'!$J:$J,'Portfolio Wise '!$B7,'Campaign - Dump'!$A:$A,'Portfolio Wise '!$A7) -> 0 | I7: =IFERROR(H7/D7,0) -> 0 | J7: =SUMIFS('Campaign - Dump'!$U:$U,'Campaign - Dump'!$J:$J,'Portfolio Wise '!$B7,'Campaign - Dump'!$A:$A,'Portfolio Wise '!$A7) -> 0 | K7: =IFERROR(F7/J7,0) -> 0 | L7: =IFERROR(J7/F7,0) -> 0 | M7: =IFERROR(J7/H7,0) -> 0 | N7: =IFERROR(Q7-H7,0) -> 20 | O7: =IFERROR(R7-J7,0) -> 536745.76 | P7: =IFERROR(O7/N7,0) -> 26837.288 | Q7: =SUMIFS('Business - Dump'!$W:$W,'Business - Dump'!$B:$B,'Portfolio Wise '!$B7,'Business - Dump'!$A:$A,'Portfolio Wise '!$A7) -> 20 | R7: =SUMIFS('Business - Dump'!$U:$U,'Business - Dump'!$B:$B,'Portfolio Wise '!$B7,'Business - Dump'!$A:$A,'Portfolio Wise '!$A7)/1.18 -> 536745.76 | S7: =IFERROR(R7/Q7,0) -> 26837.288 | T7: =IFERROR(F7/R7,0) -> 5.7941771e-05 | U7: =IFERROR(R7/F7,0) -> 17258.706 | V7: =SUMIFS('Business - Dump'!$G:$G,'Business - Dump'!$B:$B,'Portfolio Wise '!$B7,'Business - Dump'!$A:$A,'Portfolio Wise '!$A7) -> 3887 | W7: =IFERROR(Q7/V7,0) -> 0.0051453563 | X7: =IFERROR(N7/Q7,0) -> 1 | Y7: =IFERROR(O7/R7,0) -> 1 | Z7: =IFERROR(H7/Q7,0) -> 0 | AA7: =IFERROR(O7/R7,0) -> 1 | AB7: =IFERROR(AVERAGEIFS('Business - Dump'!$O:$O,'Business - Dump'!$B:$B,'Portfolio Wise '!$B7,'Business - Dump'!$A:$A,'Portfolio Wise '!$A7),0) -> 0.83335 | AC7: =F7/SUMIFS('Campaign - Dump'!$Q:$Q,'Campaign - Dump'!$A:$A,'Portfolio Wise '!$A7) -> 0.00019070974 | AD7: =IFERROR(N7/H7,0) -> 0
A8: Nov | B8: Standing Table - M3 | C8: =SUMIFS('Campaign - Dump'!$N:$N,'Campaign - Dump'!$J:$J,'Portfolio Wise '!$B8,'Campaign - Dump'!$A:$A,'Portfolio Wise '!$A8) -> 0 | D8: =SUMIFS('Campaign - Dump'!$O:$O,'Campaign - Dump'!$J:$J,'Portfolio Wise '!$B8,'Campaign - Dump'!$A:$A,'Portfolio Wise '!$A8) -> 0 | E8: =IFERROR(D8/C8,0) -> 0 | F8: =SUMIFS('Campaign - Dump'!$Q:$Q,'Campaign - Dump'!$J:$J,'Portfolio Wise '!$B8,'Campaign - Dump'!$A:$A,'Portfolio Wise '!$A8) -> 0 | G8: =IFERROR(F8/D8,0) -> 0 | H8: =SUMIFS('Campaign - Dump'!$T:$T,'Campaign - Dump'!$J:$J,'Portfolio Wise '!$B8,'Campaign - Dump'!$A:$A,'Portfolio Wise '!$A8) -> 0 | I8: =IFERROR(H8/D8,0) -> 0 | J8: =SUMIFS('Campaign - Dump'!$U:$U,'Campaign - Dump'!$J:$J,'Portfolio Wise '!$B8,'Campaign - Dump'!$A:$A,'Portfolio Wise '!$A8) -> 0 | K8: =IFERROR(F8/J8,0) -> 0 | L8: =IFERROR(J8/F8,0) -> 0 | M8: =IFERROR(J8/H8,0) -> 0 | N8: =IFERROR(Q8-H8,0) -> 0 | O8: =IFERROR(R8-J8,0) -> 0 | P8: =IFERROR(O8/N8,0) -> 0 | Q8: =SUMIFS('Business - Dump'!$W:$W,'Business - Dump'!$B:$B,'Portfolio Wise '!$B8,'Business - Dump'!$A:$A,'Portfolio Wise '!$A8) -> 0 | R8: =SUMIFS('Business - Dump'!$U:$U,'Business - Dump'!$B:$B,'Portfolio Wise '!$B8,'Business - Dump'!$A:$A,'Portfolio Wise '!$A8)/1.18 -> 0 | S8: =IFERROR(R8/Q8,0) -> 0 | T8: =IFERROR(F8/R8,0) -> 0 | U8: =IFERROR(R8/F8,0) -> 0 | V8: =SUMIFS('Business - Dump'!$G:$G,'Business - Dump'!$B:$B,'Portfolio Wise '!$B8,'Business - Dump'!$A:$A,'Portfolio Wise '!$A8) -> 0 | W8: =IFERROR(Q8/V8,0) -> 0 | X8: =IFERROR(N8/Q8,0) -> 0 | Y8: =IFERROR(O8/R8,0) -> 0 | Z8: =IFERROR(H8/Q8,0) -> 0 | AA8: =IFERROR(O8/R8,0) -> 0 | AB8: =IFERROR(AVERAGEIFS('Business - Dump'!$O:$O,'Business - Dump'!$B:$B,'Portfolio Wise '!$B8,'Business - Dump'!$A:$A,'Portfolio Wise '!$A8),0) -> 0 | AC8: =F8/SUMIFS('Campaign - Dump'!$Q:$Q,'Campaign - Dump'!$A:$A,'Portfolio Wise '!$A8) -> 0 | AD8: =IFERROR(N8/H8,0) -> 0
A9: Nov | B9: Monitor Arm Stand | C9: =SUMIFS('Campaign - Dump'!$N:$N,'Campaign - Dump'!$J:$J,'Portfolio Wise '!$B9,'Campaign - Dump'!$A:$A,'Portfolio Wise '!$A9) -> 0 | D9: =SUMIFS('Campaign - Dump'!$O:$O,'Campaign - Dump'!$J:$J,'Portfolio Wise '!$B9,'Campaign - Dump'!$A:$A,'Portfolio Wise '!$A9) -> 0 | E9: =IFERROR(D9/C9,0) -> 0 | F9: =SUMIFS('Campaign - Dump'!$Q:$Q,'Campaign - Dump'!$J:$J,'Portfolio Wise '!$B9,'Campaign - Dump'!$A:$A,'Portfolio Wise '!$A9) -> 0 | G9: =IFERROR(F9/D9,0) -> 0 | H9: =SUMIFS('Campaign - Dump'!$T:$T,'Campaign - Dump'!$J:$J,'Portfolio Wise '!$B9,'Campaign - Dump'!$A:$A,'Portfolio Wise '!$A9) -> 0 | I9: =IFERROR(H9/D9,0) -> 0 | J9: =SUMIFS('Campaign - Dump'!$U:$U,'Campaign - Dump'!$J:$J,'Portfolio Wise '!$B9,'Campaign - Dump'!$A:$A,'Portfolio Wise '!$A9) -> 0 | K9: =IFERROR(F9/J9,0) -> 0 | L9: =IFERROR(J9/F9,0) -> 0 | M9: =IFERROR(J9/H9,0) -> 0 | N9: =IFERROR(Q9-H9,0) -> 0 | O9: =IFERROR(R9-J9,0) -> 0 | P9: =IFERROR(O9/N9,0) -> 0 | Q9: =SUMIFS('Business - Dump'!$W:$W,'Business - Dump'!$B:$B,'Portfolio Wise '!$B9,'Business - Dump'!$A:$A,'Portfolio Wise '!$A9) -> 0 | R9: =SUMIFS('Business - Dump'!$U:$U,'Business - Dump'!$B:$B,'Portfolio Wise '!$B9,'Business - Dump'!$A:$A,'Portfolio Wise '!$A9)/1.18 -> 0 | S9: =IFERROR(R9/Q9,0) -> 0 | T9: =IFERROR(F9/R9,0) -> 0 | U9: =IFERROR(R9/F9,0) -> 0 | V9: =SUMIFS('Business - Dump'!$G:$G,'Business - Dump'!$B:$B,'Portfolio Wise '!$B9,'Business - Dump'!$A:$A,'Portfolio Wise '!$A9) -> 0 | W9: =IFERROR(Q9/V9,0) -> 0 | X9: =IFERROR(N9/Q9,0) -> 0 | Y9: =IFERROR(O9/R9,0) -> 0 | Z9: =IFERROR(H9/Q9,0) -> 0 | AA9: =IFERROR(O9/R9,0) -> 0 | AB9: =IFERROR(AVERAGEIFS('Business - Dump'!$O:$O,'Business - Dump'!$B:$B,'Portfolio Wise '!$B9,'Business - Dump'!$A:$A,'Portfolio Wise '!$A9),0) -> 0 | AC9: =F9/SUMIFS('Campaign - Dump'!$Q:$Q,'Campaign - Dump'!$A:$A,'Portfolio Wise '!$A9) -> 0 | AD9: =IFERROR(N9/H9,0) -> 0
A10: Nov | B10: Standing Desk Converter | C10: =SUMIFS('Campaign - Dump'!$N:$N,'Campaign - Dump'!$J:$J,'Portfolio Wise '!$B10,'Campaign - Dump'!$A:$A,'Portfolio Wise '!$A10) -> 0 | D10: =SUMIFS('Campaign - Dump'!$O:$O,'Campaign - Dump'!$J:$J,'Portfolio Wise '!$B10,'Campaign - Dump'!$A:$A,'Portfolio Wise '!$A10) -> 0 | E10: =IFERROR(D10/C10,0) -> 0 | F10: =SUMIFS('Campaign - Dump'!$Q:$Q,'Campaign - Dump'!$J:$J,'Portfolio Wise '!$B10,'Campaign - Dump'!$A:$A,'Portfolio Wise '!$A10) -> 0 | G10: =IFERROR(F10/D10,0) -> 0 | H10: =SUMIFS('Campaign - Dump'!$T:$T,'Campaign - Dump'!$J:$J,'Portfolio Wise '!$B10,'Campaign - Dump'!$A:$A,'Portfolio Wise '!$A10) -> 0 | I10: =IFERROR(H10/D10,0) -> 0 | J10: =SUMIFS('Campaign - Dump'!$U:$U,'Campaign - Dump'!$J:$J,'Portfolio Wise '!$B10,'Campaign - Dump'!$A:$A,'Portfolio Wise '!$A10) -> 0 | K10: =IFERROR(F10/J10,0) -> 0 | L10: =IFERROR(J10/F10,0) -> 0 | M10: =IFERROR(J10/H10,0) -> 0 | N10: =IFERROR(Q10-H10,0) -> 1 | O10: =IFERROR(R10-J10,0) -> 5508.4746 | P10: =IFERROR(O10/N10,0) -> 5508.4746 | Q10: =SUMIFS('Business - Dump'!$W:$W,'Business - Dump'!$B:$B,'Portfolio Wise '!$B10,'Business - Dump'!$A:$A,'Portfolio Wise '!$A10) -> 1 | R10: =SUMIFS('Business - Dump'!$U:$U,'Business - Dump'!$B:$B,'Portfolio Wise '!$B10,'Business - Dump'!$A:$A,'Portfolio Wise '!$A10)/1.18 -> 5508.4746 | S10: =IFERROR(R10/Q10,0) -> 5508.4746 | T10: =IFERROR(F10/R10,0) -> 0 | U10: =IFERROR(R10/F10,0) -> 0 | V10: =SUMIFS('Business - Dump'!$G:$G,'Business - Dump'!$B:$B,'Portfolio Wise '!$B10,'Business - Dump'!$A:$A,'Portfolio Wise '!$A10) -> 92 | W10: =IFERROR(Q10/V10,0) -> 0.010869565 | X10: =IFERROR(N10/Q10,0) -> 1 | Y10: =IFERROR(O10/R10,0) -> 1 | Z10: =IFERROR(H10/Q10,0) -> 0 | AA10: =IFERROR(O10/R10,0) -> 1 | AB10: =IFERROR(AVERAGEIFS('Business - Dump'!$O:$O,'Business - Dump'!$B:$B,'Portfolio Wise '!$B10,'Business - Dump'!$A:$A,'Portfolio Wise '!$A10),0) -> 0.771 | AC10: =F10/SUMIFS('Campaign - Dump'!$Q:$Q,'Campaign - Dump'!$A:$A,'Portfolio Wise '!$A10) -> 0 | AD10: =IFERROR(N10/H10,0) -> 0
A11: Nov | B11: Standing Table - All Frames | C11: =SUMIFS('Campaign - Dump'!$N:$N,'Campaign - Dump'!$J:$J,'Portfolio Wise '!$B11,'Campaign - Dump'!$A:$A,'Portfolio Wise '!$A11) -> 0 | D11: =SUMIFS('Campaign - Dump'!$O:$O,'Campaign - Dump'!$J:$J,'Portfolio Wise '!$B11,'Campaign - Dump'!$A:$A,'Portfolio Wise '!$A11) -> 0 | E11: =IFERROR(D11/C11,0) -> 0 | F11: =SUMIFS('Campaign - Dump'!$Q:$Q,'Campaign - Dump'!$J:$J,'Portfolio Wise '!$B11,'Campaign - Dump'!$A:$A,'Portfolio Wise '!$A11) -> 0 | G11: =IFERROR(F11/D11,0) -> 0 | H11: =SUMIFS('Campaign - Dump'!$T:$T,'Campaign - Dump'!$J:$J,'Portfolio Wise '!$B11,'Campaign - Dump'!$A:$A,'Portfolio Wise '!$A11) -> 0 | I11: =IFERROR(H11/D11,0) -> 0 | J11: =SUMIFS('Campaign - Dump'!$U:$U,'Campaign - Dump'!$J:$J,'Portfolio Wise '!$B11,'Campaign - Dump'!$A:$A,'Portfolio Wise '!$A11) -> 0 | K11: =IFERROR(F11/J11,0) -> 0 | L11: =IFERROR(J11/F11,0) -> 0 | M11: =IFERROR(J11/H11,0) -> 0 | N11: =IFERROR(Q11-H11,0) -> 15 | O11: =IFERROR(R11-J11,0) -> 280254.24 | P11: =IFERROR(O11/N11,0) -> 18683.616 | Q11: =SUMIFS('Business - Dump'!$W:$W,'Business - Dump'!$B:$B,'Portfolio Wise '!$B11,'Business - Dump'!$A:$A,'Portfolio Wise '!$A11) -> 15 | R11: =SUMIFS('Business - Dump'!$U:$U,'Business - Dump'!$B:$B,'Portfolio Wise '!$B11,'Business - Dump'!$A:$A,'Portfolio Wise '!$A11)/1.18 -> 280254.24 | S11: =IFERROR(R11/Q11,0) -> 18683.616 | T11: =IFERROR(F11/R11,0) -> 0 | U11: =IFERROR(R11/F11,0) -> 0 | V11: =SUMIFS('Business - Dump'!$G:$G,'Business - Dump'!$B:$B,'Portfolio Wise '!$B11,'Business - Dump'!$A:$A,'Portfolio Wise '!$A11) -> 3527 | W11: =IFERROR(Q11/V11,0) -> 0.0042529062 | X11: =IFERROR(N11/Q11,0) -> 1 | Y11: =IFERROR(O11/R11,0) -> 1 | Z11: =IFERROR(H11/Q11,0) -> 0 | AA11: =IFERROR(O11/R11,0) -> 1 | AB11: =IFERROR(AVERAGEIFS('Business - Dump'!$O:$O,'Business - Dump'!$B:$B,'Portfolio Wise '!$B11,'Business - Dump'!$A:$A,'Portfolio Wise '!$A11),0) -> 0.88755 | AC11: =F11/SUMIFS('Campaign - Dump'!$Q:$Q,'Campaign - Dump'!$A:$A,'Portfolio Wise '!$A11) -> 0 | AD11: =IFERROR(N11/H11,0) -> 0
A12: Nov | B12: Standing Table - E1A | C12: =SUMIFS('Campaign - Dump'!$N:$N,'Campaign - Dump'!$J:$J,'Portfolio Wise '!$B12,'Campaign - Dump'!$A:$A,'Portfolio Wise '!$A12) -> 0 | D12: =SUMIFS('Campaign - Dump'!$O:$O,'Campaign - Dump'!$J:$J,'Portfolio Wise '!$B12,'Campaign - Dump'!$A:$A,'Portfolio Wise '!$A12) -> 0 | E12: =IFERROR(D12/C12,0) -> 0 | F12: =SUMIFS('Campaign - Dump'!$Q:$Q,'Campaign - Dump'!$J:$J,'Portfolio Wise '!$B12,'Campaign - Dump'!$A:$A,'Portfolio Wise '!$A12) -> 0 | G12: =IFERROR(F12/D12,0) -> 0 | H12: =SUMIFS('Campaign - Dump'!$T:$T,'Campaign - Dump'!$J:$J,'Portfolio Wise '!$B12,'Campaign - Dump'!$A:$A,'Portfolio Wise '!$A12) -> 0 | I12: =IFERROR(H12/D12,0) -> 0 | J12: =SUMIFS('Campaign - Dump'!$U:$U,'Campaign - Dump'!$J:$J,'Portfolio Wise '!$B12,'Campaign - Dump'!$A:$A,'Portfolio Wise '!$A12) -> 0 | K12: =IFERROR(F12/J12,0) -> 0 | L12: =IFERROR(J12/F12,0) -> 0 | M12: =IFERROR(J12/H12,0) -> 0 | N12: =IFERROR(Q12-H12,0) -> 0 | O12: =IFERROR(R12-J12,0) -> 0 | P12: =IFERROR(O12/N12,0) -> 0 | Q12: =SUMIFS('Business - Dump'!$W:$W,'Business - Dump'!$B:$B,'Portfolio Wise '!$B12,'Business - Dump'!$A:$A,'Portfolio Wise '!$A12) -> 0 | R12: =SUMIFS('Business - Dump'!$U:$U,'Business - Dump'!$B:$B,'Portfolio Wise '!$B12,'Business - Dump'!$A:$A,'Portfolio Wise '!$A12)/1.18 -> 0 | S12: =IFERROR(R12/Q12,0) -> 0 | T12: =IFERROR(F12/R12,0) -> 0 | U12: =IFERROR(R12/F12,0) -> 0 | V12: =SUMIFS('Business - Dump'!$G:$G,'Business - Dump'!$B:$B,'Portfolio Wise '!$B12,'Business - Dump'!$A:$A,'Portfolio Wise '!$A12) -> 0 | W12: =IFERROR(Q12/V12,0) -> 0 | X12: =IFERROR(N12/Q12,0) -> 0 | Y12: =IFERROR(O12/R12,0) -> 0 | Z12: =IFERROR(H12/Q12,0) -> 0 | AA12: =IFERROR(O12/R12,0) -> 0 | AB12: =IFERROR(AVERAGEIFS('Business - Dump'!$O:$O,'Business - Dump'!$B:$B,'Portfolio Wise '!$B12,'Business - Dump'!$A:$A,'Portfolio Wise '!$A12),0) -> 0 | AC12: =F12/SUMIFS('Campaign - Dump'!$Q:$Q,'Campaign - Dump'!$A:$A,'Portfolio Wise '!$A12) -> 0 | AD12: =IFERROR(N12/H12,0) -> 0
A13: Nov | B13: Standing Table - E1A | C13: =SUMIFS('Campaign - Dump'!$N:$N,'Campaign - Dump'!$J:$J,'Portfolio Wise '!$B13,'Campaign - Dump'!$A:$A,'Portfolio Wise '!$A13) -> 0 | D13: =SUMIFS('Campaign - Dump'!$O:$O,'Campaign - Dump'!$J:$J,'Portfolio Wise '!$B13,'Campaign - Dump'!$A:$A,'Portfolio Wise '!$A13) -> 0 | E13: =IFERROR(D13/C13,0) -> 0 | F13: =SUMIFS('Campaign - Dump'!$Q:$Q,'Campaign - Dump'!$J:$J,'Portfolio Wise '!$B13,'Campaign - Dump'!$A:$A,'Portfolio Wise '!$A13) -> 0 | G13: =IFERROR(F13/D13,0) -> 0 | H13: =SUMIFS('Campaign - Dump'!$T:$T,'Campaign - Dump'!$J:$J,'Portfolio Wise '!$B13,'Campaign - Dump'!$A:$A,'Portfolio Wise '!$A13) -> 0 | I13: =IFERROR(H13/D13,0) -> 0 | J13: =SUMIFS('Campaign - Dump'!$U:$U,'Campaign - Dump'!$J:$J,'Portfolio Wise '!$B13,'Campaign - Dump'!$A:$A,'Portfolio Wise '!$A13) -> 0 | K13: =IFERROR(F13/J13,0) -> 0 | L13: =IFERROR(J13/F13,0) -> 0 | M13: =IFERROR(J13/H13,0) -> 0 | N13: =IFERROR(Q13-H13,0) -> 0 | O13: =IFERROR(R13-J13,0) -> 0 | P13: =IFERROR(O13/N13,0) -> 0 | Q13: =SUMIFS('Business - Dump'!$W:$W,'Business - Dump'!$B:$B,'Portfolio Wise '!$B13,'Business - Dump'!$A:$A,'Portfolio Wise '!$A13) -> 0 | R13: =SUMIFS('Business - Dump'!$U:$U,'Business - Dump'!$B:$B,'Portfolio Wise '!$B13,'Business - Dump'!$A:$A,'Portfolio Wise '!$A13)/1.18 -> 0 | S13: =IFERROR(R13/Q13,0) -> 0 | T13: =IFERROR(F13/R13,0) -> 0 | U13: =IFERROR(R13/F13,0) -> 0 | V13: =SUMIFS('Business - Dump'!$G:$G,'Business - Dump'!$B:$B,'Portfolio Wise '!$B13,'Business - Dump'!$A:$A,'Portfolio Wise '!$A13) -> 0 | W13: =IFERROR(Q13/V13,0) -> 0 | X13: =IFERROR(N13/Q13,0) -> 0 | Y13: =IFERROR(O13/R13,0) -> 0 | Z13: =IFERROR(H13/Q13,0) -> 0 | AA13: =IFERROR(O13/R13,0) -> 0 | AB13: =IFERROR(AVERAGEIFS('Business - Dump'!$O:$O,'Business - Dump'!$B:$B,'Portfolio Wise '!$B13,'Business - Dump'!$A:$A,'Portfolio Wise '!$A13),0) -> 0 | AC13: =F13/SUMIFS('Campaign - Dump'!$Q:$Q,'Campaign - Dump'!$A:$A,'Portfolio Wise '!$A13) -> 0 | AD13: =IFERROR(N13/H13,0) -> 0
A14: Nov | B14: Standing Table - SB | C14: =SUMIFS('Campaign - Dump'!$N:$N,'Campaign - Dump'!$J:$J,'Portfolio Wise '!$B14,'Campaign - Dump'!$A:$A,'Portfolio Wise '!$A14) -> 0 | D14: =SUMIFS('Campaign - Dump'!$O:$O,'Campaign - Dump'!$J:$J,'Portfolio Wise '!$B14,'Campaign - Dump'!$A:$A,'Portfolio Wise '!$A14) -> 0 | E14: =IFERROR(D14/C14,0) -> 0 | F14: =SUMIFS('Campaign - Dump'!$Q:$Q,'Campaign - Dump'!$J:$J,'Portfolio Wise '!$B14,'Campaign - Dump'!$A:$A,'Portfolio Wise '!$A14) -> 0 | G14: =IFERROR(F14/D14,0) -> 0 | H14: =SUMIFS('Campaign - Dump'!$T:$T,'Campaign - Dump'!$J:$J,'Portfolio Wise '!$B14,'Campaign - Dump'!$A:$A,'Portfolio Wise '!$A14) -> 0 | I14: =IFERROR(H14/D14,0) -> 0 | J14: =SUMIFS('Campaign - Dump'!$U:$U,'Campaign - Dump'!$J:$J,'Portfolio Wise '!$B14,'Campaign - Dump'!$A:$A,'Portfolio Wise '!$A14) -> 0 | K14: =IFERROR(F14/J14,0) -> 0 | L14: =IFERROR(J14/F14,0) -> 0 | M14: =IFERROR(J14/H14,0) -> 0 | N14: 0 | O14: 0 | P14: =IFERROR(O14/N14,0) -> 0 | Q14: =SUMIFS('Business - Dump'!$W:$W,'Business - Dump'!$B:$B,'Portfolio Wise '!$B14,'Business - Dump'!$A:$A,'Portfolio Wise '!$A14) -> 0 | R14: =SUMIFS('Business - Dump'!$U:$U,'Business - Dump'!$B:$B,'Portfolio Wise '!$B14,'Business - Dump'!$A:$A,'Portfolio Wise '!$A14)/1.18 -> 0 | S14: =IFERROR(R14/Q14,0) -> 0 | T14: =IFERROR(F14/R14,0) -> 0 | U14: =IFERROR(R14/F14,0) -> 0 | V14: =SUMIFS('Business - Dump'!$G:$G,'Business - Dump'!$B:$B,'Portfolio Wise '!$B14,'Business - Dump'!$A:$A,'Portfolio Wise '!$A14) -> 0 | W14: =IFERROR(Q14/V14,0) -> 0 | X14: =IFERROR(N14/Q14,0) -> 0 | Y14: =IFERROR(O14/R14,0) -> 0 | Z14: =IFERROR(H14/Q14,0) -> 0 | AA14: =IFERROR(O14/R14,0) -> 0 | AB14: =IFERROR(AVERAGEIFS('Business - Dump'!$O:$O,'Business - Dump'!$B:$B,'Portfolio Wise '!$B14,'Business - Dump'!$A:$A,'Portfolio Wise '!$A14),0) -> 0 | AC14: =F14/SUMIFS('Campaign - Dump'!$Q:$Q,'Campaign - Dump'!$A:$A,'Portfolio Wise '!$A14) -> 0 | AD14: =IFERROR(N14/H14,0) -> 0
A15: Nov | B15: Standing Table - E3 | C15: =SUMIFS('Campaign - Dump'!$N:$N,'Campaign - Dump'!$J:$J,'Portfolio Wise '!$B15,'Campaign - Dump'!$A:$A,'Portfolio Wise '!$A15) -> 0 | D15: =SUMIFS('Campaign - Dump'!$O:$O,'Campaign - Dump'!$J:$J,'Portfolio Wise '!$B15,'Campaign - Dump'!$A:$A,'Portfolio Wise '!$A15) -> 0 | E15: =IFERROR(D15/C15,0) -> 0 | F15: =SUMIFS('Campaign - Dump'!$Q:$Q,'Campaign - Dump'!$J:$J,'Portfolio Wise '!$B15,'Campaign - Dump'!$A:$A,'Portfolio Wise '!$A15) -> 0 | G15: =IFERROR(F15/D15,0) -> 0 | H15: =SUMIFS('Campaign - Dump'!$T:$T,'Campaign - Dump'!$J:$J,'Portfolio Wise '!$B15,'Campaign - Dump'!$A:$A,'Portfolio Wise '!$A15) -> 0 | I15: =IFERROR(H15/D15,0) -> 0 | J15: =SUMIFS('Campaign - Dump'!$U:$U,'Campaign - Dump'!$J:$J,'Portfolio Wise '!$B15,'Campaign - Dump'!$A:$A,'Portfolio Wise '!$A15) -> 0 | K15: =IFERROR(F15/J15,0) -> 0 | L15: =IFERROR(J15/F15,0) -> 0 | M15: =IFERROR(J15/H15,0) -> 0 | N15: =IFERROR(Q15-H15,0) -> 0 | O15: =IFERROR(R15-J15,0) -> 0 | P15: =IFERROR(O15/N15,0) -> 0 | Q15: =SUMIFS('Business - Dump'!$W:$W,'Business - Dump'!$B:$B,'Portfolio Wise '!$B15,'Business - Dump'!$A:$A,'Portfolio Wise '!$A15) -> 0 | R15: =SUMIFS('Business - Dump'!$U:$U,'Business - Dump'!$B:$B,'Portfolio Wise '!$B15,'Business - Dump'!$A:$A,'Portfolio Wise '!$A15)/1.18 -> 0 | S15: =IFERROR(R15/Q15,0) -> 0 | T15: =IFERROR(F15/R15,0) -> 0 | U15: =IFERROR(R15/F15,0) -> 0 | V15: =SUMIFS('Business - Dump'!$G:$G,'Business - Dump'!$B:$B,'Portfolio Wise '!$B15,'Business - Dump'!$A:$A,'Portfolio Wise '!$A15) -> 0 | W15: =IFERROR(Q15/V15,0) -> 0 | X15: =IFERROR(N15/Q15,0) -> 0 | Y15: =IFERROR(O15/R15,0) -> 0 | Z15: =IFERROR(H15/Q15,0) -> 0 | AA15: =IFERROR(O15/R15,0) -> 0 | AB15: =IFERROR(AVERAGEIFS('Business - Dump'!$O:$O,'Business - Dump'!$B:$B,'Portfolio Wise '!$B15,'Business - Dump'!$A:$A,'Portfolio Wise '!$A15),0) -> 0 | AC15: =F15/SUMIFS('Campaign - Dump'!$Q:$Q,'Campaign - Dump'!$A:$A,'Portfolio Wise '!$A15) -> 0 | AD15: =IFERROR(N15/H15,0) -> 0
A16: Nov | B16: Desk Cable Tray | C16: =SUMIFS('Campaign - Dump'!$N:$N,'Campaign - Dump'!$J:$J,'Portfolio Wise '!$B16,'Campaign - Dump'!$A:$A,'Portfolio Wise '!$A16) -> 0 | D16: =SUMIFS('Campaign - Dump'!$O:$O,'Campaign - Dump'!$J:$J,'Portfolio Wise '!$B16,'Campaign - Dump'!$A:$A,'Portfolio Wise '!$A16) -> 0 | E16: =IFERROR(D16/C16,0) -> 0 | F16: =SUMIFS('Campaign - Dump'!$Q:$Q,'Campaign - Dump'!$J:$J,'Portfolio Wise '!$B16,'Campaign - Dump'!$A:$A,'Portfolio Wise '!$A16) -> 0 | G16: =IFERROR(F16/D16,0) -> 0 | H16: =SUMIFS('Campaign - Dump'!$T:$T,'Campaign - Dump'!$J:$J,'Portfolio Wise '!$B16,'Campaign - Dump'!$A:$A,'Portfolio Wise '!$A16) -> 0 | I16: =IFERROR(H16/D16,0) -> 0 | J16: =SUMIFS('Campaign - Dump'!$U:$U,'Campaign - Dump'!$J:$J,'Portfolio Wise '!$B16,'Campaign - Dump'!$A:$A,'Portfolio Wise '!$A16) -> 0 | K16: =IFERROR(F16/J16,0) -> 0 | L16: =IFERROR(J16/F16,0) -> 0 | M16: =IFERROR(J16/H16,0) -> 0 | N16: =IFERROR(Q16-H16,0) -> 3 | O16: =IFERROR(R16-J16,0) -> 4135.5932 | P16: =IFERROR(O16/N16,0) -> 1378.5311 | Q16: =SUMIFS('Business - Dump'!$W:$W,'Business - Dump'!$B:$B,'Portfolio Wise '!$B16,'Business - Dump'!$A:$A,'Portfolio Wise '!$A16) -> 3 | R16: =SUMIFS('Business - Dump'!$U:$U,'Business - Dump'!$B:$B,'Portfolio Wise '!$B16,'Business - Dump'!$A:$A,'Portfolio Wise '!$A16)/1.18 -> 4135.5932 | S16: =IFERROR(R16/Q16,0) -> 1378.5311 | T16: =IFERROR(F16/R16,0) -> 0 | U16: =IFERROR(R16/F16,0) -> 0 | V16: =SUMIFS('Business - Dump'!$G:$G,'Business - Dump'!$B:$B,'Portfolio Wise '!$B16,'Business - Dump'!$A:$A,'Portfolio Wise '!$A16) -> 133 | W16: =IFERROR(Q16/V16,0) -> 0.022556391 | X16: =IFERROR(N16/Q16,0) -> 1 | Y16: =IFERROR(O16/R16,0) -> 1 | Z16: =IFERROR(H16/Q16,0) -> 0 | AA16: =IFERROR(O16/R16,0) -> 1 | AB16: =IFERROR(AVERAGEIFS('Business - Dump'!$O:$O,'Business - Dump'!$B:$B,'Portfolio Wise '!$B16,'Business - Dump'!$A:$A,'Portfolio Wise '!$A16),0) -> 0.9 | AC16: =F16/SUMIFS('Campaign - Dump'!$Q:$Q,'Campaign - Dump'!$A:$A,'Portfolio Wise '!$A16) -> 0 | AD16: =IFERROR(N16/H16,0) -> 0
A17: Nov | B17: Extension & Holder | C17: =SUMIFS('Campaign - Dump'!$N:$N,'Campaign - Dump'!$J:$J,'Portfolio Wise '!$B17,'Campaign - Dump'!$A:$A,'Portfolio Wise '!$A17) -> 0 | D17: =SUMIFS('Campaign - Dump'!$O:$O,'Campaign - Dump'!$J:$J,'Portfolio Wise '!$B17,'Campaign - Dump'!$A:$A,'Portfolio Wise '!$A17) -> 0 | E17: =IFERROR(D17/C17,0) -> 0 | F17: =SUMIFS('Campaign - Dump'!$Q:$Q,'Campaign - Dump'!$J:$J,'Portfolio Wise '!$B17,'Campaign - Dump'!$A:$A,'Portfolio Wise '!$A17) -> 0 | G17: =IFERROR(F17/D17,0) -> 0 | H17: =SUMIFS('Campaign - Dump'!$T:$T,'Campaign - Dump'!$J:$J,'Portfolio Wise '!$B17,'Campaign - Dump'!$A:$A,'Portfolio Wise '!$A17) -> 0 | I17: =IFERROR(H17/D17,0) -> 0 | J17: =SUMIFS('Campaign - Dump'!$U:$U,'Campaign - Dump'!$J:$J,'Portfolio Wise '!$B17,'Campaign - Dump'!$A:$A,'Portfolio Wise '!$A17) -> 0 | K17: =IFERROR(F17/J17,0) -> 0 | L17: =IFERROR(J17/F17,0) -> 0 | M17: =IFERROR(J17/H17,0) -> 0 | N17: =IFERROR(Q17-H17,0) -> 8 | O17: =IFERROR(R17-J17,0) -> 7923.7288 | P17: =IFERROR(O17/N17,0) -> 990.4661 | Q17: =SUMIFS('Business - Dump'!$W:$W,'Business - Dump'!$B:$B,'Portfolio Wise '!$B17,'Business - Dump'!$A:$A,'Portfolio Wise '!$A17) -> 8 | R17: =SUMIFS('Business - Dump'!$U:$U,'Business - Dump'!$B:$B,'Portfolio Wise '!$B17,'Business - Dump'!$A:$A,'Portfolio Wise '!$A17)/1.18 -> 7923.7288 | S17: =IFERROR(R17/Q17,0) -> 990.4661 | T17: =IFERROR(F17/R17,0) -> 0 | U17: =IFERROR(R17/F17,0) -> 0 | V17: =SUMIFS('Business - Dump'!$G:$G,'Business - Dump'!$B:$B,'Portfolio Wise '!$B17,'Business - Dump'!$A:$A,'Portfolio Wise '!$A17) -> 302 | W17: =IFERROR(Q17/V17,0) -> 0.026490066 | X17: =IFERROR(N17/Q17,0) -> 1 | Y17: =IFERROR(O17/R17,0) -> 1 | Z17: =IFERROR(H17/Q17,0) -> 0 | AA17: =IFERROR(O17/R17,0) -> 1 | AB17: =IFERROR(AVERAGEIFS('Business - Dump'!$O:$O,'Business - Dump'!$B:$B,'Portfolio Wise '!$B17,'Business - Dump'!$A:$A,'Portfolio Wise '!$A17),0) -> 0.8816 | AC17: =F17/SUMIFS('Campaign - Dump'!$Q:$Q,'Campaign - Dump'!$A:$A,'Portfolio Wise '!$A17) -> 0 | AD17: =IFERROR(N17/H17,0) -> 0
A18: Nov | B18: Standing Table - E4 | C18: =SUMIFS('Campaign - Dump'!$N:$N,'Campaign - Dump'!$J:$J,'Portfolio Wise '!$B18,'Campaign - Dump'!$A:$A,'Portfolio Wise '!$A18) -> 0 | D18: =SUMIFS('Campaign - Dump'!$O:$O,'Campaign - Dump'!$J:$J,'Portfolio Wise '!$B18,'Campaign - Dump'!$A:$A,'Portfolio Wise '!$A18) -> 0 | E18: =IFERROR(D18/C18,0) -> 0 | F18: =SUMIFS('Campaign - Dump'!$Q:$Q,'Campaign - Dump'!$J:$J,'Portfolio Wise '!$B18,'Campaign - Dump'!$A:$A,'Portfolio Wise '!$A18) -> 0 | G18: =IFERROR(F18/D18,0) -> 0 | H18: =SUMIFS('Campaign - Dump'!$T:$T,'Campaign - Dump'!$J:$J,'Portfolio Wise '!$B18,'Campaign - Dump'!$A:$A,'Portfolio Wise '!$A18) -> 0 | I18: =IFERROR(H18/D18,0) -> 0 | J18: =SUMIFS('Campaign - Dump'!$U:$U,'Campaign - Dump'!$J:$J,'Portfolio Wise '!$B18,'Campaign - Dump'!$A:$A,'Portfolio Wise '!$A18) -> 0 | K18: =IFERROR(F18/J18,0) -> 0 | L18: =IFERROR(J18/F18,0) -> 0 | M18: =IFERROR(J18/H18,0) -> 0 | N18: =IFERROR(Q18-H18,0) -> 0 | O18: =IFERROR(R18-J18,0) -> 0 | P18: =IFERROR(O18/N18,0) -> 0 | Q18: =SUMIFS('Business - Dump'!$W:$W,'Business - Dump'!$B:$B,'Portfolio Wise '!$B18,'Business - Dump'!$A:$A,'Portfolio Wise '!$A18) -> 0 | R18: =SUMIFS('Business - Dump'!$U:$U,'Business - Dump'!$B:$B,'Portfolio Wise '!$B18,'Business - Dump'!$A:$A,'Portfolio Wise '!$A18)/1.18 -> 0 | S18: =IFERROR(R18/Q18,0) -> 0 | T18: =IFERROR(F18/R18,0) -> 0 | U18: =IFERROR(R18/F18,0) -> 0 | V18: =SUMIFS('Business - Dump'!$G:$G,'Business - Dump'!$B:$B,'Portfolio Wise '!$B18,'Business - Dump'!$A:$A,'Portfolio Wise '!$A18) -> 0 | W18: =IFERROR(Q18/V18,0) -> 0 | X18: =IFERROR(N18/Q18,0) -> 0 | Y18: =IFERROR(O18/R18,0) -> 0 | Z18: =IFERROR(H18/Q18,0) -> 0 | AA18: =IFERROR(O18/R18,0) -> 0 | AB18: =IFERROR(AVERAGEIFS('Business - Dump'!$O:$O,'Business - Dump'!$B:$B,'Portfolio Wise '!$B18,'Business - Dump'!$A:$A,'Portfolio Wise '!$A18),0) -> 0 | AC18: =F18/SUMIFS('Campaign - Dump'!$Q:$Q,'Campaign - Dump'!$A:$A,'Portfolio Wise '!$A18) -> 0 | AD18: =IFERROR(N18/H18,0) -> 0
A19: Nov | B19: Standing Table - E4 | C19: =SUMIFS('Campaign - Dump'!$N:$N,'Campaign - Dump'!$J:$J,'Portfolio Wise '!$B19,'Campaign - Dump'!$A:$A,'Portfolio Wise '!$A19) -> 0 | D19: =SUMIFS('Campaign - Dump'!$O:$O,'Campaign - Dump'!$J:$J,'Portfolio Wise '!$B19,'Campaign - Dump'!$A:$A,'Portfolio Wise '!$A19) -> 0 | E19: =IFERROR(D19/C19,0) -> 0 | F19: =SUMIFS('Campaign - Dump'!$Q:$Q,'Campaign - Dump'!$J:$J,'Portfolio Wise '!$B19,'Campaign - Dump'!$A:$A,'Portfolio Wise '!$A19) -> 0 | G19: =IFERROR(F19/D19,0) -> 0 | H19: =SUMIFS('Campaign - Dump'!$T:$T,'Campaign - Dump'!$J:$J,'Portfolio Wise '!$B19,'Campaign - Dump'!$A:$A,'Portfolio Wise '!$A19) -> 0 | I19: =IFERROR(H19/D19,0) -> 0 | J19: =SUMIFS('Campaign - Dump'!$U:$U,'Campaign - Dump'!$J:$J,'Portfolio Wise '!$B19,'Campaign - Dump'!$A:$A,'Portfolio Wise '!$A19) -> 0 | K19: =IFERROR(F19/J19,0) -> 0 | L19: =IFERROR(J19/F19,0) -> 0 | M19: =IFERROR(J19/H19,0) -> 0 | N19: =IFERROR(Q19-H19,0) -> 0 | O19: =IFERROR(R19-J19,0) -> 0 | P19: =IFERROR(O19/N19,0) -> 0 | Q19: =SUMIFS('Business - Dump'!$W:$W,'Business - Dump'!$B:$B,'Portfolio Wise '!$B19,'Business - Dump'!$A:$A,'Portfolio Wise '!$A19) -> 0 | R19: =SUMIFS('Business - Dump'!$U:$U,'Business - Dump'!$B:$B,'Portfolio Wise '!$B19,'Business - Dump'!$A:$A,'Portfolio Wise '!$A19)/1.18 -> 0 | S19: =IFERROR(R19/Q19,0) -> 0 | T19: =IFERROR(F19/R19,0) -> 0 | U19: =IFERROR(R19/F19,0) -> 0 | V19: =SUMIFS('Business - Dump'!$G:$G,'Business - Dump'!$B:$B,'Portfolio Wise '!$B19,'Business - Dump'!$A:$A,'Portfolio Wise '!$A19) -> 0 | W19: =IFERROR(Q19/V19,0) -> 0 | X19: =IFERROR(N19/Q19,0) -> 0 | Y19: =IFERROR(O19/R19,0) -> 0 | Z19: =IFERROR(H19/Q19,0) -> 0 | AA19: =IFERROR(O19/R19,0) -> 0 | AB19: =IFERROR(AVERAGEIFS('Business - Dump'!$O:$O,'Business - Dump'!$B:$B,'Portfolio Wise '!$B19,'Business - Dump'!$A:$A,'Portfolio Wise '!$A19),0) -> 0 | AC19: =F19/SUMIFS('Campaign - Dump'!$Q:$Q,'Campaign - Dump'!$A:$A,'Portfolio Wise '!$A19) -> 0 | AD19: =IFERROR(N19/H19,0) -> 0
A20: Nov | B20: Standing Table - M8 | C20: =SUMIFS('Campaign - Dump'!$N:$N,'Campaign - Dump'!$J:$J,'Portfolio Wise '!$B20,'Campaign - Dump'!$A:$A,'Portfolio Wise '!$A20) -> 0 | D20: =SUMIFS('Campaign - Dump'!$O:$O,'Campaign - Dump'!$J:$J,'Portfolio Wise '!$B20,'Campaign - Dump'!$A:$A,'Portfolio Wise '!$A20) -> 0 | E20: =IFERROR(D20/C20,0) -> 0 | F20: =SUMIFS('Campaign - Dump'!$Q:$Q,'Campaign - Dump'!$J:$J,'Portfolio Wise '!$B20,'Campaign - Dump'!$A:$A,'Portfolio Wise '!$A20) -> 0 | G20: =IFERROR(F20/D20,0) -> 0 | H20: =SUMIFS('Campaign - Dump'!$T:$T,'Campaign - Dump'!$J:$J,'Portfolio Wise '!$B20,'Campaign - Dump'!$A:$A,'Portfolio Wise '!$A20) -> 0 | I20: =IFERROR(H20/D20,0) -> 0 | J20: =SUMIFS('Campaign - Dump'!$U:$U,'Campaign - Dump'!$J:$J,'Portfolio Wise '!$B20,'Campaign - Dump'!$A:$A,'Portfolio Wise '!$A20) -> 0 | K20: =IFERROR(F20/J20,0) -> 0 | L20: =IFERROR(J20/F20,0) -> 0 | M20: =IFERROR(J20/H20,0) -> 0 | N20: =IFERROR(Q20-H20,0) -> 21 | O20: =IFERROR(R20-J20,0) -> 322103.39 | P20: =IFERROR(O20/N20,0) -> 15338.257 | Q20: =SUMIFS('Business - Dump'!$W:$W,'Business - Dump'!$B:$B,'Portfolio Wise '!$B20,'Business - Dump'!$A:$A,'Portfolio Wise '!$A20) -> 21 | R20: =SUMIFS('Business - Dump'!$U:$U,'Business - Dump'!$B:$B,'Portfolio Wise '!$B20,'Business - Dump'!$A:$A,'Portfolio Wise '!$A20)/1.18 -> 322103.39 | S20: =IFERROR(R20/Q20,0) -> 15338.257 | T20: =IFERROR(F20/R20,0) -> 0 | U20: =IFERROR(R20/F20,0) -> 0 | V20: =SUMIFS('Business - Dump'!$G:$G,'Business - Dump'!$B:$B,'Portfolio Wise '!$B20,'Business - Dump'!$A:$A,'Portfolio Wise '!$A20) -> 5776 | W20: =IFERROR(Q20/V20,0) -> 0.0036357341 | X20: =IFERROR(N20/Q20,0) -> 1 | Y20: =IFERROR(O20/R20,0) -> 1 | Z20: =IFERROR(H20/Q20,0) -> 0 | AA20: =IFERROR(O20/R20,0) -> 1 | AB20: =IFERROR(AVERAGEIFS('Business - Dump'!$O:$O,'Business - Dump'!$B:$B,'Portfolio Wise '!$B20,'Business - Dump'!$A:$A,'Portfolio Wise '!$A20),0) -> 0.83862 | AC20: =F20/SUMIFS('Campaign - Dump'!$Q:$Q,'Campaign - Dump'!$A:$A,'Portfolio Wise '!$A20) -> 0 | AD20: =IFERROR(N20/H20,0) -> 0
A21: Nov | B21: Video Funnel | C21: =SUMIFS('Campaign - Dump'!$N:$N,'Campaign - Dump'!$J:$J,'Portfolio Wise '!$B21,'Campaign - Dump'!$A:$A,'Portfolio Wise '!$A21) -> 0 | D21: =SUMIFS('Campaign - Dump'!$O:$O,'Campaign - Dump'!$J:$J,'Portfolio Wise '!$B21,'Campaign - Dump'!$A:$A,'Portfolio Wise '!$A21) -> 0 | E21: =IFERROR(D21/C21,0) -> 0 | F21: =SUMIFS('Campaign - Dump'!$Q:$Q,'Campaign - Dump'!$J:$J,'Portfolio Wise '!$B21,'Campaign - Dump'!$A:$A,'Portfolio Wise '!$A21) -> 0 | G21: =IFERROR(F21/D21,0) -> 0 | H21: =SUMIFS('Campaign - Dump'!$T:$T,'Campaign - Dump'!$J:$J,'Portfolio Wise '!$B21,'Campaign - Dump'!$A:$A,'Portfolio Wise '!$A21) -> 0 | I21: =IFERROR(H21/D21,0) -> 0 | J21: =SUMIFS('Campaign - Dump'!$U:$U,'Campaign - Dump'!$J:$J,'Portfolio Wise '!$B21,'Campaign - Dump'!$A:$A,'Portfolio Wise '!$A21) -> 0 | K21: =IFERROR(F21/J21,0) -> 0 | L21: =IFERROR(J21/F21,0) -> 0 | M21: =IFERROR(J21/H21,0) -> 0 | N21: =IFERROR(Q21-H21,0) -> 0 | O21: =IFERROR(R21-J21,0) -> 0 | P21: =IFERROR(O21/N21,0) -> 0 | Q21: =SUMIFS('Business - Dump'!$W:$W,'Business - Dump'!$B:$B,'Portfolio Wise '!$B21,'Business - Dump'!$A:$A,'Portfolio Wise '!$A21) -> 0 | R21: =SUMIFS('Business - Dump'!$U:$U,'Business - Dump'!$B:$B,'Portfolio Wise '!$B21,'Business - Dump'!$A:$A,'Portfolio Wise '!$A21)/1.18 -> 0 | S21: =IFERROR(R21/Q21,0) -> 0 | T21: =IFERROR(F21/R21,0) -> 0 | U21: =IFERROR(R21/F21,0) -> 0 | V21: =SUMIFS('Business - Dump'!$G:$G,'Business - Dump'!$B:$B,'Portfolio Wise '!$B21,'Business - Dump'!$A:$A,'Portfolio Wise '!$A21) -> 0 | W21: =IFERROR(Q21/V21,0) -> 0 | X21: =IFERROR(N21/Q21,0) -> 0 | Y21: =IFERROR(O21/R21,0) -> 0 | Z21: =IFERROR(H21/Q21,0) -> 0 | AA21: =IFERROR(O21/R21,0) -> 0 | AB21: =IFERROR(AVERAGEIFS('Business - Dump'!$O:$O,'Business - Dump'!$B:$B,'Portfolio Wise '!$B21,'Business - Dump'!$A:$A,'Portfolio Wise '!$A21),0) -> 0 | AC21: =F21/SUMIFS('Campaign - Dump'!$Q:$Q,'Campaign - Dump'!$A:$A,'Portfolio Wise '!$A21) -> 0 | AD21: =IFERROR(N21/H21,0) -> 0
A22: Nov | B22: Keyboard Tray | C22: =SUMIFS('Campaign - Dump'!$N:$N,'Campaign - Dump'!$J:$J,'Portfolio Wise '!$B22,'Campaign - Dump'!$A:$A,'Portfolio Wise '!$A22) -> 0 | D22: =SUMIFS('Campaign - Dump'!$O:$O,'Campaign - Dump'!$J:$J,'Portfolio Wise '!$B22,'Campaign - Dump'!$A:$A,'Portfolio Wise '!$A22) -> 0 | E22: =IFERROR(D22/C22,0) -> 0 | F22: =SUMIFS('Campaign - Dump'!$Q:$Q,'Campaign - Dump'!$J:$J,'Portfolio Wise '!$B22,'Campaign - Dump'!$A:$A,'Portfolio Wise '!$A22) -> 0 | G22: =IFERROR(F22/D22,0) -> 0 | H22: =SUMIFS('Campaign - Dump'!$T:$T,'Campaign - Dump'!$J:$J,'Portfolio Wise '!$B22,'Campaign - Dump'!$A:$A,'Portfolio Wise '!$A22) -> 0 | I22: =IFERROR(H22/D22,0) -> 0 | J22: =SUMIFS('Campaign - Dump'!$U:$U,'Campaign - Dump'!$J:$J,'Portfolio Wise '!$B22,'Campaign - Dump'!$A:$A,'Portfolio Wise '!$A22) -> 0 | K22: =IFERROR(F22/J22,0) -> 0 | L22: =IFERROR(J22/F22,0) -> 0 | M22: =IFERROR(J22/H22,0) -> 0 | N22: =IFERROR(Q22-H22,0) -> 0 | O22: =IFERROR(R22-J22,0) -> 0 | P22: =IFERROR(O22/N22,0) -> 0 | Q22: =SUMIFS('Business - Dump'!$W:$W,'Business - Dump'!$B:$B,'Portfolio Wise '!$B22,'Business - Dump'!$A:$A,'Portfolio Wise '!$A22) -> 0 | R22: =SUMIFS('Business - Dump'!$U:$U,'Business - Dump'!$B:$B,'Portfolio Wise '!$B22,'Business - Dump'!$A:$A,'Portfolio Wise '!$A22)/1.18 -> 0 | S22: =IFERROR(R22/Q22,0) -> 0 | T22: =IFERROR(F22/R22,0) -> 0 | U22: =IFERROR(R22/F22,0) -> 0 | V22: =SUMIFS('Business - Dump'!$G:$G,'Business - Dump'!$B:$B,'Portfolio Wise '!$B22,'Business - Dump'!$A:$A,'Portfolio Wise '!$A22) -> 0 | W22: =IFERROR(Q22/V22,0) -> 0 | X22: =IFERROR(N22/Q22,0) -> 0 | Y22: =IFERROR(O22/R22,0) -> 0 | Z22: =IFERROR(H22/Q22,0) -> 0 | AA22: =IFERROR(O22/R22,0) -> 0 | AB22: =IFERROR(AVERAGEIFS('Business - Dump'!$O:$O,'Business - Dump'!$B:$B,'Portfolio Wise '!$B22,'Business - Dump'!$A:$A,'Portfolio Wise '!$A22),0) -> 0 | AC22: =F22/SUMIFS('Campaign - Dump'!$Q:$Q,'Campaign - Dump'!$A:$A,'Portfolio Wise '!$A22) -> 0 | AD22: =IFERROR(N22/H22,0) -> 0
A23: Nov | B23: Footrests | C23: =SUMIFS('Campaign - Dump'!$N:$N,'Campaign - Dump'!$J:$J,'Portfolio Wise '!$B23,'Campaign - Dump'!$A:$A,'Portfolio Wise '!$A23) -> 0 | D23: =SUMIFS('Campaign - Dump'!$O:$O,'Campaign - Dump'!$J:$J,'Portfolio Wise '!$B23,'Campaign - Dump'!$A:$A,'Portfolio Wise '!$A23) -> 0 | E23: =IFERROR(D23/C23,0) -> 0 | F23: =SUMIFS('Campaign - Dump'!$Q:$Q,'Campaign - Dump'!$J:$J,'Portfolio Wise '!$B23,'Campaign - Dump'!$A:$A,'Portfolio Wise '!$A23) -> 0 | G23: =IFERROR(F23/D23,0) -> 0 | H23: =SUMIFS('Campaign - Dump'!$T:$T,'Campaign - Dump'!$J:$J,'Portfolio Wise '!$B23,'Campaign - Dump'!$A:$A,'Portfolio Wise '!$A23) -> 0 | I23: =IFERROR(H23/D23,0) -> 0 | J23: =SUMIFS('Campaign - Dump'!$U:$U,'Campaign - Dump'!$J:$J,'Portfolio Wise '!$B23,'Campaign - Dump'!$A:$A,'Portfolio Wise '!$A23) -> 0 | K23: =IFERROR(F23/J23,0) -> 0 | L23: =IFERROR(J23/F23,0) -> 0 | M23: =IFERROR(J23/H23,0) -> 0 | N23: =IFERROR(Q23-H23,0) -> 0 | O23: =IFERROR(R23-J23,0) -> 0 | P23: =IFERROR(O23/N23,0) -> 0 | Q23: =SUMIFS('Business - Dump'!$W:$W,'Business - Dump'!$B:$B,'Portfolio Wise '!$B23,'Business - Dump'!$A:$A,'Portfolio Wise '!$A23) -> 0 | R23: =SUMIFS('Business - Dump'!$U:$U,'Business - Dump'!$B:$B,'Portfolio Wise '!$B23,'Business - Dump'!$A:$A,'Portfolio Wise '!$A23)/1.18 -> 0 | S23: =IFERROR(R23/Q23,0) -> 0 | T23: =IFERROR(F23/R23,0) -> 0 | U23: =IFERROR(R23/F23,0) -> 0 | V23: =SUMIFS('Business - Dump'!$G:$G,'Business - Dump'!$B:$B,'Portfolio Wise '!$B23,'Business - Dump'!$A:$A,'Portfolio Wise '!$A23) -> 0 | W23: =IFERROR(Q23/V23,0) -> 0 | X23: =IFERROR(N23/Q23,0) -> 0 | Y23: =IFERROR(O23/R23,0) -> 0 | Z23: =IFERROR(H23/Q23,0) -> 0 | AA23: =IFERROR(O23/R23,0) -> 0 | AB23: =IFERROR(AVERAGEIFS('Business - Dump'!$O:$O,'Business - Dump'!$B:$B,'Portfolio Wise '!$B23,'Business - Dump'!$A:$A,'Portfolio Wise '!$A23),0) -> 0 | AC23: =F23/SUMIFS('Campaign - Dump'!$Q:$Q,'Campaign - Dump'!$A:$A,'Portfolio Wise '!$A23) -> 0 | AD23: =IFERROR(N23/H23,0) -> 0
A24: Nov | B24: Single Leg Gas | C24: =SUMIFS('Campaign - Dump'!$N:$N,'Campaign - Dump'!$J:$J,'Portfolio Wise '!$B24,'Campaign - Dump'!$A:$A,'Portfolio Wise '!$A24) -> 0 | D24: =SUMIFS('Campaign - Dump'!$O:$O,'Campaign - Dump'!$J:$J,'Portfolio Wise '!$B24,'Campaign - Dump'!$A:$A,'Portfolio Wise '!$A24) -> 0 | E24: =IFERROR(D24/C24,0) -> 0 | F24: =SUMIFS('Campaign - Dump'!$Q:$Q,'Campaign - Dump'!$J:$J,'Portfolio Wise '!$B24,'Campaign - Dump'!$A:$A,'Portfolio Wise '!$A24) -> 0 | G24: =IFERROR(F24/D24,0) -> 0 | H24: =SUMIFS('Campaign - Dump'!$T:$T,'Campaign - Dump'!$J:$J,'Portfolio Wise '!$B24,'Campaign - Dump'!$A:$A,'Portfolio Wise '!$A24) -> 0 | I24: =IFERROR(H24/D24,0) -> 0 | J24: =SUMIFS('Campaign - Dump'!$U:$U,'Campaign - Dump'!$J:$J,'Portfolio Wise '!$B24,'Campaign - Dump'!$A:$A,'Portfolio Wise '!$A24) -> 0 | K24: =IFERROR(F24/J24,0) -> 0 | L24: =IFERROR(J24/F24,0) -> 0 | M24: =IFERROR(J24/H24,0) -> 0 | N24: =IFERROR(Q24-H24,0) -> 0 | O24: =IFERROR(R24-J24,0) -> 0 | P24: =IFERROR(O24/N24,0) -> 0 | Q24: =SUMIFS('Business - Dump'!$W:$W,'Business - Dump'!$B:$B,'Portfolio Wise '!$B24,'Business - Dump'!$A:$A,'Portfolio Wise '!$A24) -> 0 | R24: =SUMIFS('Business - Dump'!$U:$U,'Business - Dump'!$B:$B,'Portfolio Wise '!$B24,'Business - Dump'!$A:$A,'Portfolio Wise '!$A24)/1.18 -> 0 | S24: =IFERROR(R24/Q24,0) -> 0 | T24: =IFERROR(F24/R24,0) -> 0 | U24: =IFERROR(R24/F24,0) -> 0 | V24: =SUMIFS('Business - Dump'!$G:$G,'Business - Dump'!$B:$B,'Portfolio Wise '!$B24,'Business - Dump'!$A:$A,'Portfolio Wise '!$A24) -> 0 | W24: =IFERROR(Q24/V24,0) -> 0 | X24: =IFERROR(N24/Q24,0) -> 0 | Y24: =IFERROR(O24/R24,0) -> 0 | Z24: =IFERROR(H24/Q24,0) -> 0 | AA24: =IFERROR(O24/R24,0) -> 0 | AB24: =IFERROR(AVERAGEIFS('Business - Dump'!$O:$O,'Business - Dump'!$B:$B,'Portfolio Wise '!$B24,'Business - Dump'!$A:$A,'Portfolio Wise '!$A24),0) -> 0 | AC24: =F24/SUMIFS('Campaign - Dump'!$Q:$Q,'Campaign - Dump'!$A:$A,'Portfolio Wise '!$A24) -> 0 | AD24: =IFERROR(N24/H24,0) -> 0
A25: Nov | B25: Total Nov | C25: =SUM(C2:C24) -> 4056219 | D25: =SUM(D2:D24) -> 12959 | E25: =IFERROR(D25/C25,0) -> 0.0031948472 | F25: =SUM(F2:F24) -> 163075.05 | G25: =IFERROR(F25/D25,0) -> 12.583922 | H25: =SUM(H2:H24) -> 49 | I25: =IFERROR(H25/D25,0) -> 0.003781156 | J25: =SUM(J2:J24) -> 843788.92 | K25: =IFERROR(F25/J25,0) -> 0.19326522 | L25: =IFERROR(J25/F25,0) -> 5.1742368 | M25: =IFERROR(J25/H25,0) -> 17220.182 | N25: =SUM(N2:N24) -> 104 | O25: =SUM(O2:O24) -> 1820739 | P25: =IFERROR(O25/N25,0) -> 17507.106 | Q25: =SUM(Q2:Q24) -> 104 | R25: =SUM(R2:R24) -> 1820739 | S25: =IFERROR(R25/Q25,0) -> 17507.106 | T25: =IFERROR(F25/R25,0) -> 0.089565309 | U25: =IFERROR(R25/F25,0) -> 11.165037 | V25: =SUM(V2:V24) -> 22980 | W25: =IFERROR(Q25/V25,0) -> 0.0045256745 | X25: =IFERROR(N25/Q25,0) -> 1 | Y25: =IFERROR(O25/R25,0) -> 1 | Z25: =IFERROR(H25/Q25,0) -> 0.47115385 | AA25: =IFERROR(O25/R25,0) -> 1 | AB25: =IFERROR(AVERAGEIFS('Business - Dump'!$O:$O,'Business - Dump'!$B:$B,'Portfolio Wise '!$B25,'Business - Dump'!$A:$A,'Portfolio Wise '!$A25),0) -> 0 | AC25: =F25/SUMIFS('Campaign - Dump'!$Q:$Q,'Campaign - Dump'!$A:$A,'Portfolio Wise '!$A25) -> 1 | AD25: =IFERROR(N25/H25,0) -> 2.122449
A26: Dec | B26: Sales Day | C26: =SUMIFS('Campaign - Dump'!$N:$N,'Campaign - Dump'!$J:$J,'Portfolio Wise '!$B26,'Campaign - Dump'!$A:$A,'Portfolio Wise '!$A26) -> 3160468 | D26: =SUMIFS('Campaign - Dump'!$O:$O,'Campaign - Dump'!$J:$J,'Portfolio Wise '!$B26,'Campaign - Dump'!$A:$A,'Portfolio Wise '!$A26) -> 11230 | E26: =IFERROR(D26/C26,0) -> 0.0035532712 | F26: =SUMIFS('Campaign - Dump'!$Q:$Q,'Campaign - Dump'!$J:$J,'Portfolio Wise '!$B26,'Campaign - Dump'!$A:$A,'Portfolio Wise '!$A26) -> 126298.03 | G26: =IFERROR(F26/D26,0) -> 11.246485 | H26: =SUMIFS('Campaign - Dump'!$T:$T,'Campaign - Dump'!$J:$J,'Portfolio Wise '!$B26,'Campaign - Dump'!$A:$A,'Portfolio Wise '!$A26) -> 62 | I26: =IFERROR(H26/D26,0) -> 0.0055209261 | J26: =SUMIFS('Campaign - Dump'!$U:$U,'Campaign - Dump'!$J:$J,'Portfolio Wise '!$B26,'Campaign - Dump'!$A:$A,'Portfolio Wise '!$A26) -> 1026813.4 | K26: =IFERROR(F26/J26,0) -> 0.12299998 | L26: =IFERROR(J26/F26,0) -> 8.1300826 | M26: =IFERROR(J26/H26,0) -> 16561.507 | N26: 0 | O26: 0 | P26: =IFERROR(O26/N26,0) -> 0 | Q26: =SUMIFS('Business - Dump'!$W:$W,'Business - Dump'!$B:$B,'Portfolio Wise '!$B26,'Business - Dump'!$A:$A,'Portfolio Wise '!$A26) -> 0 | R26: =SUMIFS('Business - Dump'!$U:$U,'Business - Dump'!$B:$B,'Portfolio Wise '!$B26,'Business - Dump'!$A:$A,'Portfolio Wise '!$A26)/1.18 -> 0 | S26: =IFERROR(R26/Q26,0) -> 0 | T26: =IFERROR(F26/R26,0) -> 0 | U26: =IFERROR(R26/F26,0) -> 0 | V26: =SUMIFS('Business - Dump'!$G:$G,'Business - Dump'!$B:$B,'Portfolio Wise '!$B26,'Business - Dump'!$A:$A,'Portfolio Wise '!$A26) -> 0 | W26: =IFERROR(Q26/V26,0) -> 0 | X26: =IFERROR(N26/Q26,0) -> 0 | Y26: =IFERROR(O26/R26,0) -> 0 | Z26: =IFERROR(H26/Q26,0) -> 0 | AA26: =IFERROR(O26/R26,0) -> 0 | AB26: =IFERROR(AVERAGEIFS('Business - Dump'!$O:$O,'Business - Dump'!$B:$B,'Portfolio Wise '!$B26,'Business - Dump'!$A:$A,'Portfolio Wise '!$A26),0) -> 0 | AC26: =F26/SUMIFS('Campaign - Dump'!$Q:$Q,'Campaign - Dump'!$A:$A,'Portfolio Wise '!$A26) -> 0.48416753 | AD26: =IFERROR(N26/H26,0) -> 0
A27: Dec | B27: Standing Table | C27: =SUMIFS('Campaign - Dump'!$N:$N,'Campaign - Dump'!$J:$J,'Portfolio Wise '!$B27,'Campaign - Dump'!$A:$A,'Portfolio Wise '!$A27) -> 0 | D27: =SUMIFS('Campaign - Dump'!$O:$O,'Campaign - Dump'!$J:$J,'Portfolio Wise '!$B27,'Campaign - Dump'!$A:$A,'Portfolio Wise '!$A27) -> 0 | E27: =IFERROR(D27/C27,0) -> 0 | F27: =SUMIFS('Campaign - Dump'!$Q:$Q,'Campaign - Dump'!$J:$J,'Portfolio Wise '!$B27,'Campaign - Dump'!$A:$A,'Portfolio Wise '!$A27) -> 0 | G27: =IFERROR(F27/D27,0) -> 0 | H27: =SUMIFS('Campaign - Dump'!$T:$T,'Campaign - Dump'!$J:$J,'Portfolio Wise '!$B27,'Campaign - Dump'!$A:$A,'Portfolio Wise '!$A27) -> 0 | I27: =IFERROR(H27/D27,0) -> 0 | J27: =SUMIFS('Campaign - Dump'!$U:$U,'Campaign - Dump'!$J:$J,'Portfolio Wise '!$B27,'Campaign - Dump'!$A:$A,'Portfolio Wise '!$A27) -> 0 | K27: =IFERROR(F27/J27,0) -> 0 | L27: =IFERROR(J27/F27,0) -> 0 | M27: =IFERROR(J27/H27,0) -> 0 | N27: =IFERROR(Q27-H27,0) -> 0 | O27: =IFERROR(R27-J27,0) -> 0 | P27: =IFERROR(O27/N27,0) -> 0 | Q27: =SUMIFS('Business - Dump'!$W:$W,'Business - Dump'!$B:$B,'Portfolio Wise '!$B27,'Business - Dump'!$A:$A,'Portfolio Wise '!$A27) -> 0 | R27: =SUMIFS('Business - Dump'!$U:$U,'Business - Dump'!$B:$B,'Portfolio Wise '!$B27,'Business - Dump'!$A:$A,'Portfolio Wise '!$A27)/1.18 -> 0 | S27: =IFERROR(R27/Q27,0) -> 0 | T27: =IFERROR(F27/R27,0) -> 0 | U27: =IFERROR(R27/F27,0) -> 0 | V27: =SUMIFS('Business - Dump'!$G:$G,'Business - Dump'!$B:$B,'Portfolio Wise '!$B27,'Business - Dump'!$A:$A,'Portfolio Wise '!$A27) -> 0 | W27: =IFERROR(Q27/V27,0) -> 0 | X27: =IFERROR(N27/Q27,0) -> 0 | Y27: =IFERROR(O27/R27,0) -> 0 | Z27: =IFERROR(H27/Q27,0) -> 0 | AA27: =IFERROR(O27/R27,0) -> 0 | AB27: =IFERROR(AVERAGEIFS('Business - Dump'!$O:$O,'Business - Dump'!$B:$B,'Portfolio Wise '!$B27,'Business - Dump'!$A:$A,'Portfolio Wise '!$A27),0) -> 0 | AC27: =F27/SUMIFS('Campaign - Dump'!$Q:$Q,'Campaign - Dump'!$A:$A,'Portfolio Wise '!$A27) -> 0 | AD27: =IFERROR(N27/H27,0) -> 0
A28: Dec | B28: TABLE TOP | C28: =SUMIFS('Campaign - Dump'!$N:$N,'Campaign - Dump'!$J:$J,'Portfolio Wise '!$B28,'Campaign - Dump'!$A:$A,'Portfolio Wise '!$A28) -> 103 | D28: =SUMIFS('Campaign - Dump'!$O:$O,'Campaign - Dump'!$J:$J,'Portfolio Wise '!$B28,'Campaign - Dump'!$A:$A,'Portfolio Wise '!$A28) -> 1 | E28: =IFERROR(D28/C28,0) -> 0.0097087379 | F28: =SUMIFS('Campaign - Dump'!$Q:$Q,'Campaign - Dump'!$J:$J,'Portfolio Wise '!$B28,'Campaign - Dump'!$A:$A,'Portfolio Wise '!$A28) -> 3.59 | G28: =IFERROR(F28/D28,0) -> 3.59 | H28: =SUMIFS('Campaign - Dump'!$T:$T,'Campaign - Dump'!$J:$J,'Portfolio Wise '!$B28,'Campaign - Dump'!$A:$A,'Portfolio Wise '!$A28) -> 0 | I28: =IFERROR(H28/D28,0) -> 0 | J28: =SUMIFS('Campaign - Dump'!$U:$U,'Campaign - Dump'!$J:$J,'Portfolio Wise '!$B28,'Campaign - Dump'!$A:$A,'Portfolio Wise '!$A28) -> 0 | K28: =IFERROR(F28/J28,0) -> 0 | L28: =IFERROR(J28/F28,0) -> 0 | M28: =IFERROR(J28/H28,0) -> 0 | N28: =IFERROR(Q28-H28,0) -> 3 | O28: =IFERROR(R28-J28,0) -> 16228.814 | P28: =IFERROR(O28/N28,0) -> 5409.6045 | Q28: =SUMIFS('Business - Dump'!$W:$W,'Business - Dump'!$B:$B,'Portfolio Wise '!$B28,'Business - Dump'!$A:$A,'Portfolio Wise '!$A28) -> 3 | R28: =SUMIFS('Business - Dump'!$U:$U,'Business - Dump'!$B:$B,'Portfolio Wise '!$B28,'Business - Dump'!$A:$A,'Portfolio Wise '!$A28)/1.18 -> 16228.814 | S28: =IFERROR(R28/Q28,0) -> 5409.6045 | T28: =IFERROR(F28/R28,0) -> 0.00022121149 | U28: =IFERROR(R28/F28,0) -> 4520.5609 | V28: =SUMIFS('Business - Dump'!$G:$G,'Business - Dump'!$B:$B,'Portfolio Wise '!$B28,'Business - Dump'!$A:$A,'Portfolio Wise '!$A28) -> 911 | W28: =IFERROR(Q28/V28,0) -> 0.0032930845 | X28: =IFERROR(N28/Q28,0) -> 1 | Y28: =IFERROR(O28/R28,0) -> 1 | Z28: =IFERROR(H28/Q28,0) -> 0 | AA28: =IFERROR(O28/R28,0) -> 1 | AB28: =IFERROR(AVERAGEIFS('Business - Dump'!$O:$O,'Business - Dump'!$B:$B,'Portfolio Wise '!$B28,'Business - Dump'!$A:$A,'Portfolio Wise '!$A28),0) -> 0.794 | AC28: =F28/SUMIFS('Campaign - Dump'!$Q:$Q,'Campaign - Dump'!$A:$A,'Portfolio Wise '!$A28) -> 1.376238e-05 | AD28: =IFERROR(N28/H28,0) -> 0
A29: Dec | B29: Brand | C29: =SUMIFS('Campaign - Dump'!$N:$N,'Campaign - Dump'!$J:$J,'Portfolio Wise '!$B29,'Campaign - Dump'!$A:$A,'Portfolio Wise '!$A29) -> 216178 | D29: =SUMIFS('Campaign - Dump'!$O:$O,'Campaign - Dump'!$J:$J,'Portfolio Wise '!$B29,'Campaign - Dump'!$A:$A,'Portfolio Wise '!$A29) -> 947 | E29: =IFERROR(D29/C29,0) -> 0.0043806493 | F29: =SUMIFS('Campaign - Dump'!$Q:$Q,'Campaign - Dump'!$J:$J,'Portfolio Wise '!$B29,'Campaign - Dump'!$A:$A,'Portfolio Wise '!$A29) -> 21127.47 | G29: =IFERROR(F29/D29,0) -> 22.309894 | H29: =SUMIFS('Campaign - Dump'!$T:$T,'Campaign - Dump'!$J:$J,'Portfolio Wise '!$B29,'Campaign - Dump'!$A:$A,'Portfolio Wise '!$A29) -> 30 | I29: =IFERROR(H29/D29,0) -> 0.031678986 | J29: =SUMIFS('Campaign - Dump'!$U:$U,'Campaign - Dump'!$J:$J,'Portfolio Wise '!$B29,'Campaign - Dump'!$A:$A,'Portfolio Wise '!$A29) -> 477509.29 | K29: =IFERROR(F29/J29,0) -> 0.04424515 | L29: =IFERROR(J29/F29,0) -> 22.601347 | M29: =IFERROR(J29/H29,0) -> 15916.976 | N29: 0 | O29: 0 | P29: =IFERROR(O29/N29,0) -> 0 | Q29: =SUMIFS('Business - Dump'!$W:$W,'Business - Dump'!$B:$B,'Portfolio Wise '!$B29,'Business - Dump'!$A:$A,'Portfolio Wise '!$A29) -> 0 | R29: =SUMIFS('Business - Dump'!$U:$U,'Business - Dump'!$B:$B,'Portfolio Wise '!$B29,'Business - Dump'!$A:$A,'Portfolio Wise '!$A29)/1.18 -> 0 | S29: =IFERROR(R29/Q29,0) -> 0 | T29: =IFERROR(F29/R29,0) -> 0 | U29: =IFERROR(R29/F29,0) -> 0 | V29: =SUMIFS('Business - Dump'!$G:$G,'Business - Dump'!$B:$B,'Portfolio Wise '!$B29,'Business - Dump'!$A:$A,'Portfolio Wise '!$A29) -> 0 | W29: =IFERROR(Q29/V29,0) -> 0 | X29: =IFERROR(N29/Q29,0) -> 0 | Y29: =IFERROR(O29/R29,0) -> 0 | Z29: =IFERROR(H29/Q29,0) -> 0 | AA29: =IFERROR(O29/R29,0) -> 0 | AB29: =IFERROR(AVERAGEIFS('Business - Dump'!$O:$O,'Business - Dump'!$B:$B,'Portfolio Wise '!$B29,'Business - Dump'!$A:$A,'Portfolio Wise '!$A29),0) -> 0 | AC29: =F29/SUMIFS('Campaign - Dump'!$Q:$Q,'Campaign - Dump'!$A:$A,'Portfolio Wise '!$A29) -> 0.080992831 | AD29: =IFERROR(N29/H29,0) -> 0
A30: Dec | B30: Standing Table - SM3 | C30: =SUMIFS('Campaign - Dump'!$N:$N,'Campaign - Dump'!$J:$J,'Portfolio Wise '!$B30,'Campaign - Dump'!$A:$A,'Portfolio Wise '!$A30) -> 500612 | D30: =SUMIFS('Campaign - Dump'!$O:$O,'Campaign - Dump'!$J:$J,'Portfolio Wise '!$B30,'Campaign - Dump'!$A:$A,'Portfolio Wise '!$A30) -> 2642 | E30: =IFERROR(D30/C30,0) -> 0.0052775403 | F30: =SUMIFS('Campaign - Dump'!$Q:$Q,'Campaign - Dump'!$J:$J,'Portfolio Wise '!$B30,'Campaign - Dump'!$A:$A,'Portfolio Wise '!$A30) -> 50766.91 | G30: =IFERROR(F30/D30,0) -> 19.215333 | H30: =SUMIFS('Campaign - Dump'!$T:$T,'Campaign - Dump'!$J:$J,'Portfolio Wise '!$B30,'Campaign - Dump'!$A:$A,'Portfolio Wise '!$A30) -> 26 | I30: =IFERROR(H30/D30,0) -> 0.0098410295 | J30: =SUMIFS('Campaign - Dump'!$U:$U,'Campaign - Dump'!$J:$J,'Portfolio Wise '!$B30,'Campaign - Dump'!$A:$A,'Portfolio Wise '!$A30) -> 523557.57 | K30: =IFERROR(F30/J30,0) -> 0.096965287 | L30: =IFERROR(J30/F30,0) -> 10.312969 | M30: =IFERROR(J30/H30,0) -> 20136.83 | N30: =IFERROR(Q30-H30,0) -> 42 | O30: =IFERROR(R30-J30,0) -> 781527.18 | P30: =IFERROR(O30/N30,0) -> 18607.79 | Q30: =SUMIFS('Business - Dump'!$W:$W,'Business - Dump'!$B:$B,'Portfolio Wise '!$B30,'Business - Dump'!$A:$A,'Portfolio Wise '!$A30) -> 68 | R30: =SUMIFS('Business - Dump'!$U:$U,'Business - Dump'!$B:$B,'Portfolio Wise '!$B30,'Business - Dump'!$A:$A,'Portfolio Wise '!$A30)/1.18 -> 1305084.7 | S30: =IFERROR(R30/Q30,0) -> 19192.423 | T30: =IFERROR(F30/R30,0) -> 0.038899321 | U30: =IFERROR(R30/F30,0) -> 25.70739 | V30: =SUMIFS('Business - Dump'!$G:$G,'Business - Dump'!$B:$B,'Portfolio Wise '!$B30,'Business - Dump'!$A:$A,'Portfolio Wise '!$A30) -> 10420 | W30: =IFERROR(Q30/V30,0) -> 0.0065259117 | X30: =IFERROR(N30/Q30,0) -> 0.61764706 | Y30: =IFERROR(O30/R30,0) -> 0.59883251 | Z30: =IFERROR(H30/Q30,0) -> 0.38235294 | AA30: =IFERROR(O30/R30,0) -> 0.59883251 | AB30: =IFERROR(AVERAGEIFS('Business - Dump'!$O:$O,'Business - Dump'!$B:$B,'Portfolio Wise '!$B30,'Business - Dump'!$A:$A,'Portfolio Wise '!$A30),0) -> 0.929975 | AC30: =F30/SUMIFS('Campaign - Dump'!$Q:$Q,'Campaign - Dump'!$A:$A,'Portfolio Wise '!$A30) -> 0.19461657 | AD30: =IFERROR(N30/H30,0) -> 1.6153846
A31: Dec | B31: Standing Table - E2 | C31: =SUMIFS('Campaign - Dump'!$N:$N,'Campaign - Dump'!$J:$J,'Portfolio Wise '!$B31,'Campaign - Dump'!$A:$A,'Portfolio Wise '!$A31) -> 558377 | D31: =SUMIFS('Campaign - Dump'!$O:$O,'Campaign - Dump'!$J:$J,'Portfolio Wise '!$B31,'Campaign - Dump'!$A:$A,'Portfolio Wise '!$A31) -> 1946 | E31: =IFERROR(D31/C31,0) -> 0.0034851006 | F31: =SUMIFS('Campaign - Dump'!$Q:$Q,'Campaign - Dump'!$J:$J,'Portfolio Wise '!$B31,'Campaign - Dump'!$A:$A,'Portfolio Wise '!$A31) -> 56521.85 | G31: =IFERROR(F31/D31,0) -> 29.045144 | H31: =SUMIFS('Campaign - Dump'!$T:$T,'Campaign - Dump'!$J:$J,'Portfolio Wise '!$B31,'Campaign - Dump'!$A:$A,'Portfolio Wise '!$A31) -> 19 | I31: =IFERROR(H31/D31,0) -> 0.0097636177 | J31: =SUMIFS('Campaign - Dump'!$U:$U,'Campaign - Dump'!$J:$J,'Portfolio Wise '!$B31,'Campaign - Dump'!$A:$A,'Portfolio Wise '!$A31) -> 401183.87 | K31: =IFERROR(F31/J31,0) -> 0.14088764 | L31: =IFERROR(J31/F31,0) -> 7.0978545 | M31: =IFERROR(J31/H31,0) -> 21114.941 | N31: =IFERROR(Q31-H31,0) -> 11 | O31: =IFERROR(R31-J31,0) -> 435172.06 | P31: =IFERROR(O31/N31,0) -> 39561.097 | Q31: =SUMIFS('Business - Dump'!$W:$W,'Business - Dump'!$B:$B,'Portfolio Wise '!$B31,'Business - Dump'!$A:$A,'Portfolio Wise '!$A31) -> 30 | R31: =SUMIFS('Business - Dump'!$U:$U,'Business - Dump'!$B:$B,'Portfolio Wise '!$B31,'Business - Dump'!$A:$A,'Portfolio Wise '!$A31)/1.18 -> 836355.93 | S31: =IFERROR(R31/Q31,0) -> 27878.531 | T31: =IFERROR(F31/R31,0) -> 0.067581095 | U31: =IFERROR(R31/F31,0) -> 14.797037 | V31: =SUMIFS('Business - Dump'!$G:$G,'Business - Dump'!$B:$B,'Portfolio Wise '!$B31,'Business - Dump'!$A:$A,'Portfolio Wise '!$A31) -> 5585 | W31: =IFERROR(Q31/V31,0) -> 0.0053715309 | X31: =IFERROR(N31/Q31,0) -> 0.36666667 | Y31: =IFERROR(O31/R31,0) -> 0.52031922 | Z31: =IFERROR(H31/Q31,0) -> 0.63333333 | AA31: =IFERROR(O31/R31,0) -> 0.52031922 | AB31: =IFERROR(AVERAGEIFS('Business - Dump'!$O:$O,'Business - Dump'!$B:$B,'Portfolio Wise '!$B31,'Business - Dump'!$A:$A,'Portfolio Wise '!$A31),0) -> 0.865875 | AC31: =F31/SUMIFS('Campaign - Dump'!$Q:$Q,'Campaign - Dump'!$A:$A,'Portfolio Wise '!$A31) -> 0.21667832 | AD31: =IFERROR(N31/H31,0) -> 0.57894737
A32: Dec | B32: Standing Table - M3 | C32: =SUMIFS('Campaign - Dump'!$N:$N,'Campaign - Dump'!$J:$J,'Portfolio Wise '!$B32,'Campaign - Dump'!$A:$A,'Portfolio Wise '!$A32) -> 27667 | D32: =SUMIFS('Campaign - Dump'!$O:$O,'Campaign - Dump'!$J:$J,'Portfolio Wise '!$B32,'Campaign - Dump'!$A:$A,'Portfolio Wise '!$A32) -> 193 | E32: =IFERROR(D32/C32,0) -> 0.0069758196 | F32: =SUMIFS('Campaign - Dump'!$Q:$Q,'Campaign - Dump'!$J:$J,'Portfolio Wise '!$B32,'Campaign - Dump'!$A:$A,'Portfolio Wise '!$A32) -> 3382.32 | G32: =IFERROR(F32/D32,0) -> 17.524974 | H32: =SUMIFS('Campaign - Dump'!$T:$T,'Campaign - Dump'!$J:$J,'Portfolio Wise '!$B32,'Campaign - Dump'!$A:$A,'Portfolio Wise '!$A32) -> 1 | I32: =IFERROR(H32/D32,0) -> 0.0051813471 | J32: =SUMIFS('Campaign - Dump'!$U:$U,'Campaign - Dump'!$J:$J,'Portfolio Wise '!$B32,'Campaign - Dump'!$A:$A,'Portfolio Wise '!$A32) -> 13558.48 | K32: =IFERROR(F32/J32,0) -> 0.24946159 | L32: =IFERROR(J32/F32,0) -> 4.0086331 | M32: =IFERROR(J32/H32,0) -> 13558.48 | N32: =IFERROR(Q32-H32,0) -> 8 | O32: =IFERROR(R32-J32,0) -> 103136.44 | P32: =IFERROR(O32/N32,0) -> 12892.054 | Q32: =SUMIFS('Business - Dump'!$W:$W,'Business - Dump'!$B:$B,'Portfolio Wise '!$B32,'Business - Dump'!$A:$A,'Portfolio Wise '!$A32) -> 9 | R32: =SUMIFS('Business - Dump'!$U:$U,'Business - Dump'!$B:$B,'Portfolio Wise '!$B32,'Business - Dump'!$A:$A,'Portfolio Wise '!$A32)/1.18 -> 116694.92 | S32: =IFERROR(R32/Q32,0) -> 12966.102 | T32: =IFERROR(F32/R32,0) -> 0.028984296 | U32: =IFERROR(R32/F32,0) -> 34.501441 | V32: =SUMIFS('Business - Dump'!$G:$G,'Business - Dump'!$B:$B,'Portfolio Wise '!$B32,'Business - Dump'!$A:$A,'Portfolio Wise '!$A32) -> 906 | W32: =IFERROR(Q32/V32,0) -> 0.0099337748 | X32: =IFERROR(N32/Q32,0) -> 0.88888889 | Y32: =IFERROR(O32/R32,0) -> 0.88381259 | Z32: =IFERROR(H32/Q32,0) -> 0.11111111 | AA32: =IFERROR(O32/R32,0) -> 0.88381259 | AB32: =IFERROR(AVERAGEIFS('Business - Dump'!$O:$O,'Business - Dump'!$B:$B,'Portfolio Wise '!$B32,'Business - Dump'!$A:$A,'Portfolio Wise '!$A32),0) -> 0.889 | AC32: =F32/SUMIFS('Campaign - Dump'!$Q:$Q,'Campaign - Dump'!$A:$A,'Portfolio Wise '!$A32) -> 0.012966232 | AD32: =IFERROR(N32/H32,0) -> 8
A33: Dec | B33: Monitor Arm Stand | C33: =SUMIFS('Campaign - Dump'!$N:$N,'Campaign - Dump'!$J:$J,'Portfolio Wise '!$B33,'Campaign - Dump'!$A:$A,'Portfolio Wise '!$A33) -> 0 | D33: =SUMIFS('Campaign - Dump'!$O:$O,'Campaign - Dump'!$J:$J,'Portfolio Wise '!$B33,'Campaign - Dump'!$A:$A,'Portfolio Wise '!$A33) -> 0 | E33: =IFERROR(D33/C33,0) -> 0 | F33: =SUMIFS('Campaign - Dump'!$Q:$Q,'Campaign - Dump'!$J:$J,'Portfolio Wise '!$B33,'Campaign - Dump'!$A:$A,'Portfolio Wise '!$A33) -> 0 | G33: =IFERROR(F33/D33,0) -> 0 | H33: =SUMIFS('Campaign - Dump'!$T:$T,'Campaign - Dump'!$J:$J,'Portfolio Wise '!$B33,'Campaign - Dump'!$A:$A,'Portfolio Wise '!$A33) -> 0 | I33: =IFERROR(H33/D33,0) -> 0 | J33: =SUMIFS('Campaign - Dump'!$U:$U,'Campaign - Dump'!$J:$J,'Portfolio Wise '!$B33,'Campaign - Dump'!$A:$A,'Portfolio Wise '!$A33) -> 0 | K33: =IFERROR(F33/J33,0) -> 0 | L33: =IFERROR(J33/F33,0) -> 0 | M33: =IFERROR(J33/H33,0) -> 0 | N33: =IFERROR(Q33-H33,0) -> 1 | O33: =IFERROR(R33-J33,0) -> 10974.576 | P33: =IFERROR(O33/N33,0) -> 10974.576 | Q33: =SUMIFS('Business - Dump'!$W:$W,'Business - Dump'!$B:$B,'Portfolio Wise '!$B33,'Business - Dump'!$A:$A,'Portfolio Wise '!$A33) -> 1 | R33: =SUMIFS('Business - Dump'!$U:$U,'Business - Dump'!$B:$B,'Portfolio Wise '!$B33,'Business - Dump'!$A:$A,'Portfolio Wise '!$A33)/1.18 -> 10974.576 | S33: =IFERROR(R33/Q33,0) -> 10974.576 | T33: =IFERROR(F33/R33,0) -> 0 | U33: =IFERROR(R33/F33,0) -> 0 | V33: =SUMIFS('Business - Dump'!$G:$G,'Business - Dump'!$B:$B,'Portfolio Wise '!$B33,'Business - Dump'!$A:$A,'Portfolio Wise '!$A33) -> 112 | W33: =IFERROR(Q33/V33,0) -> 0.0089285714 | X33: =IFERROR(N33/Q33,0) -> 1 | Y33: =IFERROR(O33/R33,0) -> 1 | Z33: =IFERROR(H33/Q33,0) -> 0 | AA33: =IFERROR(O33/R33,0) -> 1 | AB33: =IFERROR(AVERAGEIFS('Business - Dump'!$O:$O,'Business - Dump'!$B:$B,'Portfolio Wise '!$B33,'Business - Dump'!$A:$A,'Portfolio Wise '!$A33),0) -> 0.8593 | AC33: =F33/SUMIFS('Campaign - Dump'!$Q:$Q,'Campaign - Dump'!$A:$A,'Portfolio Wise '!$A33) -> 0 | AD33: =IFERROR(N33/H33,0) -> 0
A34: Dec | B34: Standing Desk Converter | C34: =SUMIFS('Campaign - Dump'!$N:$N,'Campaign - Dump'!$J:$J,'Portfolio Wise '!$B34,'Campaign - Dump'!$A:$A,'Portfolio Wise '!$A34) -> 0 | D34: =SUMIFS('Campaign - Dump'!$O:$O,'Campaign - Dump'!$J:$J,'Portfolio Wise '!$B34,'Campaign - Dump'!$A:$A,'Portfolio Wise '!$A34) -> 0 | E34: =IFERROR(D34/C34,0) -> 0 | F34: =SUMIFS('Campaign - Dump'!$Q:$Q,'Campaign - Dump'!$J:$J,'Portfolio Wise '!$B34,'Campaign - Dump'!$A:$A,'Portfolio Wise '!$A34) -> 0 | G34: =IFERROR(F34/D34,0) -> 0 | H34: =SUMIFS('Campaign - Dump'!$T:$T,'Campaign - Dump'!$J:$J,'Portfolio Wise '!$B34,'Campaign - Dump'!$A:$A,'Portfolio Wise '!$A34) -> 0 | I34: =IFERROR(H34/D34,0) -> 0 | J34: =SUMIFS('Campaign - Dump'!$U:$U,'Campaign - Dump'!$J:$J,'Portfolio Wise '!$B34,'Campaign - Dump'!$A:$A,'Portfolio Wise '!$A34) -> 0 | K34: =IFERROR(F34/J34,0) -> 0 | L34: =IFERROR(J34/F34,0) -> 0 | M34: =IFERROR(J34/H34,0) -> 0 | N34: =IFERROR(Q34-H34,0) -> 3 | O34: =IFERROR(R34-J34,0) -> 16525.424 | P34: =IFERROR(O34/N34,0) -> 5508.4746 | Q34: =SUMIFS('Business - Dump'!$W:$W,'Business - Dump'!$B:$B,'Portfolio Wise '!$B34,'Business - Dump'!$A:$A,'Portfolio Wise '!$A34) -> 3 | R34: =SUMIFS('Business - Dump'!$U:$U,'Business - Dump'!$B:$B,'Portfolio Wise '!$B34,'Business - Dump'!$A:$A,'Portfolio Wise '!$A34)/1.18 -> 16525.424 | S34: =IFERROR(R34/Q34,0) -> 5508.4746 | T34: =IFERROR(F34/R34,0) -> 0 | U34: =IFERROR(R34/F34,0) -> 0 | V34: =SUMIFS('Business - Dump'!$G:$G,'Business - Dump'!$B:$B,'Portfolio Wise '!$B34,'Business - Dump'!$A:$A,'Portfolio Wise '!$A34) -> 150 | W34: =IFERROR(Q34/V34,0) -> 0.02 | X34: =IFERROR(N34/Q34,0) -> 1 | Y34: =IFERROR(O34/R34,0) -> 1 | Z34: =IFERROR(H34/Q34,0) -> 0 | AA34: =IFERROR(O34/R34,0) -> 1 | AB34: =IFERROR(AVERAGEIFS('Business - Dump'!$O:$O,'Business - Dump'!$B:$B,'Portfolio Wise '!$B34,'Business - Dump'!$A:$A,'Portfolio Wise '!$A34),0) -> 0.9026 | AC34: =F34/SUMIFS('Campaign - Dump'!$Q:$Q,'Campaign - Dump'!$A:$A,'Portfolio Wise '!$A34) -> 0 | AD34: =IFERROR(N34/H34,0) -> 0
A35: Dec | B35: Standing Table - All Frames | C35: =SUMIFS('Campaign - Dump'!$N:$N,'Campaign - Dump'!$J:$J,'Portfolio Wise '!$B35,'Campaign - Dump'!$A:$A,'Portfolio Wise '!$A35) -> 10342 | D35: =SUMIFS('Campaign - Dump'!$O:$O,'Campaign - Dump'!$J:$J,'Portfolio Wise '!$B35,'Campaign - Dump'!$A:$A,'Portfolio Wise '!$A35) -> 125 | E35: =IFERROR(D35/C35,0) -> 0.012086637 | F35: =SUMIFS('Campaign - Dump'!$Q:$Q,'Campaign - Dump'!$J:$J,'Portfolio Wise '!$B35,'Campaign - Dump'!$A:$A,'Portfolio Wise '!$A35) -> 2755.88 | G35: =IFERROR(F35/D35,0) -> 22.04704 | H35: =SUMIFS('Campaign - Dump'!$T:$T,'Campaign - Dump'!$J:$J,'Portfolio Wise '!$B35,'Campaign - Dump'!$A:$A,'Portfolio Wise '!$A35) -> 2 | I35: =IFERROR(H35/D35,0) -> 0.016 | J35: =SUMIFS('Campaign - Dump'!$U:$U,'Campaign - Dump'!$J:$J,'Portfolio Wise '!$B35,'Campaign - Dump'!$A:$A,'Portfolio Wise '!$A35) -> 28305.08 | K35: =IFERROR(F35/J35,0) -> 0.097363441 | L35: =IFERROR(J35/F35,0) -> 10.270796 | M35: =IFERROR(J35/H35,0) -> 14152.54 | N35: =IFERROR(Q35-H35,0) -> 20 | O35: =IFERROR(R35-J35,0) -> 377966.11 | P35: =IFERROR(O35/N35,0) -> 18898.305 | Q35: =SUMIFS('Business - Dump'!$W:$W,'Business - Dump'!$B:$B,'Portfolio Wise '!$B35,'Business - Dump'!$A:$A,'Portfolio Wise '!$A35) -> 22 | R35: =SUMIFS('Business - Dump'!$U:$U,'Business - Dump'!$B:$B,'Portfolio Wise '!$B35,'Business - Dump'!$A:$A,'Portfolio Wise '!$A35)/1.18 -> 406271.19 | S35: =IFERROR(R35/Q35,0) -> 18466.872 | T35: =IFERROR(F35/R35,0) -> 0.0067833509 | U35: =IFERROR(R35/F35,0) -> 147.41977 | V35: =SUMIFS('Business - Dump'!$G:$G,'Business - Dump'!$B:$B,'Portfolio Wise '!$B35,'Business - Dump'!$A:$A,'Portfolio Wise '!$A35) -> 4578 | W35: =IFERROR(Q35/V35,0) -> 0.004805592 | X35: =IFERROR(N35/Q35,0) -> 0.90909091 | Y35: =IFERROR(O35/R35,0) -> 0.93032959 | Z35: =IFERROR(H35/Q35,0) -> 0.090909091 | AA35: =IFERROR(O35/R35,0) -> 0.93032959 | AB35: =IFERROR(AVERAGEIFS('Business - Dump'!$O:$O,'Business - Dump'!$B:$B,'Portfolio Wise '!$B35,'Business - Dump'!$A:$A,'Portfolio Wise '!$A35),0) -> 0.8511 | AC35: =F35/SUMIFS('Campaign - Dump'!$Q:$Q,'Campaign - Dump'!$A:$A,'Portfolio Wise '!$A35) -> 0.010564754 | AD35: =IFERROR(N35/H35,0) -> 10
A36: Dec | B36: Standing Table - E1A | C36: =SUMIFS('Campaign - Dump'!$N:$N,'Campaign - Dump'!$J:$J,'Portfolio Wise '!$B36,'Campaign - Dump'!$A:$A,'Portfolio Wise '!$A36) -> 0 | D36: =SUMIFS('Campaign - Dump'!$O:$O,'Campaign - Dump'!$J:$J,'Portfolio Wise '!$B36,'Campaign - Dump'!$A:$A,'Portfolio Wise '!$A36) -> 0 | E36: =IFERROR(D36/C36,0) -> 0 | F36: =SUMIFS('Campaign - Dump'!$Q:$Q,'Campaign - Dump'!$J:$J,'Portfolio Wise '!$B36,'Campaign - Dump'!$A:$A,'Portfolio Wise '!$A36) -> 0 | G36: =IFERROR(F36/D36,0) -> 0 | H36: =SUMIFS('Campaign - Dump'!$T:$T,'Campaign - Dump'!$J:$J,'Portfolio Wise '!$B36,'Campaign - Dump'!$A:$A,'Portfolio Wise '!$A36) -> 0 | I36: =IFERROR(H36/D36,0) -> 0 | J36: =SUMIFS('Campaign - Dump'!$U:$U,'Campaign - Dump'!$J:$J,'Portfolio Wise '!$B36,'Campaign - Dump'!$A:$A,'Portfolio Wise '!$A36) -> 0 | K36: =IFERROR(F36/J36,0) -> 0 | L36: =IFERROR(J36/F36,0) -> 0 | M36: =IFERROR(J36/H36,0) -> 0 | N36: =IFERROR(Q36-H36,0) -> 0 | O36: =IFERROR(R36-J36,0) -> 0 | P36: =IFERROR(O36/N36,0) -> 0 | Q36: =SUMIFS('Business - Dump'!$W:$W,'Business - Dump'!$B:$B,'Portfolio Wise '!$B36,'Business - Dump'!$A:$A,'Portfolio Wise '!$A36) -> 0 | R36: =SUMIFS('Business - Dump'!$U:$U,'Business - Dump'!$B:$B,'Portfolio Wise '!$B36,'Business - Dump'!$A:$A,'Portfolio Wise '!$A36)/1.18 -> 0 | S36: =IFERROR(R36/Q36,0) -> 0 | T36: =IFERROR(F36/R36,0) -> 0 | U36: =IFERROR(R36/F36,0) -> 0 | V36: =SUMIFS('Business - Dump'!$G:$G,'Business - Dump'!$B:$B,'Portfolio Wise '!$B36,'Business - Dump'!$A:$A,'Portfolio Wise '!$A36) -> 0 | W36: =IFERROR(Q36/V36,0) -> 0 | X36: =IFERROR(N36/Q36,0) -> 0 | Y36: =IFERROR(O36/R36,0) -> 0 | Z36: =IFERROR(H36/Q36,0) -> 0 | AA36: =IFERROR(O36/R36,0) -> 0 | AB36: =IFERROR(AVERAGEIFS('Business - Dump'!$O:$O,'Business - Dump'!$B:$B,'Portfolio Wise '!$B36,'Business - Dump'!$A:$A,'Portfolio Wise '!$A36),0) -> 0 | AC36: =F36/SUMIFS('Campaign - Dump'!$Q:$Q,'Campaign - Dump'!$A:$A,'Portfolio Wise '!$A36) -> 0 | AD36: =IFERROR(N36/H36,0) -> 0
A37: Dec | B37: Standing Table - E1A | C37: =SUMIFS('Campaign - Dump'!$N:$N,'Campaign - Dump'!$J:$J,'Portfolio Wise '!$B37,'Campaign - Dump'!$A:$A,'Portfolio Wise '!$A37) -> 0 | D37: =SUMIFS('Campaign - Dump'!$O:$O,'Campaign - Dump'!$J:$J,'Portfolio Wise '!$B37,'Campaign - Dump'!$A:$A,'Portfolio Wise '!$A37) -> 0 | E37: =IFERROR(D37/C37,0) -> 0 | F37: =SUMIFS('Campaign - Dump'!$Q:$Q,'Campaign - Dump'!$J:$J,'Portfolio Wise '!$B37,'Campaign - Dump'!$A:$A,'Portfolio Wise '!$A37) -> 0 | G37: =IFERROR(F37/D37,0) -> 0 | H37: =SUMIFS('Campaign - Dump'!$T:$T,'Campaign - Dump'!$J:$J,'Portfolio Wise '!$B37,'Campaign - Dump'!$A:$A,'Portfolio Wise '!$A37) -> 0 | I37: =IFERROR(H37/D37,0) -> 0 | J37: =SUMIFS('Campaign - Dump'!$U:$U,'Campaign - Dump'!$J:$J,'Portfolio Wise '!$B37,'Campaign - Dump'!$A:$A,'Portfolio Wise '!$A37) -> 0 | K37: =IFERROR(F37/J37,0) -> 0 | L37: =IFERROR(J37/F37,0) -> 0 | M37: =IFERROR(J37/H37,0) -> 0 | N37: =IFERROR(Q37-H37,0) -> 0 | O37: =IFERROR(R37-J37,0) -> 0 | P37: =IFERROR(O37/N37,0) -> 0 | Q37: =SUMIFS('Business - Dump'!$W:$W,'Business - Dump'!$B:$B,'Portfolio Wise '!$B37,'Business - Dump'!$A:$A,'Portfolio Wise '!$A37) -> 0 | R37: =SUMIFS('Business - Dump'!$U:$U,'Business - Dump'!$B:$B,'Portfolio Wise '!$B37,'Business - Dump'!$A:$A,'Portfolio Wise '!$A37)/1.18 -> 0 | S37: =IFERROR(R37/Q37,0) -> 0 | T37: =IFERROR(F37/R37,0) -> 0 | U37: =IFERROR(R37/F37,0) -> 0 | V37: =SUMIFS('Business - Dump'!$G:$G,'Business - Dump'!$B:$B,'Portfolio Wise '!$B37,'Business - Dump'!$A:$A,'Portfolio Wise '!$A37) -> 0 | W37: =IFERROR(Q37/V37,0) -> 0 | X37: =IFERROR(N37/Q37,0) -> 0 | Y37: =IFERROR(O37/R37,0) -> 0 | Z37: =IFERROR(H37/Q37,0) -> 0 | AA37: =IFERROR(O37/R37,0) -> 0 | AB37: =IFERROR(AVERAGEIFS('Business - Dump'!$O:$O,'Business - Dump'!$B:$B,'Portfolio Wise '!$B37,'Business - Dump'!$A:$A,'Portfolio Wise '!$A37),0) -> 0 | AC37: =F37/SUMIFS('Campaign - Dump'!$Q:$Q,'Campaign - Dump'!$A:$A,'Portfolio Wise '!$A37) -> 0 | AD37: =IFERROR(N37/H37,0) -> 0
A38: Dec | B38: Standing Table - SB | C38: =SUMIFS('Campaign - Dump'!$N:$N,'Campaign - Dump'!$J:$J,'Portfolio Wise '!$B38,'Campaign - Dump'!$A:$A,'Portfolio Wise '!$A38) -> 0 | D38: =SUMIFS('Campaign - Dump'!$O:$O,'Campaign - Dump'!$J:$J,'Portfolio Wise '!$B38,'Campaign - Dump'!$A:$A,'Portfolio Wise '!$A38) -> 0 | E38: =IFERROR(D38/C38,0) -> 0 | F38: =SUMIFS('Campaign - Dump'!$Q:$Q,'Campaign - Dump'!$J:$J,'Portfolio Wise '!$B38,'Campaign - Dump'!$A:$A,'Portfolio Wise '!$A38) -> 0 | G38: =IFERROR(F38/D38,0) -> 0 | H38: =SUMIFS('Campaign - Dump'!$T:$T,'Campaign - Dump'!$J:$J,'Portfolio Wise '!$B38,'Campaign - Dump'!$A:$A,'Portfolio Wise '!$A38) -> 0 | I38: =IFERROR(H38/D38,0) -> 0 | J38: =SUMIFS('Campaign - Dump'!$U:$U,'Campaign - Dump'!$J:$J,'Portfolio Wise '!$B38,'Campaign - Dump'!$A:$A,'Portfolio Wise '!$A38) -> 0 | K38: =IFERROR(F38/J38,0) -> 0 | L38: =IFERROR(J38/F38,0) -> 0 | M38: =IFERROR(J38/H38,0) -> 0 | N38: 0 | O38: 0 | P38: =IFERROR(O38/N38,0) -> 0 | Q38: =SUMIFS('Business - Dump'!$W:$W,'Business - Dump'!$B:$B,'Portfolio Wise '!$B38,'Business - Dump'!$A:$A,'Portfolio Wise '!$A38) -> 0 | R38: =SUMIFS('Business - Dump'!$U:$U,'Business - Dump'!$B:$B,'Portfolio Wise '!$B38,'Business - Dump'!$A:$A,'Portfolio Wise '!$A38)/1.18 -> 0 | S38: =IFERROR(R38/Q38,0) -> 0 | T38: =IFERROR(F38/R38,0) -> 0 | U38: =IFERROR(R38/F38,0) -> 0 | V38: =SUMIFS('Business - Dump'!$G:$G,'Business - Dump'!$B:$B,'Portfolio Wise '!$B38,'Business - Dump'!$A:$A,'Portfolio Wise '!$A38) -> 0 | W38: =IFERROR(Q38/V38,0) -> 0 | X38: =IFERROR(N38/Q38,0) -> 0 | Y38: =IFERROR(O38/R38,0) -> 0 | Z38: =IFERROR(H38/Q38,0) -> 0 | AA38: =IFERROR(O38/R38,0) -> 0 | AB38: =IFERROR(AVERAGEIFS('Business - Dump'!$O:$O,'Business - Dump'!$B:$B,'Portfolio Wise '!$B38,'Business - Dump'!$A:$A,'Portfolio Wise '!$A38),0) -> 0 | AC38: =F38/SUMIFS('Campaign - Dump'!$Q:$Q,'Campaign - Dump'!$A:$A,'Portfolio Wise '!$A38) -> 0 | AD38: =IFERROR(N38/H38,0) -> 0
A39: Dec | B39: Standing Table - E3 | C39: =SUMIFS('Campaign - Dump'!$N:$N,'Campaign - Dump'!$J:$J,'Portfolio Wise '!$B39,'Campaign - Dump'!$A:$A,'Portfolio Wise '!$A39) -> 0 | D39: =SUMIFS('Campaign - Dump'!$O:$O,'Campaign - Dump'!$J:$J,'Portfolio Wise '!$B39,'Campaign - Dump'!$A:$A,'Portfolio Wise '!$A39) -> 0 | E39: =IFERROR(D39/C39,0) -> 0 | F39: =SUMIFS('Campaign - Dump'!$Q:$Q,'Campaign - Dump'!$J:$J,'Portfolio Wise '!$B39,'Campaign - Dump'!$A:$A,'Portfolio Wise '!$A39) -> 0 | G39: =IFERROR(F39/D39,0) -> 0 | H39: =SUMIFS('Campaign - Dump'!$T:$T,'Campaign - Dump'!$J:$J,'Portfolio Wise '!$B39,'Campaign - Dump'!$A:$A,'Portfolio Wise '!$A39) -> 0 | I39: =IFERROR(H39/D39,0) -> 0 | J39: =SUMIFS('Campaign - Dump'!$U:$U,'Campaign - Dump'!$J:$J,'Portfolio Wise '!$B39,'Campaign - Dump'!$A:$A,'Portfolio Wise '!$A39) -> 0 | K39: =IFERROR(F39/J39,0) -> 0 | L39: =IFERROR(J39/F39,0) -> 0 | M39: =IFERROR(J39/H39,0) -> 0 | N39: =IFERROR(Q39-H39,0) -> 1 | O39: =IFERROR(R39-J39,0) -> 40669.492 | P39: =IFERROR(O39/N39,0) -> 40669.492 | Q39: =SUMIFS('Business - Dump'!$W:$W,'Business - Dump'!$B:$B,'Portfolio Wise '!$B39,'Business - Dump'!$A:$A,'Portfolio Wise '!$A39) -> 1 | R39: =SUMIFS('Business - Dump'!$U:$U,'Business - Dump'!$B:$B,'Portfolio Wise '!$B39,'Business - Dump'!$A:$A,'Portfolio Wise '!$A39)/1.18 -> 40669.492 | S39: =IFERROR(R39/Q39,0) -> 40669.492 | T39: =IFERROR(F39/R39,0) -> 0 | U39: =IFERROR(R39/F39,0) -> 0 | V39: =SUMIFS('Business - Dump'!$G:$G,'Business - Dump'!$B:$B,'Portfolio Wise '!$B39,'Business - Dump'!$A:$A,'Portfolio Wise '!$A39) -> 129 | W39: =IFERROR(Q39/V39,0) -> 0.007751938 | X39: =IFERROR(N39/Q39,0) -> 1 | Y39: =IFERROR(O39/R39,0) -> 1 | Z39: =IFERROR(H39/Q39,0) -> 0 | AA39: =IFERROR(O39/R39,0) -> 1 | AB39: =IFERROR(AVERAGEIFS('Business - Dump'!$O:$O,'Business - Dump'!$B:$B,'Portfolio Wise '!$B39,'Business - Dump'!$A:$A,'Portfolio Wise '!$A39),0) -> 0.8607 | AC39: =F39/SUMIFS('Campaign - Dump'!$Q:$Q,'Campaign - Dump'!$A:$A,'Portfolio Wise '!$A39) -> 0 | AD39: =IFERROR(N39/H39,0) -> 0
A40: Dec | B40: Desk Cable Tray | C40: =SUMIFS('Campaign - Dump'!$N:$N,'Campaign - Dump'!$J:$J,'Portfolio Wise '!$B40,'Campaign - Dump'!$A:$A,'Portfolio Wise '!$A40) -> 0 | D40: =SUMIFS('Campaign - Dump'!$O:$O,'Campaign - Dump'!$J:$J,'Portfolio Wise '!$B40,'Campaign - Dump'!$A:$A,'Portfolio Wise '!$A40) -> 0 | E40: =IFERROR(D40/C40,0) -> 0 | F40: =SUMIFS('Campaign - Dump'!$Q:$Q,'Campaign - Dump'!$J:$J,'Portfolio Wise '!$B40,'Campaign - Dump'!$A:$A,'Portfolio Wise '!$A40) -> 0 | G40: =IFERROR(F40/D40,0) -> 0 | H40: =SUMIFS('Campaign - Dump'!$T:$T,'Campaign - Dump'!$J:$J,'Portfolio Wise '!$B40,'Campaign - Dump'!$A:$A,'Portfolio Wise '!$A40) -> 0 | I40: =IFERROR(H40/D40,0) -> 0 | J40: =SUMIFS('Campaign - Dump'!$U:$U,'Campaign - Dump'!$J:$J,'Portfolio Wise '!$B40,'Campaign - Dump'!$A:$A,'Portfolio Wise '!$A40) -> 0 | K40: =IFERROR(F40/J40,0) -> 0 | L40: =IFERROR(J40/F40,0) -> 0 | M40: =IFERROR(J40/H40,0) -> 0 | N40: =IFERROR(Q40-H40,0) -> 9 | O40: =IFERROR(R40-J40,0) -> 9305.0847 | P40: =IFERROR(O40/N40,0) -> 1033.8983 | Q40: =SUMIFS('Business - Dump'!$W:$W,'Business - Dump'!$B:$B,'Portfolio Wise '!$B40,'Business - Dump'!$A:$A,'Portfolio Wise '!$A40) -> 9 | R40: =SUMIFS('Business - Dump'!$U:$U,'Business - Dump'!$B:$B,'Portfolio Wise '!$B40,'Business - Dump'!$A:$A,'Portfolio Wise '!$A40)/1.18 -> 9305.0847 | S40: =IFERROR(R40/Q40,0) -> 1033.8983 | T40: =IFERROR(F40/R40,0) -> 0 | U40: =IFERROR(R40/F40,0) -> 0 | V40: =SUMIFS('Business - Dump'!$G:$G,'Business - Dump'!$B:$B,'Portfolio Wise '!$B40,'Business - Dump'!$A:$A,'Portfolio Wise '!$A40) -> 166 | W40: =IFERROR(Q40/V40,0) -> 0.054216867 | X40: =IFERROR(N40/Q40,0) -> 1 | Y40: =IFERROR(O40/R40,0) -> 1 | Z40: =IFERROR(H40/Q40,0) -> 0 | AA40: =IFERROR(O40/R40,0) -> 1 | AB40: =IFERROR(AVERAGEIFS('Business - Dump'!$O:$O,'Business - Dump'!$B:$B,'Portfolio Wise '!$B40,'Business - Dump'!$A:$A,'Portfolio Wise '!$A40),0) -> 0.9185 | AC40: =F40/SUMIFS('Campaign - Dump'!$Q:$Q,'Campaign - Dump'!$A:$A,'Portfolio Wise '!$A40) -> 0 | AD40: =IFERROR(N40/H40,0) -> 0
A41: Dec | B41: Extension & Holder | C41: =SUMIFS('Campaign - Dump'!$N:$N,'Campaign - Dump'!$J:$J,'Portfolio Wise '!$B41,'Campaign - Dump'!$A:$A,'Portfolio Wise '!$A41) -> 0 | D41: =SUMIFS('Campaign - Dump'!$O:$O,'Campaign - Dump'!$J:$J,'Portfolio Wise '!$B41,'Campaign - Dump'!$A:$A,'Portfolio Wise '!$A41) -> 0 | E41: =IFERROR(D41/C41,0) -> 0 | F41: =SUMIFS('Campaign - Dump'!$Q:$Q,'Campaign - Dump'!$J:$J,'Portfolio Wise '!$B41,'Campaign - Dump'!$A:$A,'Portfolio Wise '!$A41) -> 0 | G41: =IFERROR(F41/D41,0) -> 0 | H41: =SUMIFS('Campaign - Dump'!$T:$T,'Campaign - Dump'!$J:$J,'Portfolio Wise '!$B41,'Campaign - Dump'!$A:$A,'Portfolio Wise '!$A41) -> 0 | I41: =IFERROR(H41/D41,0) -> 0 | J41: =SUMIFS('Campaign - Dump'!$U:$U,'Campaign - Dump'!$J:$J,'Portfolio Wise '!$B41,'Campaign - Dump'!$A:$A,'Portfolio Wise '!$A41) -> 0 | K41: =IFERROR(F41/J41,0) -> 0 | L41: =IFERROR(J41/F41,0) -> 0 | M41: =IFERROR(J41/H41,0) -> 0 | N41: =IFERROR(Q41-H41,0) -> 4 | O41: =IFERROR(R41-J41,0) -> 4491.5254 | P41: =IFERROR(O41/N41,0) -> 1122.8814 | Q41: =SUMIFS('Business - Dump'!$W:$W,'Business - Dump'!$B:$B,'Portfolio Wise '!$B41,'Business - Dump'!$A:$A,'Portfolio Wise '!$A41) -> 4 | R41: =SUMIFS('Business - Dump'!$U:$U,'Business - Dump'!$B:$B,'Portfolio Wise '!$B41,'Business - Dump'!$A:$A,'Portfolio Wise '!$A41)/1.18 -> 4491.5254 | S41: =IFERROR(R41/Q41,0) -> 1122.8814 | T41: =IFERROR(F41/R41,0) -> 0 | U41: =IFERROR(R41/F41,0) -> 0 | V41: =SUMIFS('Business - Dump'!$G:$G,'Business - Dump'!$B:$B,'Portfolio Wise '!$B41,'Business - Dump'!$A:$A,'Portfolio Wise '!$A41) -> 341 | W41: =IFERROR(Q41/V41,0) -> 0.011730205 | X41: =IFERROR(N41/Q41,0) -> 1 | Y41: =IFERROR(O41/R41,0) -> 1 | Z41: =IFERROR(H41/Q41,0) -> 0 | AA41: =IFERROR(O41/R41,0) -> 1 | AB41: =IFERROR(AVERAGEIFS('Business - Dump'!$O:$O,'Business - Dump'!$B:$B,'Portfolio Wise '!$B41,'Business - Dump'!$A:$A,'Portfolio Wise '!$A41),0) -> 0.8759 | AC41: =F41/SUMIFS('Campaign - Dump'!$Q:$Q,'Campaign - Dump'!$A:$A,'Portfolio Wise '!$A41) -> 0 | AD41: =IFERROR(N41/H41,0) -> 0
A42: Dec | B42: Standing Table - E4 | C42: =SUMIFS('Campaign - Dump'!$N:$N,'Campaign - Dump'!$J:$J,'Portfolio Wise '!$B42,'Campaign - Dump'!$A:$A,'Portfolio Wise '!$A42) -> 0 | D42: =SUMIFS('Campaign - Dump'!$O:$O,'Campaign - Dump'!$J:$J,'Portfolio Wise '!$B42,'Campaign - Dump'!$A:$A,'Portfolio Wise '!$A42) -> 0 | E42: =IFERROR(D42/C42,0) -> 0 | F42: =SUMIFS('Campaign - Dump'!$Q:$Q,'Campaign - Dump'!$J:$J,'Portfolio Wise '!$B42,'Campaign - Dump'!$A:$A,'Portfolio Wise '!$A42) -> 0 | G42: =IFERROR(F42/D42,0) -> 0 | H42: =SUMIFS('Campaign - Dump'!$T:$T,'Campaign - Dump'!$J:$J,'Portfolio Wise '!$B42,'Campaign - Dump'!$A:$A,'Portfolio Wise '!$A42) -> 0 | I42: =IFERROR(H42/D42,0) -> 0 | J42: =SUMIFS('Campaign - Dump'!$U:$U,'Campaign - Dump'!$J:$J,'Portfolio Wise '!$B42,'Campaign - Dump'!$A:$A,'Portfolio Wise '!$A42) -> 0 | K42: =IFERROR(F42/J42,0) -> 0 | L42: =IFERROR(J42/F42,0) -> 0 | M42: =IFERROR(J42/H42,0) -> 0 | N42: =IFERROR(Q42-H42,0) -> 0 | O42: =IFERROR(R42-J42,0) -> 0 | P42: =IFERROR(O42/N42,0) -> 0 | Q42: =SUMIFS('Business - Dump'!$W:$W,'Business - Dump'!$B:$B,'Portfolio Wise '!$B42,'Business - Dump'!$A:$A,'Portfolio Wise '!$A42) -> 0 | R42: =SUMIFS('Business - Dump'!$U:$U,'Business - Dump'!$B:$B,'Portfolio Wise '!$B42,'Business - Dump'!$A:$A,'Portfolio Wise '!$A42)/1.18 -> 0 | S42: =IFERROR(R42/Q42,0) -> 0 | T42: =IFERROR(F42/R42,0) -> 0 | U42: =IFERROR(R42/F42,0) -> 0 | V42: =SUMIFS('Business - Dump'!$G:$G,'Business - Dump'!$B:$B,'Portfolio Wise '!$B42,'Business - Dump'!$A:$A,'Portfolio Wise '!$A42) -> 0 | W42: =IFERROR(Q42/V42,0) -> 0 | X42: =IFERROR(N42/Q42,0) -> 0 | Y42: =IFERROR(O42/R42,0) -> 0 | Z42: =IFERROR(H42/Q42,0) -> 0 | AA42: =IFERROR(O42/R42,0) -> 0 | AB42: =IFERROR(AVERAGEIFS('Business - Dump'!$O:$O,'Business - Dump'!$B:$B,'Portfolio Wise '!$B42,'Business - Dump'!$A:$A,'Portfolio Wise '!$A42),0) -> 0 | AC42: =F42/SUMIFS('Campaign - Dump'!$Q:$Q,'Campaign - Dump'!$A:$A,'Portfolio Wise '!$A42) -> 0 | AD42: =IFERROR(N42/H42,0) -> 0
A43: Dec | B43: Standing Table - E4 | C43: =SUMIFS('Campaign - Dump'!$N:$N,'Campaign - Dump'!$J:$J,'Portfolio Wise '!$B43,'Campaign - Dump'!$A:$A,'Portfolio Wise '!$A43) -> 0 | D43: =SUMIFS('Campaign - Dump'!$O:$O,'Campaign - Dump'!$J:$J,'Portfolio Wise '!$B43,'Campaign - Dump'!$A:$A,'Portfolio Wise '!$A43) -> 0 | E43: =IFERROR(D43/C43,0) -> 0 | F43: =SUMIFS('Campaign - Dump'!$Q:$Q,'Campaign - Dump'!$J:$J,'Portfolio Wise '!$B43,'Campaign - Dump'!$A:$A,'Portfolio Wise '!$A43) -> 0 | G43: =IFERROR(F43/D43,0) -> 0 | H43: =SUMIFS('Campaign - Dump'!$T:$T,'Campaign - Dump'!$J:$J,'Portfolio Wise '!$B43,'Campaign - Dump'!$A:$A,'Portfolio Wise '!$A43) -> 0 | I43: =IFERROR(H43/D43,0) -> 0 | J43: =SUMIFS('Campaign - Dump'!$U:$U,'Campaign - Dump'!$J:$J,'Portfolio Wise '!$B43,'Campaign - Dump'!$A:$A,'Portfolio Wise '!$A43) -> 0 | K43: =IFERROR(F43/J43,0) -> 0 | L43: =IFERROR(J43/F43,0) -> 0 | M43: =IFERROR(J43/H43,0) -> 0 | N43: =IFERROR(Q43-H43,0) -> 0 | O43: =IFERROR(R43-J43,0) -> 0 | P43: =IFERROR(O43/N43,0) -> 0 | Q43: =SUMIFS('Business - Dump'!$W:$W,'Business - Dump'!$B:$B,'Portfolio Wise '!$B43,'Business - Dump'!$A:$A,'Portfolio Wise '!$A43) -> 0 | R43: =SUMIFS('Business - Dump'!$U:$U,'Business - Dump'!$B:$B,'Portfolio Wise '!$B43,'Business - Dump'!$A:$A,'Portfolio Wise '!$A43)/1.18 -> 0 | S43: =IFERROR(R43/Q43,0) -> 0 | T43: =IFERROR(F43/R43,0) -> 0 | U43: =IFERROR(R43/F43,0) -> 0 | V43: =SUMIFS('Business - Dump'!$G:$G,'Business - Dump'!$B:$B,'Portfolio Wise '!$B43,'Business - Dump'!$A:$A,'Portfolio Wise '!$A43) -> 0 | W43: =IFERROR(Q43/V43,0) -> 0 | X43: =IFERROR(N43/Q43,0) -> 0 | Y43: =IFERROR(O43/R43,0) -> 0 | Z43: =IFERROR(H43/Q43,0) -> 0 | AA43: =IFERROR(O43/R43,0) -> 0 | AB43: =IFERROR(AVERAGEIFS('Business - Dump'!$O:$O,'Business - Dump'!$B:$B,'Portfolio Wise '!$B43,'Business - Dump'!$A:$A,'Portfolio Wise '!$A43),0) -> 0 | AC43: =F43/SUMIFS('Campaign - Dump'!$Q:$Q,'Campaign - Dump'!$A:$A,'Portfolio Wise '!$A43) -> 0 | AD43: =IFERROR(N43/H43,0) -> 0
A44: Dec | B44: Standing Table - M8 | C44: =SUMIFS('Campaign - Dump'!$N:$N,'Campaign - Dump'!$J:$J,'Portfolio Wise '!$B44,'Campaign - Dump'!$A:$A,'Portfolio Wise '!$A44) -> 0 | D44: =SUMIFS('Campaign - Dump'!$O:$O,'Campaign - Dump'!$J:$J,'Portfolio Wise '!$B44,'Campaign - Dump'!$A:$A,'Portfolio Wise '!$A44) -> 0 | E44: =IFERROR(D44/C44,0) -> 0 | F44: =SUMIFS('Campaign - Dump'!$Q:$Q,'Campaign - Dump'!$J:$J,'Portfolio Wise '!$B44,'Campaign - Dump'!$A:$A,'Portfolio Wise '!$A44) -> 0 | G44: =IFERROR(F44/D44,0) -> 0 | H44: =SUMIFS('Campaign - Dump'!$T:$T,'Campaign - Dump'!$J:$J,'Portfolio Wise '!$B44,'Campaign - Dump'!$A:$A,'Portfolio Wise '!$A44) -> 0 | I44: =IFERROR(H44/D44,0) -> 0 | J44: =SUMIFS('Campaign - Dump'!$U:$U,'Campaign - Dump'!$J:$J,'Portfolio Wise '!$B44,'Campaign - Dump'!$A:$A,'Portfolio Wise '!$A44) -> 0 | K44: =IFERROR(F44/J44,0) -> 0 | L44: =IFERROR(J44/F44,0) -> 0 | M44: =IFERROR(J44/H44,0) -> 0 | N44: =IFERROR(Q44-H44,0) -> 52 | O44: =IFERROR(R44-J44,0) -> 754201.69 | P44: =IFERROR(O44/N44,0) -> 14503.879 | Q44: =SUMIFS('Business - Dump'!$W:$W,'Business - Dump'!$B:$B,'Portfolio Wise '!$B44,'Business - Dump'!$A:$A,'Portfolio Wise '!$A44) -> 52 | R44: =SUMIFS('Business - Dump'!$U:$U,'Business - Dump'!$B:$B,'Portfolio Wise '!$B44,'Business - Dump'!$A:$A,'Portfolio Wise '!$A44)/1.18 -> 754201.69 | S44: =IFERROR(R44/Q44,0) -> 14503.879 | T44: =IFERROR(F44/R44,0) -> 0 | U44: =IFERROR(R44/F44,0) -> 0 | V44: =SUMIFS('Business - Dump'!$G:$G,'Business - Dump'!$B:$B,'Portfolio Wise '!$B44,'Business - Dump'!$A:$A,'Portfolio Wise '!$A44) -> 7682 | W44: =IFERROR(Q44/V44,0) -> 0.0067690706 | X44: =IFERROR(N44/Q44,0) -> 1 | Y44: =IFERROR(O44/R44,0) -> 1 | Z44: =IFERROR(H44/Q44,0) -> 0 | AA44: =IFERROR(O44/R44,0) -> 1 | AB44: =IFERROR(AVERAGEIFS('Business - Dump'!$O:$O,'Business - Dump'!$B:$B,'Portfolio Wise '!$B44,'Business - Dump'!$A:$A,'Portfolio Wise '!$A44),0) -> 0.88038 | AC44: =F44/SUMIFS('Campaign - Dump'!$Q:$Q,'Campaign - Dump'!$A:$A,'Portfolio Wise '!$A44) -> 0 | AD44: =IFERROR(N44/H44,0) -> 0
A45: Dec | B45: Video Funnel | C45: =SUMIFS('Campaign - Dump'!$N:$N,'Campaign - Dump'!$J:$J,'Portfolio Wise '!$B45,'Campaign - Dump'!$A:$A,'Portfolio Wise '!$A45) -> 0 | D45: =SUMIFS('Campaign - Dump'!$O:$O,'Campaign - Dump'!$J:$J,'Portfolio Wise '!$B45,'Campaign - Dump'!$A:$A,'Portfolio Wise '!$A45) -> 0 | E45: =IFERROR(D45/C45,0) -> 0 | F45: =SUMIFS('Campaign - Dump'!$Q:$Q,'Campaign - Dump'!$J:$J,'Portfolio Wise '!$B45,'Campaign - Dump'!$A:$A,'Portfolio Wise '!$A45) -> 0 | G45: =IFERROR(F45/D45,0) -> 0 | H45: =SUMIFS('Campaign - Dump'!$T:$T,'Campaign - Dump'!$J:$J,'Portfolio Wise '!$B45,'Campaign - Dump'!$A:$A,'Portfolio Wise '!$A45) -> 0 | I45: =IFERROR(H45/D45,0) -> 0 | J45: =SUMIFS('Campaign - Dump'!$U:$U,'Campaign - Dump'!$J:$J,'Portfolio Wise '!$B45,'Campaign - Dump'!$A:$A,'Portfolio Wise '!$A45) -> 0 | K45: =IFERROR(F45/J45,0) -> 0 | L45: =IFERROR(J45/F45,0) -> 0 | M45: =IFERROR(J45/H45,0) -> 0 | N45: =IFERROR(Q45-H45,0) -> 0 | O45: =IFERROR(R45-J45,0) -> 0 | P45: =IFERROR(O45/N45,0) -> 0 | Q45: =SUMIFS('Business - Dump'!$W:$W,'Business - Dump'!$B:$B,'Portfolio Wise '!$B45,'Business - Dump'!$A:$A,'Portfolio Wise '!$A45) -> 0 | R45: =SUMIFS('Business - Dump'!$U:$U,'Business - Dump'!$B:$B,'Portfolio Wise '!$B45,'Business - Dump'!$A:$A,'Portfolio Wise '!$A45)/1.18 -> 0 | S45: =IFERROR(R45/Q45,0) -> 0 | T45: =IFERROR(F45/R45,0) -> 0 | U45: =IFERROR(R45/F45,0) -> 0 | V45: =SUMIFS('Business - Dump'!$G:$G,'Business - Dump'!$B:$B,'Portfolio Wise '!$B45,'Business - Dump'!$A:$A,'Portfolio Wise '!$A45) -> 0 | W45: =IFERROR(Q45/V45,0) -> 0 | X45: =IFERROR(N45/Q45,0) -> 0 | Y45: =IFERROR(O45/R45,0) -> 0 | Z45: =IFERROR(H45/Q45,0) -> 0 | AA45: =IFERROR(O45/R45,0) -> 0 | AB45: =IFERROR(AVERAGEIFS('Business - Dump'!$O:$O,'Business - Dump'!$B:$B,'Portfolio Wise '!$B45,'Business - Dump'!$A:$A,'Portfolio Wise '!$A45),0) -> 0 | AC45: =F45/SUMIFS('Campaign - Dump'!$Q:$Q,'Campaign - Dump'!$A:$A,'Portfolio Wise '!$A45) -> 0 | AD45: =IFERROR(N45/H45,0) -> 0
A46: Dec | B46: Keyboard Tray | C46: =SUMIFS('Campaign - Dump'!$N:$N,'Campaign - Dump'!$J:$J,'Portfolio Wise '!$B46,'Campaign - Dump'!$A:$A,'Portfolio Wise '!$A46) -> 0 | D46: =SUMIFS('Campaign - Dump'!$O:$O,'Campaign - Dump'!$J:$J,'Portfolio Wise '!$B46,'Campaign - Dump'!$A:$A,'Portfolio Wise '!$A46) -> 0 | E46: =IFERROR(D46/C46,0) -> 0 | F46: =SUMIFS('Campaign - Dump'!$Q:$Q,'Campaign - Dump'!$J:$J,'Portfolio Wise '!$B46,'Campaign - Dump'!$A:$A,'Portfolio Wise '!$A46) -> 0 | G46: =IFERROR(F46/D46,0) -> 0 | H46: =SUMIFS('Campaign - Dump'!$T:$T,'Campaign - Dump'!$J:$J,'Portfolio Wise '!$B46,'Campaign - Dump'!$A:$A,'Portfolio Wise '!$A46) -> 0 | I46: =IFERROR(H46/D46,0) -> 0 | J46: =SUMIFS('Campaign - Dump'!$U:$U,'Campaign - Dump'!$J:$J,'Portfolio Wise '!$B46,'Campaign - Dump'!$A:$A,'Portfolio Wise '!$A46) -> 0 | K46: =IFERROR(F46/J46,0) -> 0 | L46: =IFERROR(J46/F46,0) -> 0 | M46: =IFERROR(J46/H46,0) -> 0 | N46: =IFERROR(Q46-H46,0) -> 0 | O46: =IFERROR(R46-J46,0) -> 0 | P46: =IFERROR(O46/N46,0) -> 0 | Q46: =SUMIFS('Business - Dump'!$W:$W,'Business - Dump'!$B:$B,'Portfolio Wise '!$B46,'Business - Dump'!$A:$A,'Portfolio Wise '!$A46) -> 0 | R46: =SUMIFS('Business - Dump'!$U:$U,'Business - Dump'!$B:$B,'Portfolio Wise '!$B46,'Business - Dump'!$A:$A,'Portfolio Wise '!$A46)/1.18 -> 0 | S46: =IFERROR(R46/Q46,0) -> 0 | T46: =IFERROR(F46/R46,0) -> 0 | U46: =IFERROR(R46/F46,0) -> 0 | V46: =SUMIFS('Business - Dump'!$G:$G,'Business - Dump'!$B:$B,'Portfolio Wise '!$B46,'Business - Dump'!$A:$A,'Portfolio Wise '!$A46) -> 0 | W46: =IFERROR(Q46/V46,0) -> 0 | X46: =IFERROR(N46/Q46,0) -> 0 | Y46: =IFERROR(O46/R46,0) -> 0 | Z46: =IFERROR(H46/Q46,0) -> 0 | AA46: =IFERROR(O46/R46,0) -> 0 | AB46: =IFERROR(AVERAGEIFS('Business - Dump'!$O:$O,'Business - Dump'!$B:$B,'Portfolio Wise '!$B46,'Business - Dump'!$A:$A,'Portfolio Wise '!$A46),0) -> 0 | AC46: =F46/SUMIFS('Campaign - Dump'!$Q:$Q,'Campaign - Dump'!$A:$A,'Portfolio Wise '!$A46) -> 0 | AD46: =IFERROR(N46/H46,0) -> 0
A47: Dec | B47: Footrests | C47: =SUMIFS('Campaign - Dump'!$N:$N,'Campaign - Dump'!$J:$J,'Portfolio Wise '!$B47,'Campaign - Dump'!$A:$A,'Portfolio Wise '!$A47) -> 0 | D47: =SUMIFS('Campaign - Dump'!$O:$O,'Campaign - Dump'!$J:$J,'Portfolio Wise '!$B47,'Campaign - Dump'!$A:$A,'Portfolio Wise '!$A47) -> 0 | E47: =IFERROR(D47/C47,0) -> 0 | F47: =SUMIFS('Campaign - Dump'!$Q:$Q,'Campaign - Dump'!$J:$J,'Portfolio Wise '!$B47,'Campaign - Dump'!$A:$A,'Portfolio Wise '!$A47) -> 0 | G47: =IFERROR(F47/D47,0) -> 0 | H47: =SUMIFS('Campaign - Dump'!$T:$T,'Campaign - Dump'!$J:$J,'Portfolio Wise '!$B47,'Campaign - Dump'!$A:$A,'Portfolio Wise '!$A47) -> 0 | I47: =IFERROR(H47/D47,0) -> 0 | J47: =SUMIFS('Campaign - Dump'!$U:$U,'Campaign - Dump'!$J:$J,'Portfolio Wise '!$B47,'Campaign - Dump'!$A:$A,'Portfolio Wise '!$A47) -> 0 | K47: =IFERROR(F47/J47,0) -> 0 | L47: =IFERROR(J47/F47,0) -> 0 | M47: =IFERROR(J47/H47,0) -> 0 | N47: =IFERROR(Q47-H47,0) -> 4 | O47: =IFERROR(R47-J47,0) -> 8457.6271 | P47: =IFERROR(O47/N47,0) -> 2114.4068 | Q47: =SUMIFS('Business - Dump'!$W:$W,'Business - Dump'!$B:$B,'Portfolio Wise '!$B47,'Business - Dump'!$A:$A,'Portfolio Wise '!$A47) -> 4 | R47: =SUMIFS('Business - Dump'!$U:$U,'Business - Dump'!$B:$B,'Portfolio Wise '!$B47,'Business - Dump'!$A:$A,'Portfolio Wise '!$A47)/1.18 -> 8457.6271 | S47: =IFERROR(R47/Q47,0) -> 2114.4068 | T47: =IFERROR(F47/R47,0) -> 0 | U47: =IFERROR(R47/F47,0) -> 0 | V47: =SUMIFS('Business - Dump'!$G:$G,'Business - Dump'!$B:$B,'Portfolio Wise '!$B47,'Business - Dump'!$A:$A,'Portfolio Wise '!$A47) -> 95 | W47: =IFERROR(Q47/V47,0) -> 0.042105263 | X47: =IFERROR(N47/Q47,0) -> 1 | Y47: =IFERROR(O47/R47,0) -> 1 | Z47: =IFERROR(H47/Q47,0) -> 0 | AA47: =IFERROR(O47/R47,0) -> 1 | AB47: =IFERROR(AVERAGEIFS('Business - Dump'!$O:$O,'Business - Dump'!$B:$B,'Portfolio Wise '!$B47,'Business - Dump'!$A:$A,'Portfolio Wise '!$A47),0) -> 0.82956667 | AC47: =F47/SUMIFS('Campaign - Dump'!$Q:$Q,'Campaign - Dump'!$A:$A,'Portfolio Wise '!$A47) -> 0 | AD47: =IFERROR(N47/H47,0) -> 0
A48: Dec | B48: Single Leg Gas | C48: =SUMIFS('Campaign - Dump'!$N:$N,'Campaign - Dump'!$J:$J,'Portfolio Wise '!$B48,'Campaign - Dump'!$A:$A,'Portfolio Wise '!$A48) -> 0 | D48: =SUMIFS('Campaign - Dump'!$O:$O,'Campaign - Dump'!$J:$J,'Portfolio Wise '!$B48,'Campaign - Dump'!$A:$A,'Portfolio Wise '!$A48) -> 0 | E48: =IFERROR(D48/C48,0) -> 0 | F48: =SUMIFS('Campaign - Dump'!$Q:$Q,'Campaign - Dump'!$J:$J,'Portfolio Wise '!$B48,'Campaign - Dump'!$A:$A,'Portfolio Wise '!$A48) -> 0 | G48: =IFERROR(F48/D48,0) -> 0 | H48: =SUMIFS('Campaign - Dump'!$T:$T,'Campaign - Dump'!$J:$J,'Portfolio Wise '!$B48,'Campaign - Dump'!$A:$A,'Portfolio Wise '!$A48) -> 0 | I48: =IFERROR(H48/D48,0) -> 0 | J48: =SUMIFS('Campaign - Dump'!$U:$U,'Campaign - Dump'!$J:$J,'Portfolio Wise '!$B48,'Campaign - Dump'!$A:$A,'Portfolio Wise '!$A48) -> 0 | K48: =IFERROR(F48/J48,0) -> 0 | L48: =IFERROR(J48/F48,0) -> 0 | M48: =IFERROR(J48/H48,0) -> 0 | N48: =IFERROR(Q48-H48,0) -> 6 | O48: =IFERROR(R48-J48,0) -> 59661.017 | P48: =IFERROR(O48/N48,0) -> 9943.5028 | Q48: =SUMIFS('Business - Dump'!$W:$W,'Business - Dump'!$B:$B,'Portfolio Wise '!$B48,'Business - Dump'!$A:$A,'Portfolio Wise '!$A48) -> 6 | R48: =SUMIFS('Business - Dump'!$U:$U,'Business - Dump'!$B:$B,'Portfolio Wise '!$B48,'Business - Dump'!$A:$A,'Portfolio Wise '!$A48)/1.18 -> 59661.017 | S48: =IFERROR(R48/Q48,0) -> 9943.5028 | T48: =IFERROR(F48/R48,0) -> 0 | U48: =IFERROR(R48/F48,0) -> 0 | V48: =SUMIFS('Business - Dump'!$G:$G,'Business - Dump'!$B:$B,'Portfolio Wise '!$B48,'Business - Dump'!$A:$A,'Portfolio Wise '!$A48) -> 371 | W48: =IFERROR(Q48/V48,0) -> 0.016172507 | X48: =IFERROR(N48/Q48,0) -> 1 | Y48: =IFERROR(O48/R48,0) -> 1 | Z48: =IFERROR(H48/Q48,0) -> 0 | AA48: =IFERROR(O48/R48,0) -> 1 | AB48: =IFERROR(AVERAGEIFS('Business - Dump'!$O:$O,'Business - Dump'!$B:$B,'Portfolio Wise '!$B48,'Business - Dump'!$A:$A,'Portfolio Wise '!$A48),0) -> 0.86873333 | AC48: =F48/SUMIFS('Campaign - Dump'!$Q:$Q,'Campaign - Dump'!$A:$A,'Portfolio Wise '!$A48) -> 0 | AD48: =IFERROR(N48/H48,0) -> 0
A49: Dec | B49: Total Dec | C49: =SUM(C26:C48) -> 4473747 | D49: =SUM(D26:D48) -> 17084 | E49: =IFERROR(D49/C49,0) -> 0.0038187229 | F49: =SUM(F26:F48) -> 260856.05 | G49: =IFERROR(F49/D49,0) -> 15.269027 | H49: =SUM(H26:H48) -> 140 | I49: =IFERROR(H49/D49,0) -> 0.0081948022 | J49: =SUM(J26:J48) -> 2470927.7 | K49: =IFERROR(F49/J49,0) -> 0.10557009 | L49: =IFERROR(J49/F49,0) -> 9.4723803 | M49: =IFERROR(J49/H49,0) -> 17649.484 | N49: =SUM(N26:N48) -> 164 | O49: =SUM(O26:O48) -> 2618317 | P49: =IFERROR(O49/N49,0) -> 15965.348 | Q49: =SUM(Q26:Q48) -> 212 | R49: =SUM(R26:R48) -> 3584922 | S49: =IFERROR(R49/Q49,0) -> 16910.01 | T49: =IFERROR(F49/R49,0) -> 0.072764776 | U49: =IFERROR(R49/F49,0) -> 13.742913 | V49: =SUM(V26:V48) -> 31446 | W49: =IFERROR(Q49/V49,0) -> 0.006741716 | X49: =IFERROR(N49/Q49,0) -> 0.77358491 | Y49: =IFERROR(O49/R49,0) -> 0.73036931 | Z49: =IFERROR(H49/Q49,0) -> 0.66037736 | AA49: =IFERROR(O49/R49,0) -> 0.73036931 | AB49: =IFERROR(AVERAGEIFS('Business - Dump'!$O:$O,'Business - Dump'!$B:$B,'Portfolio Wise '!$B49,'Business - Dump'!$A:$A,'Portfolio Wise '!$A49),0) -> 0 | AC49: =F49/SUMIFS('Campaign - Dump'!$Q:$Q,'Campaign - Dump'!$A:$A,'Portfolio Wise '!$A49) -> 1 | AD49: =IFERROR(N49/H49,0) -> 1.1714286
A50: Jan | B50: Sales Day | C50: =SUMIFS('Campaign - Dump'!$N:$N,'Campaign - Dump'!$J:$J,'Portfolio Wise '!$B50,'Campaign - Dump'!$A:$A,'Portfolio Wise '!$A50) -> 686769 | D50: =SUMIFS('Campaign - Dump'!$O:$O,'Campaign - Dump'!$J:$J,'Portfolio Wise '!$B50,'Campaign - Dump'!$A:$A,'Portfolio Wise '!$A50) -> 2881 | E50: =IFERROR(D50/C50,0) -> 0.0041950059 | F50: =SUMIFS('Campaign - Dump'!$Q:$Q,'Campaign - Dump'!$J:$J,'Portfolio Wise '!$B50,'Campaign - Dump'!$A:$A,'Portfolio Wise '!$A50) -> 21351.63 | G50: =IFERROR(F50/D50,0) -> 7.4111871 | H50: =SUMIFS('Campaign - Dump'!$T:$T,'Campaign - Dump'!$J:$J,'Portfolio Wise '!$B50,'Campaign - Dump'!$A:$A,'Portfolio Wise '!$A50) -> 3 | I50: =IFERROR(H50/D50,0) -> 0.0010413051 | J50: =SUMIFS('Campaign - Dump'!$U:$U,'Campaign - Dump'!$J:$J,'Portfolio Wise '!$B50,'Campaign - Dump'!$A:$A,'Portfolio Wise '!$A50) -> 49583.9 | K50: =IFERROR(F50/J50,0) -> 0.43061619 | L50: =IFERROR(J50/F50,0) -> 2.3222536 | M50: =IFERROR(J50/H50,0) -> 16527.967 | N50: 0 | O50: 0 | P50: =IFERROR(O50/N50,0) -> 0 | Q50: =SUMIFS('Business - Dump'!$W:$W,'Business - Dump'!$B:$B,'Portfolio Wise '!$B50,'Business - Dump'!$A:$A,'Portfolio Wise '!$A50) -> 0 | R50: =SUMIFS('Business - Dump'!$U:$U,'Business - Dump'!$B:$B,'Portfolio Wise '!$B50,'Business - Dump'!$A:$A,'Portfolio Wise '!$A50)/1.18 -> 0 | S50: =IFERROR(R50/Q50,0) -> 0 | T50: =IFERROR(F50/R50,0) -> 0 | U50: =IFERROR(R50/F50,0) -> 0 | V50: =SUMIFS('Business - Dump'!$G:$G,'Business - Dump'!$B:$B,'Portfolio Wise '!$B50,'Business - Dump'!$A:$A,'Portfolio Wise '!$A50) -> 0 | W50: =IFERROR(Q50/V50,0) -> 0 | X50: =IFERROR(N50/Q50,0) -> 0 | Y50: =IFERROR(O50/R50,0) -> 0 | Z50: =IFERROR(H50/Q50,0) -> 0 | AA50: =IFERROR(O50/R50,0) -> 0 | AB50: =IFERROR(AVERAGEIFS('Business - Dump'!$O:$O,'Business - Dump'!$B:$B,'Portfolio Wise '!$B50,'Business - Dump'!$A:$A,'Portfolio Wise '!$A50),0) -> 0 | AC50: =F50/SUMIFS('Campaign - Dump'!$Q:$Q,'Campaign - Dump'!$A:$A,'Portfolio Wise '!$A50) -> 0.079094354 | AD50: =IFERROR(N50/H50,0) -> 0
A51: Jan | B51: Standing Table | C51: =SUMIFS('Campaign - Dump'!$N:$N,'Campaign - Dump'!$J:$J,'Portfolio Wise '!$B51,'Campaign - Dump'!$A:$A,'Portfolio Wise '!$A51) -> 0 | D51: =SUMIFS('Campaign - Dump'!$O:$O,'Campaign - Dump'!$J:$J,'Portfolio Wise '!$B51,'Campaign - Dump'!$A:$A,'Portfolio Wise '!$A51) -> 0 | E51: =IFERROR(D51/C51,0) -> 0 | F51: =SUMIFS('Campaign - Dump'!$Q:$Q,'Campaign - Dump'!$J:$J,'Portfolio Wise '!$B51,'Campaign - Dump'!$A:$A,'Portfolio Wise '!$A51) -> 0 | G51: =IFERROR(F51/D51,0) -> 0 | H51: =SUMIFS('Campaign - Dump'!$T:$T,'Campaign - Dump'!$J:$J,'Portfolio Wise '!$B51,'Campaign - Dump'!$A:$A,'Portfolio Wise '!$A51) -> 0 | I51: =IFERROR(H51/D51,0) -> 0 | J51: =SUMIFS('Campaign - Dump'!$U:$U,'Campaign - Dump'!$J:$J,'Portfolio Wise '!$B51,'Campaign - Dump'!$A:$A,'Portfolio Wise '!$A51) -> 0 | K51: =IFERROR(F51/J51,0) -> 0 | L51: =IFERROR(J51/F51,0) -> 0 | M51: =IFERROR(J51/H51,0) -> 0 | N51: =IFERROR(Q51-H51,0) -> 0 | O51: =IFERROR(R51-J51,0) -> 0 | P51: =IFERROR(O51/N51,0) -> 0 | Q51: =SUMIFS('Business - Dump'!$W:$W,'Business - Dump'!$B:$B,'Portfolio Wise '!$B51,'Business - Dump'!$A:$A,'Portfolio Wise '!$A51) -> 0 | R51: =SUMIFS('Business - Dump'!$U:$U,'Business - Dump'!$B:$B,'Portfolio Wise '!$B51,'Business - Dump'!$A:$A,'Portfolio Wise '!$A51)/1.18 -> 0 | S51: =IFERROR(R51/Q51,0) -> 0 | T51: =IFERROR(F51/R51,0) -> 0 | U51: =IFERROR(R51/F51,0) -> 0 | V51: =SUMIFS('Business - Dump'!$G:$G,'Business - Dump'!$B:$B,'Portfolio Wise '!$B51,'Business - Dump'!$A:$A,'Portfolio Wise '!$A51) -> 0 | W51: =IFERROR(Q51/V51,0) -> 0 | X51: =IFERROR(N51/Q51,0) -> 0 | Y51: =IFERROR(O51/R51,0) -> 0 | Z51: =IFERROR(H51/Q51,0) -> 0 | AA51: =IFERROR(O51/R51,0) -> 0 | AB51: =IFERROR(AVERAGEIFS('Business - Dump'!$O:$O,'Business - Dump'!$B:$B,'Portfolio Wise '!$B51,'Business - Dump'!$A:$A,'Portfolio Wise '!$A51),0) -> 0 | AC51: =F51/SUMIFS('Campaign - Dump'!$Q:$Q,'Campaign - Dump'!$A:$A,'Portfolio Wise '!$A51) -> 0 | AD51: =IFERROR(N51/H51,0) -> 0
A52: Jan | B52: TABLE TOP | C52: =SUMIFS('Campaign - Dump'!$N:$N,'Campaign - Dump'!$J:$J,'Portfolio Wise '!$B52,'Campaign - Dump'!$A:$A,'Portfolio Wise '!$A52) -> 160352 | D52: =SUMIFS('Campaign - Dump'!$O:$O,'Campaign - Dump'!$J:$J,'Portfolio Wise '!$B52,'Campaign - Dump'!$A:$A,'Portfolio Wise '!$A52) -> 498 | E52: =IFERROR(D52/C52,0) -> 0.0031056675 | F52: =SUMIFS('Campaign - Dump'!$Q:$Q,'Campaign - Dump'!$J:$J,'Portfolio Wise '!$B52,'Campaign - Dump'!$A:$A,'Portfolio Wise '!$A52) -> 5723.43 | G52: =IFERROR(F52/D52,0) -> 11.492831 | H52: =SUMIFS('Campaign - Dump'!$T:$T,'Campaign - Dump'!$J:$J,'Portfolio Wise '!$B52,'Campaign - Dump'!$A:$A,'Portfolio Wise '!$A52) -> 1 | I52: =IFERROR(H52/D52,0) -> 0.0020080321 | J52: =SUMIFS('Campaign - Dump'!$U:$U,'Campaign - Dump'!$J:$J,'Portfolio Wise '!$B52,'Campaign - Dump'!$A:$A,'Portfolio Wise '!$A52) -> 3771.18 | K52: =IFERROR(F52/J52,0) -> 1.5176762 | L52: =IFERROR(J52/F52,0) -> 0.65890209 | M52: =IFERROR(J52/H52,0) -> 3771.18 | N52: =IFERROR(Q52-H52,0) -> 1 | O52: =IFERROR(R52-J52,0) -> 6228.82 | P52: =IFERROR(O52/N52,0) -> 6228.82 | Q52: =SUMIFS('Business - Dump'!$W:$W,'Business - Dump'!$B:$B,'Portfolio Wise '!$B52,'Business - Dump'!$A:$A,'Portfolio Wise '!$A52) -> 2 | R52: =SUMIFS('Business - Dump'!$U:$U,'Business - Dump'!$B:$B,'Portfolio Wise '!$B52,'Business - Dump'!$A:$A,'Portfolio Wise '!$A52)/1.18 -> 10000 | S52: =IFERROR(R52/Q52,0) -> 5000 | T52: =IFERROR(F52/R52,0) -> 0.572343 | U52: =IFERROR(R52/F52,0) -> 1.747204 | V52: =SUMIFS('Business - Dump'!$G:$G,'Business - Dump'!$B:$B,'Portfolio Wise '!$B52,'Business - Dump'!$A:$A,'Portfolio Wise '!$A52) -> 1059 | W52: =IFERROR(Q52/V52,0) -> 0.0018885741 | X52: =IFERROR(N52/Q52,0) -> 0.5 | Y52: =IFERROR(O52/R52,0) -> 0.622882 | Z52: =IFERROR(H52/Q52,0) -> 0.5 | AA52: =IFERROR(O52/R52,0) -> 0.622882 | AB52: =IFERROR(AVERAGEIFS('Business - Dump'!$O:$O,'Business - Dump'!$B:$B,'Portfolio Wise '!$B52,'Business - Dump'!$A:$A,'Portfolio Wise '!$A52),0) -> 0.84385 | AC52: =F52/SUMIFS('Campaign - Dump'!$Q:$Q,'Campaign - Dump'!$A:$A,'Portfolio Wise '!$A52) -> 0.021201707 | AD52: =IFERROR(N52/H52,0) -> 1
A53: Jan | B53: Brand | C53: =SUMIFS('Campaign - Dump'!$N:$N,'Campaign - Dump'!$J:$J,'Portfolio Wise '!$B53,'Campaign - Dump'!$A:$A,'Portfolio Wise '!$A53) -> 439464 | D53: =SUMIFS('Campaign - Dump'!$O:$O,'Campaign - Dump'!$J:$J,'Portfolio Wise '!$B53,'Campaign - Dump'!$A:$A,'Portfolio Wise '!$A53) -> 2063 | E53: =IFERROR(D53/C53,0) -> 0.0046943549 | F53: =SUMIFS('Campaign - Dump'!$Q:$Q,'Campaign - Dump'!$J:$J,'Portfolio Wise '!$B53,'Campaign - Dump'!$A:$A,'Portfolio Wise '!$A53) -> 61844.96 | G53: =IFERROR(F53/D53,0) -> 29.978168 | H53: =SUMIFS('Campaign - Dump'!$T:$T,'Campaign - Dump'!$J:$J,'Portfolio Wise '!$B53,'Campaign - Dump'!$A:$A,'Portfolio Wise '!$A53) -> 38 | I53: =IFERROR(H53/D53,0) -> 0.018419777 | J53: =SUMIFS('Campaign - Dump'!$U:$U,'Campaign - Dump'!$J:$J,'Portfolio Wise '!$B53,'Campaign - Dump'!$A:$A,'Portfolio Wise '!$A53) -> 723105.38 | K53: =IFERROR(F53/J53,0) -> 0.085526898 | L53: =IFERROR(J53/F53,0) -> 11.692228 | M53: =IFERROR(J53/H53,0) -> 19029.089 | N53: 0 | O53: 0 | P53: =IFERROR(O53/N53,0) -> 0 | Q53: =SUMIFS('Business - Dump'!$W:$W,'Business - Dump'!$B:$B,'Portfolio Wise '!$B53,'Business - Dump'!$A:$A,'Portfolio Wise '!$A53) -> 0 | R53: =SUMIFS('Business - Dump'!$U:$U,'Business - Dump'!$B:$B,'Portfolio Wise '!$B53,'Business - Dump'!$A:$A,'Portfolio Wise '!$A53)/1.18 -> 0 | S53: =IFERROR(R53/Q53,0) -> 0 | T53: =IFERROR(F53/R53,0) -> 0 | U53: =IFERROR(R53/F53,0) -> 0 | V53: =SUMIFS('Business - Dump'!$G:$G,'Business - Dump'!$B:$B,'Portfolio Wise '!$B53,'Business - Dump'!$A:$A,'Portfolio Wise '!$A53) -> 0 | W53: =IFERROR(Q53/V53,0) -> 0 | X53: =IFERROR(N53/Q53,0) -> 0 | Y53: =IFERROR(O53/R53,0) -> 0 | Z53: =IFERROR(H53/Q53,0) -> 0 | AA53: =IFERROR(O53/R53,0) -> 0 | AB53: =IFERROR(AVERAGEIFS('Business - Dump'!$O:$O,'Business - Dump'!$B:$B,'Portfolio Wise '!$B53,'Business - Dump'!$A:$A,'Portfolio Wise '!$A53),0) -> 0 | AC53: =F53/SUMIFS('Campaign - Dump'!$Q:$Q,'Campaign - Dump'!$A:$A,'Portfolio Wise '!$A53) -> 0.22909666 | AD53: =IFERROR(N53/H53,0) -> 0
A54: Jan | B54: Standing Table - SM3 | C54: =SUMIFS('Campaign - Dump'!$N:$N,'Campaign - Dump'!$J:$J,'Portfolio Wise '!$B54,'Campaign - Dump'!$A:$A,'Portfolio Wise '!$A54) -> 846519 | D54: =SUMIFS('Campaign - Dump'!$O:$O,'Campaign - Dump'!$J:$J,'Portfolio Wise '!$B54,'Campaign - Dump'!$A:$A,'Portfolio Wise '!$A54) -> 4794 | E54: =IFERROR(D54/C54,0) -> 0.0056631924 | F54: =SUMIFS('Campaign - Dump'!$Q:$Q,'Campaign - Dump'!$J:$J,'Portfolio Wise '!$B54,'Campaign - Dump'!$A:$A,'Portfolio Wise '!$A54) -> 108220.77 | G54: =IFERROR(F54/D54,0) -> 22.574212 | H54: =SUMIFS('Campaign - Dump'!$T:$T,'Campaign - Dump'!$J:$J,'Portfolio Wise '!$B54,'Campaign - Dump'!$A:$A,'Portfolio Wise '!$A54) -> 30 | I54: =IFERROR(H54/D54,0) -> 0.0062578223 | J54: =SUMIFS('Campaign - Dump'!$U:$U,'Campaign - Dump'!$J:$J,'Portfolio Wise '!$B54,'Campaign - Dump'!$A:$A,'Portfolio Wise '!$A54) -> 608388.08 | K54: =IFERROR(F54/J54,0) -> 0.17788115 | L54: =IFERROR(J54/F54,0) -> 5.6217312 | M54: =IFERROR(J54/H54,0) -> 20279.603 | N54: =IFERROR(Q54-H54,0) -> 27 | O54: =IFERROR(R54-J54,0) -> 478094.97 | P54: =IFERROR(O54/N54,0) -> 17707.221 | Q54: =SUMIFS('Business - Dump'!$W:$W,'Business - Dump'!$B:$B,'Portfolio Wise '!$B54,'Business - Dump'!$A:$A,'Portfolio Wise '!$A54) -> 57 | R54: =SUMIFS('Business - Dump'!$U:$U,'Business - Dump'!$B:$B,'Portfolio Wise '!$B54,'Business - Dump'!$A:$A,'Portfolio Wise '!$A54)/1.18 -> 1086483.1 | S54: =IFERROR(R54/Q54,0) -> 19061.106 | T54: =IFERROR(F54/R54,0) -> 0.099606496 | U54: =IFERROR(R54/F54,0) -> 10.039506 | V54: =SUMIFS('Business - Dump'!$G:$G,'Business - Dump'!$B:$B,'Portfolio Wise '!$B54,'Business - Dump'!$A:$A,'Portfolio Wise '!$A54) -> 10214 | W54: =IFERROR(Q54/V54,0) -> 0.0055805757 | X54: =IFERROR(N54/Q54,0) -> 0.47368421 | Y54: =IFERROR(O54/R54,0) -> 0.44003905 | Z54: =IFERROR(H54/Q54,0) -> 0.52631579 | AA54: =IFERROR(O54/R54,0) -> 0.44003905 | AB54: =IFERROR(AVERAGEIFS('Business - Dump'!$O:$O,'Business - Dump'!$B:$B,'Portfolio Wise '!$B54,'Business - Dump'!$A:$A,'Portfolio Wise '!$A54),0) -> 0.8885 | AC54: =F54/SUMIFS('Campaign - Dump'!$Q:$Q,'Campaign - Dump'!$A:$A,'Portfolio Wise '!$A54) -> 0.40088986 | AD54: =IFERROR(N54/H54,0) -> 0.9
A55: Jan | B55: Standing Table - E2 | C55: =SUMIFS('Campaign - Dump'!$N:$N,'Campaign - Dump'!$J:$J,'Portfolio Wise '!$B55,'Campaign - Dump'!$A:$A,'Portfolio Wise '!$A55) -> 305268 | D55: =SUMIFS('Campaign - Dump'!$O:$O,'Campaign - Dump'!$J:$J,'Portfolio Wise '!$B55,'Campaign - Dump'!$A:$A,'Portfolio Wise '!$A55) -> 781 | E55: =IFERROR(D55/C55,0) -> 0.0025584077 | F55: =SUMIFS('Campaign - Dump'!$Q:$Q,'Campaign - Dump'!$J:$J,'Portfolio Wise '!$B55,'Campaign - Dump'!$A:$A,'Portfolio Wise '!$A55) -> 23776.97 | G55: =IFERROR(F55/D55,0) -> 30.444264 | H55: =SUMIFS('Campaign - Dump'!$T:$T,'Campaign - Dump'!$J:$J,'Portfolio Wise '!$B55,'Campaign - Dump'!$A:$A,'Portfolio Wise '!$A55) -> 1 | I55: =IFERROR(H55/D55,0) -> 0.0012804097 | J55: =SUMIFS('Campaign - Dump'!$U:$U,'Campaign - Dump'!$J:$J,'Portfolio Wise '!$B55,'Campaign - Dump'!$A:$A,'Portfolio Wise '!$A55) -> 28728.81 | K55: =IFERROR(F55/J55,0) -> 0.82763505 | L55: =IFERROR(J55/F55,0) -> 1.208262 | M55: =IFERROR(J55/H55,0) -> 28728.81 | N55: =IFERROR(Q55-H55,0) -> 17 | O55: =IFERROR(R55-J55,0) -> 457309.33 | P55: =IFERROR(O55/N55,0) -> 26900.549 | Q55: =SUMIFS('Business - Dump'!$W:$W,'Business - Dump'!$B:$B,'Portfolio Wise '!$B55,'Business - Dump'!$A:$A,'Portfolio Wise '!$A55) -> 18 | R55: =SUMIFS('Business - Dump'!$U:$U,'Business - Dump'!$B:$B,'Portfolio Wise '!$B55,'Business - Dump'!$A:$A,'Portfolio Wise '!$A55)/1.18 -> 486038.14 | S55: =IFERROR(R55/Q55,0) -> 27002.119 | T55: =IFERROR(F55/R55,0) -> 0.048919968 | U55: =IFERROR(R55/F55,0) -> 20.441551 | V55: =SUMIFS('Business - Dump'!$G:$G,'Business - Dump'!$B:$B,'Portfolio Wise '!$B55,'Business - Dump'!$A:$A,'Portfolio Wise '!$A55) -> 3246 | W55: =IFERROR(Q55/V55,0) -> 0.0055452865 | X55: =IFERROR(N55/Q55,0) -> 0.94444444 | Y55: =IFERROR(O55/R55,0) -> 0.94089186 | Z55: =IFERROR(H55/Q55,0) -> 0.055555556 | AA55: =IFERROR(O55/R55,0) -> 0.94089186 | AB55: =IFERROR(AVERAGEIFS('Business - Dump'!$O:$O,'Business - Dump'!$B:$B,'Portfolio Wise '!$B55,'Business - Dump'!$A:$A,'Portfolio Wise '!$A55),0) -> 0.91486667 | AC55: =F55/SUMIFS('Campaign - Dump'!$Q:$Q,'Campaign - Dump'!$A:$A,'Portfolio Wise '!$A55) -> 0.088078713 | AD55: =IFERROR(N55/H55,0) -> 17
A56: Jan | B56: Standing Table - M3 | C56: =SUMIFS('Campaign - Dump'!$N:$N,'Campaign - Dump'!$J:$J,'Portfolio Wise '!$B56,'Campaign - Dump'!$A:$A,'Portfolio Wise '!$A56) -> 550182 | D56: =SUMIFS('Campaign - Dump'!$O:$O,'Campaign - Dump'!$J:$J,'Portfolio Wise '!$B56,'Campaign - Dump'!$A:$A,'Portfolio Wise '!$A56) -> 1459 | E56: =IFERROR(D56/C56,0) -> 0.0026518498 | F56: =SUMIFS('Campaign - Dump'!$Q:$Q,'Campaign - Dump'!$J:$J,'Portfolio Wise '!$B56,'Campaign - Dump'!$A:$A,'Portfolio Wise '!$A56) -> 38921.76 | G56: =IFERROR(F56/D56,0) -> 26.677012 | H56: =SUMIFS('Campaign - Dump'!$T:$T,'Campaign - Dump'!$J:$J,'Portfolio Wise '!$B56,'Campaign - Dump'!$A:$A,'Portfolio Wise '!$A56) -> 7 | I56: =IFERROR(H56/D56,0) -> 0.0047978067 | J56: =SUMIFS('Campaign - Dump'!$U:$U,'Campaign - Dump'!$J:$J,'Portfolio Wise '!$B56,'Campaign - Dump'!$A:$A,'Portfolio Wise '!$A56) -> 102800.84 | K56: =IFERROR(F56/J56,0) -> 0.37861325 | L56: =IFERROR(J56/F56,0) -> 2.6412177 | M56: =IFERROR(J56/H56,0) -> 14685.834 | N56: =IFERROR(Q56-H56,0) -> 6 | O56: =IFERROR(R56-J56,0) -> 64283.906 | P56: =IFERROR(O56/N56,0) -> 10713.984 | Q56: =SUMIFS('Business - Dump'!$W:$W,'Business - Dump'!$B:$B,'Portfolio Wise '!$B56,'Business - Dump'!$A:$A,'Portfolio Wise '!$A56) -> 13 | R56: =SUMIFS('Business - Dump'!$U:$U,'Business - Dump'!$B:$B,'Portfolio Wise '!$B56,'Business - Dump'!$A:$A,'Portfolio Wise '!$A56)/1.18 -> 167084.75 | S56: =IFERROR(R56/Q56,0) -> 12852.673 | T56: =IFERROR(F56/R56,0) -> 0.23294622 | U56: =IFERROR(R56/F56,0) -> 4.2928363 | V56: =SUMIFS('Business - Dump'!$G:$G,'Business - Dump'!$B:$B,'Portfolio Wise '!$B56,'Business - Dump'!$A:$A,'Portfolio Wise '!$A56) -> 2685 | W56: =IFERROR(Q56/V56,0) -> 0.0048417132 | X56: =IFERROR(N56/Q56,0) -> 0.46153846 | Y56: =IFERROR(O56/R56,0) -> 0.38473833 | Z56: =IFERROR(H56/Q56,0) -> 0.53846154 | AA56: =IFERROR(O56/R56,0) -> 0.38473833 | AB56: =IFERROR(AVERAGEIFS('Business - Dump'!$O:$O,'Business - Dump'!$B:$B,'Portfolio Wise '!$B56,'Business - Dump'!$A:$A,'Portfolio Wise '!$A56),0) -> 0.9168 | AC56: =F56/SUMIFS('Campaign - Dump'!$Q:$Q,'Campaign - Dump'!$A:$A,'Portfolio Wise '!$A56) -> 0.14418063 | AD56: =IFERROR(N56/H56,0) -> 0.85714286
A57: Jan | B57: Monitor Arm Stand | C57: =SUMIFS('Campaign - Dump'!$N:$N,'Campaign - Dump'!$J:$J,'Portfolio Wise '!$B57,'Campaign - Dump'!$A:$A,'Portfolio Wise '!$A57) -> 115711 | D57: =SUMIFS('Campaign - Dump'!$O:$O,'Campaign - Dump'!$J:$J,'Portfolio Wise '!$B57,'Campaign - Dump'!$A:$A,'Portfolio Wise '!$A57) -> 532 | E57: =IFERROR(D57/C57,0) -> 0.0045976614 | F57: =SUMIFS('Campaign - Dump'!$Q:$Q,'Campaign - Dump'!$J:$J,'Portfolio Wise '!$B57,'Campaign - Dump'!$A:$A,'Portfolio Wise '!$A57) -> 5368.75 | G57: =IFERROR(F57/D57,0) -> 10.091635 | H57: =SUMIFS('Campaign - Dump'!$T:$T,'Campaign - Dump'!$J:$J,'Portfolio Wise '!$B57,'Campaign - Dump'!$A:$A,'Portfolio Wise '!$A57) -> 1 | I57: =IFERROR(H57/D57,0) -> 0.0018796992 | J57: =SUMIFS('Campaign - Dump'!$U:$U,'Campaign - Dump'!$J:$J,'Portfolio Wise '!$B57,'Campaign - Dump'!$A:$A,'Portfolio Wise '!$A57) -> 9237.29 | K57: =IFERROR(F57/J57,0) -> 0.58120401 | L57: =IFERROR(J57/F57,0) -> 1.7205662 | M57: =IFERROR(J57/H57,0) -> 9237.29 | N57: =IFERROR(Q57-H57,0) -> 0 | O57: =IFERROR(R57-J57,0) -> -0.0018644068 | P57: =IFERROR(O57/N57,0) -> 0 | Q57: =SUMIFS('Business - Dump'!$W:$W,'Business - Dump'!$B:$B,'Portfolio Wise '!$B57,'Business - Dump'!$A:$A,'Portfolio Wise '!$A57) -> 1 | R57: =SUMIFS('Business - Dump'!$U:$U,'Business - Dump'!$B:$B,'Portfolio Wise '!$B57,'Business - Dump'!$A:$A,'Portfolio Wise '!$A57)/1.18 -> 9237.2881 | S57: =IFERROR(R57/Q57,0) -> 9237.2881 | T57: =IFERROR(F57/R57,0) -> 0.58120413 | U57: =IFERROR(R57/F57,0) -> 1.7205659 | V57: =SUMIFS('Business - Dump'!$G:$G,'Business - Dump'!$B:$B,'Portfolio Wise '!$B57,'Business - Dump'!$A:$A,'Portfolio Wise '!$A57) -> 673 | W57: =IFERROR(Q57/V57,0) -> 0.0014858841 | X57: =IFERROR(N57/Q57,0) -> 0 | Y57: =IFERROR(O57/R57,0) -> -2.0183486e-07 | Z57: =IFERROR(H57/Q57,0) -> 1 | AA57: =IFERROR(O57/R57,0) -> -2.0183486e-07 | AB57: =IFERROR(AVERAGEIFS('Business - Dump'!$O:$O,'Business - Dump'!$B:$B,'Portfolio Wise '!$B57,'Business - Dump'!$A:$A,'Portfolio Wise '!$A57),0) -> 0.8025 | AC57: =F57/SUMIFS('Campaign - Dump'!$Q:$Q,'Campaign - Dump'!$A:$A,'Portfolio Wise '!$A57) -> 0.019887841 | AD57: =IFERROR(N57/H57,0) -> 0
A58: Jan | B58: Standing Desk Converter | C58: =SUMIFS('Campaign - Dump'!$N:$N,'Campaign - Dump'!$J:$J,'Portfolio Wise '!$B58,'Campaign - Dump'!$A:$A,'Portfolio Wise '!$A58) -> 84944 | D58: =SUMIFS('Campaign - Dump'!$O:$O,'Campaign - Dump'!$J:$J,'Portfolio Wise '!$B58,'Campaign - Dump'!$A:$A,'Portfolio Wise '!$A58) -> 227 | E58: =IFERROR(D58/C58,0) -> 0.0026723488 | F58: =SUMIFS('Campaign - Dump'!$Q:$Q,'Campaign - Dump'!$J:$J,'Portfolio Wise '!$B58,'Campaign - Dump'!$A:$A,'Portfolio Wise '!$A58) -> 1613.67 | G58: =IFERROR(F58/D58,0) -> 7.1086784 | H58: =SUMIFS('Campaign - Dump'!$T:$T,'Campaign - Dump'!$J:$J,'Portfolio Wise '!$B58,'Campaign - Dump'!$A:$A,'Portfolio Wise '!$A58) -> 1 | I58: =IFERROR(H58/D58,0) -> 0.0044052863 | J58: =SUMIFS('Campaign - Dump'!$U:$U,'Campaign - Dump'!$J:$J,'Portfolio Wise '!$B58,'Campaign - Dump'!$A:$A,'Portfolio Wise '!$A58) -> 669.5 | K58: =IFERROR(F58/J58,0) -> 2.4102614 | L58: =IFERROR(J58/F58,0) -> 0.41489276 | M58: =IFERROR(J58/H58,0) -> 669.5 | N58: =IFERROR(Q58-H58,0) -> -1 | O58: =IFERROR(R58-J58,0) -> -669.5 | P58: =IFERROR(O58/N58,0) -> 669.5 | Q58: =SUMIFS('Business - Dump'!$W:$W,'Business - Dump'!$B:$B,'Portfolio Wise '!$B58,'Business - Dump'!$A:$A,'Portfolio Wise '!$A58) -> 0 | R58: =SUMIFS('Business - Dump'!$U:$U,'Business - Dump'!$B:$B,'Portfolio Wise '!$B58,'Business - Dump'!$A:$A,'Portfolio Wise '!$A58)/1.18 -> 0 | S58: =IFERROR(R58/Q58,0) -> 0 | T58: =IFERROR(F58/R58,0) -> 0 | U58: =IFERROR(R58/F58,0) -> 0 | V58: =SUMIFS('Business - Dump'!$G:$G,'Business - Dump'!$B:$B,'Portfolio Wise '!$B58,'Business - Dump'!$A:$A,'Portfolio Wise '!$A58) -> 0 | W58: =IFERROR(Q58/V58,0) -> 0 | X58: =IFERROR(N58/Q58,0) -> 0 | Y58: =IFERROR(O58/R58,0) -> 0 | Z58: =IFERROR(H58/Q58,0) -> 0 | AA58: =IFERROR(O58/R58,0) -> 0 | AB58: =IFERROR(AVERAGEIFS('Business - Dump'!$O:$O,'Business - Dump'!$B:$B,'Portfolio Wise '!$B58,'Business - Dump'!$A:$A,'Portfolio Wise '!$A58),0) -> 0 | AC58: =F58/SUMIFS('Campaign - Dump'!$Q:$Q,'Campaign - Dump'!$A:$A,'Portfolio Wise '!$A58) -> 0.005977632 | AD58: =IFERROR(N58/H58,0) -> -1
A59: Jan | B59: Standing Table - All Frames | C59: =SUMIFS('Campaign - Dump'!$N:$N,'Campaign - Dump'!$J:$J,'Portfolio Wise '!$B59,'Campaign - Dump'!$A:$A,'Portfolio Wise '!$A59) -> 27798 | D59: =SUMIFS('Campaign - Dump'!$O:$O,'Campaign - Dump'!$J:$J,'Portfolio Wise '!$B59,'Campaign - Dump'!$A:$A,'Portfolio Wise '!$A59) -> 68 | E59: =IFERROR(D59/C59,0) -> 0.0024462192 | F59: =SUMIFS('Campaign - Dump'!$Q:$Q,'Campaign - Dump'!$J:$J,'Portfolio Wise '!$B59,'Campaign - Dump'!$A:$A,'Portfolio Wise '!$A59) -> 1746.28 | G59: =IFERROR(F59/D59,0) -> 25.680588 | H59: =SUMIFS('Campaign - Dump'!$T:$T,'Campaign - Dump'!$J:$J,'Portfolio Wise '!$B59,'Campaign - Dump'!$A:$A,'Portfolio Wise '!$A59) -> 0 | I59: =IFERROR(H59/D59,0) -> 0 | J59: =SUMIFS('Campaign - Dump'!$U:$U,'Campaign - Dump'!$J:$J,'Portfolio Wise '!$B59,'Campaign - Dump'!$A:$A,'Portfolio Wise '!$A59) -> 0 | K59: =IFERROR(F59/J59,0) -> 0 | L59: =IFERROR(J59/F59,0) -> 0 | M59: =IFERROR(J59/H59,0) -> 0 | N59: =IFERROR(Q59-H59,0) -> 21 | O59: =IFERROR(R59-J59,0) -> 402193.22 | P59: =IFERROR(O59/N59,0) -> 19152.058 | Q59: =SUMIFS('Business - Dump'!$W:$W,'Business - Dump'!$B:$B,'Portfolio Wise '!$B59,'Business - Dump'!$A:$A,'Portfolio Wise '!$A59) -> 21 | R59: =SUMIFS('Business - Dump'!$U:$U,'Business - Dump'!$B:$B,'Portfolio Wise '!$B59,'Business - Dump'!$A:$A,'Portfolio Wise '!$A59)/1.18 -> 402193.22 | S59: =IFERROR(R59/Q59,0) -> 19152.058 | T59: =IFERROR(F59/R59,0) -> 0.0043418932 | U59: =IFERROR(R59/F59,0) -> 230.31428 | V59: =SUMIFS('Business - Dump'!$G:$G,'Business - Dump'!$B:$B,'Portfolio Wise '!$B59,'Business - Dump'!$A:$A,'Portfolio Wise '!$A59) -> 3785 | W59: =IFERROR(Q59/V59,0) -> 0.0055482166 | X59: =IFERROR(N59/Q59,0) -> 1 | Y59: =IFERROR(O59/R59,0) -> 1 | Z59: =IFERROR(H59/Q59,0) -> 0 | AA59: =IFERROR(O59/R59,0) -> 1 | AB59: =IFERROR(AVERAGEIFS('Business - Dump'!$O:$O,'Business - Dump'!$B:$B,'Portfolio Wise '!$B59,'Business - Dump'!$A:$A,'Portfolio Wise '!$A59),0) -> 0.867 | AC59: =F59/SUMIFS('Campaign - Dump'!$Q:$Q,'Campaign - Dump'!$A:$A,'Portfolio Wise '!$A59) -> 0.0064688686 | AD59: =IFERROR(N59/H59,0) -> 0
A60: Jan | B60: Standing Table - E1A | C60: =SUMIFS('Campaign - Dump'!$N:$N,'Campaign - Dump'!$J:$J,'Portfolio Wise '!$B60,'Campaign - Dump'!$A:$A,'Portfolio Wise '!$A60) -> 776 | D60: =SUMIFS('Campaign - Dump'!$O:$O,'Campaign - Dump'!$J:$J,'Portfolio Wise '!$B60,'Campaign - Dump'!$A:$A,'Portfolio Wise '!$A60) -> 3 | E60: =IFERROR(D60/C60,0) -> 0.0038659794 | F60: =SUMIFS('Campaign - Dump'!$Q:$Q,'Campaign - Dump'!$J:$J,'Portfolio Wise '!$B60,'Campaign - Dump'!$A:$A,'Portfolio Wise '!$A60) -> 7.98 | G60: =IFERROR(F60/D60,0) -> 2.66 | H60: =SUMIFS('Campaign - Dump'!$T:$T,'Campaign - Dump'!$J:$J,'Portfolio Wise '!$B60,'Campaign - Dump'!$A:$A,'Portfolio Wise '!$A60) -> 0 | I60: =IFERROR(H60/D60,0) -> 0 | J60: =SUMIFS('Campaign - Dump'!$U:$U,'Campaign - Dump'!$J:$J,'Portfolio Wise '!$B60,'Campaign - Dump'!$A:$A,'Portfolio Wise '!$A60) -> 0 | K60: =IFERROR(F60/J60,0) -> 0 | L60: =IFERROR(J60/F60,0) -> 0 | M60: =IFERROR(J60/H60,0) -> 0 | N60: =IFERROR(Q60-H60,0) -> 1 | O60: =IFERROR(R60-J60,0) -> 24575.424 | P60: =IFERROR(O60/N60,0) -> 24575.424 | Q60: =SUMIFS('Business - Dump'!$W:$W,'Business - Dump'!$B:$B,'Portfolio Wise '!$B60,'Business - Dump'!$A:$A,'Portfolio Wise '!$A60) -> 1 | R60: =SUMIFS('Business - Dump'!$U:$U,'Business - Dump'!$B:$B,'Portfolio Wise '!$B60,'Business - Dump'!$A:$A,'Portfolio Wise '!$A60)/1.18 -> 24575.424 | S60: =IFERROR(R60/Q60,0) -> 24575.424 | T60: =IFERROR(F60/R60,0) -> 0.00032471465 | U60: =IFERROR(R60/F60,0) -> 3079.627 | V60: =SUMIFS('Business - Dump'!$G:$G,'Business - Dump'!$B:$B,'Portfolio Wise '!$B60,'Business - Dump'!$A:$A,'Portfolio Wise '!$A60) -> 57 | W60: =IFERROR(Q60/V60,0) -> 0.01754386 | X60: =IFERROR(N60/Q60,0) -> 1 | Y60: =IFERROR(O60/R60,0) -> 1 | Z60: =IFERROR(H60/Q60,0) -> 0 | AA60: =IFERROR(O60/R60,0) -> 1 | AB60: =IFERROR(AVERAGEIFS('Business - Dump'!$O:$O,'Business - Dump'!$B:$B,'Portfolio Wise '!$B60,'Business - Dump'!$A:$A,'Portfolio Wise '!$A60),0) -> 0.8871 | AC60: =F60/SUMIFS('Campaign - Dump'!$Q:$Q,'Campaign - Dump'!$A:$A,'Portfolio Wise '!$A60) -> 2.9560879e-05 | AD60: =IFERROR(N60/H60,0) -> 0
A61: Jan | B61: Standing Table - E1A | C61: =SUMIFS('Campaign - Dump'!$N:$N,'Campaign - Dump'!$J:$J,'Portfolio Wise '!$B61,'Campaign - Dump'!$A:$A,'Portfolio Wise '!$A61) -> 776 | D61: =SUMIFS('Campaign - Dump'!$O:$O,'Campaign - Dump'!$J:$J,'Portfolio Wise '!$B61,'Campaign - Dump'!$A:$A,'Portfolio Wise '!$A61) -> 3 | E61: =IFERROR(D61/C61,0) -> 0.0038659794 | F61: =SUMIFS('Campaign - Dump'!$Q:$Q,'Campaign - Dump'!$J:$J,'Portfolio Wise '!$B61,'Campaign - Dump'!$A:$A,'Portfolio Wise '!$A61) -> 7.98 | G61: =IFERROR(F61/D61,0) -> 2.66 | H61: =SUMIFS('Campaign - Dump'!$T:$T,'Campaign - Dump'!$J:$J,'Portfolio Wise '!$B61,'Campaign - Dump'!$A:$A,'Portfolio Wise '!$A61) -> 0 | I61: =IFERROR(H61/D61,0) -> 0 | J61: =SUMIFS('Campaign - Dump'!$U:$U,'Campaign - Dump'!$J:$J,'Portfolio Wise '!$B61,'Campaign - Dump'!$A:$A,'Portfolio Wise '!$A61) -> 0 | K61: =IFERROR(F61/J61,0) -> 0 | L61: =IFERROR(J61/F61,0) -> 0 | M61: =IFERROR(J61/H61,0) -> 0 | N61: =IFERROR(Q61-H61,0) -> 1 | O61: =IFERROR(R61-J61,0) -> 24575.424 | P61: =IFERROR(O61/N61,0) -> 24575.424 | Q61: =SUMIFS('Business - Dump'!$W:$W,'Business - Dump'!$B:$B,'Portfolio Wise '!$B61,'Business - Dump'!$A:$A,'Portfolio Wise '!$A61) -> 1 | R61: =SUMIFS('Business - Dump'!$U:$U,'Business - Dump'!$B:$B,'Portfolio Wise '!$B61,'Business - Dump'!$A:$A,'Portfolio Wise '!$A61)/1.18 -> 24575.424 | S61: =IFERROR(R61/Q61,0) -> 24575.424 | T61: =IFERROR(F61/R61,0) -> 0.00032471465 | U61: =IFERROR(R61/F61,0) -> 3079.627 | V61: =SUMIFS('Business - Dump'!$G:$G,'Business - Dump'!$B:$B,'Portfolio Wise '!$B61,'Business - Dump'!$A:$A,'Portfolio Wise '!$A61) -> 57 | W61: =IFERROR(Q61/V61,0) -> 0.01754386 | X61: =IFERROR(N61/Q61,0) -> 1 | Y61: =IFERROR(O61/R61,0) -> 1 | Z61: =IFERROR(H61/Q61,0) -> 0 | AA61: =IFERROR(O61/R61,0) -> 1 | AB61: =IFERROR(AVERAGEIFS('Business - Dump'!$O:$O,'Business - Dump'!$B:$B,'Portfolio Wise '!$B61,'Business - Dump'!$A:$A,'Portfolio Wise '!$A61),0) -> 0.8871 | AC61: =F61/SUMIFS('Campaign - Dump'!$Q:$Q,'Campaign - Dump'!$A:$A,'Portfolio Wise '!$A61) -> 2.9560879e-05 | AD61: =IFERROR(N61/H61,0) -> 0
A62: Jan | B62: Standing Table - SB | C62: =SUMIFS('Campaign - Dump'!$N:$N,'Campaign - Dump'!$J:$J,'Portfolio Wise '!$B62,'Campaign - Dump'!$A:$A,'Portfolio Wise '!$A62) -> 0 | D62: =SUMIFS('Campaign - Dump'!$O:$O,'Campaign - Dump'!$J:$J,'Portfolio Wise '!$B62,'Campaign - Dump'!$A:$A,'Portfolio Wise '!$A62) -> 0 | E62: =IFERROR(D62/C62,0) -> 0 | F62: =SUMIFS('Campaign - Dump'!$Q:$Q,'Campaign - Dump'!$J:$J,'Portfolio Wise '!$B62,'Campaign - Dump'!$A:$A,'Portfolio Wise '!$A62) -> 0 | G62: =IFERROR(F62/D62,0) -> 0 | H62: =SUMIFS('Campaign - Dump'!$T:$T,'Campaign - Dump'!$J:$J,'Portfolio Wise '!$B62,'Campaign - Dump'!$A:$A,'Portfolio Wise '!$A62) -> 0 | I62: =IFERROR(H62/D62,0) -> 0 | J62: =SUMIFS('Campaign - Dump'!$U:$U,'Campaign - Dump'!$J:$J,'Portfolio Wise '!$B62,'Campaign - Dump'!$A:$A,'Portfolio Wise '!$A62) -> 0 | K62: =IFERROR(F62/J62,0) -> 0 | L62: =IFERROR(J62/F62,0) -> 0 | M62: =IFERROR(J62/H62,0) -> 0 | N62: 0 | O62: 0 | P62: =IFERROR(O62/N62,0) -> 0 | Q62: =SUMIFS('Business - Dump'!$W:$W,'Business - Dump'!$B:$B,'Portfolio Wise '!$B62,'Business - Dump'!$A:$A,'Portfolio Wise '!$A62) -> 0 | R62: =SUMIFS('Business - Dump'!$U:$U,'Business - Dump'!$B:$B,'Portfolio Wise '!$B62,'Business - Dump'!$A:$A,'Portfolio Wise '!$A62)/1.18 -> 0 | S62: =IFERROR(R62/Q62,0) -> 0 | T62: =IFERROR(F62/R62,0) -> 0 | U62: =IFERROR(R62/F62,0) -> 0 | V62: =SUMIFS('Business - Dump'!$G:$G,'Business - Dump'!$B:$B,'Portfolio Wise '!$B62,'Business - Dump'!$A:$A,'Portfolio Wise '!$A62) -> 0 | W62: =IFERROR(Q62/V62,0) -> 0 | X62: =IFERROR(N62/Q62,0) -> 0 | Y62: =IFERROR(O62/R62,0) -> 0 | Z62: =IFERROR(H62/Q62,0) -> 0 | AA62: =IFERROR(O62/R62,0) -> 0 | AB62: =IFERROR(AVERAGEIFS('Business - Dump'!$O:$O,'Business - Dump'!$B:$B,'Portfolio Wise '!$B62,'Business - Dump'!$A:$A,'Portfolio Wise '!$A62),0) -> 0 | AC62: =F62/SUMIFS('Campaign - Dump'!$Q:$Q,'Campaign - Dump'!$A:$A,'Portfolio Wise '!$A62) -> 0 | AD62: =IFERROR(N62/H62,0) -> 0
A63: Jan | B63: Standing Table - E3 | C63: =SUMIFS('Campaign - Dump'!$N:$N,'Campaign - Dump'!$J:$J,'Portfolio Wise '!$B63,'Campaign - Dump'!$A:$A,'Portfolio Wise '!$A63) -> 0 | D63: =SUMIFS('Campaign - Dump'!$O:$O,'Campaign - Dump'!$J:$J,'Portfolio Wise '!$B63,'Campaign - Dump'!$A:$A,'Portfolio Wise '!$A63) -> 0 | E63: =IFERROR(D63/C63,0) -> 0 | F63: =SUMIFS('Campaign - Dump'!$Q:$Q,'Campaign - Dump'!$J:$J,'Portfolio Wise '!$B63,'Campaign - Dump'!$A:$A,'Portfolio Wise '!$A63) -> 0 | G63: =IFERROR(F63/D63,0) -> 0 | H63: =SUMIFS('Campaign - Dump'!$T:$T,'Campaign - Dump'!$J:$J,'Portfolio Wise '!$B63,'Campaign - Dump'!$A:$A,'Portfolio Wise '!$A63) -> 0 | I63: =IFERROR(H63/D63,0) -> 0 | J63: =SUMIFS('Campaign - Dump'!$U:$U,'Campaign - Dump'!$J:$J,'Portfolio Wise '!$B63,'Campaign - Dump'!$A:$A,'Portfolio Wise '!$A63) -> 0 | K63: =IFERROR(F63/J63,0) -> 0 | L63: =IFERROR(J63/F63,0) -> 0 | M63: =IFERROR(J63/H63,0) -> 0 | N63: =IFERROR(Q63-H63,0) -> 0 | O63: =IFERROR(R63-J63,0) -> 0 | P63: =IFERROR(O63/N63,0) -> 0 | Q63: =SUMIFS('Business - Dump'!$W:$W,'Business - Dump'!$B:$B,'Portfolio Wise '!$B63,'Business - Dump'!$A:$A,'Portfolio Wise '!$A63) -> 0 | R63: =SUMIFS('Business - Dump'!$U:$U,'Business - Dump'!$B:$B,'Portfolio Wise '!$B63,'Business - Dump'!$A:$A,'Portfolio Wise '!$A63)/1.18 -> 0 | S63: =IFERROR(R63/Q63,0) -> 0 | T63: =IFERROR(F63/R63,0) -> 0 | U63: =IFERROR(R63/F63,0) -> 0 | V63: =SUMIFS('Business - Dump'!$G:$G,'Business - Dump'!$B:$B,'Portfolio Wise '!$B63,'Business - Dump'!$A:$A,'Portfolio Wise '!$A63) -> 0 | W63: =IFERROR(Q63/V63,0) -> 0 | X63: =IFERROR(N63/Q63,0) -> 0 | Y63: =IFERROR(O63/R63,0) -> 0 | Z63: =IFERROR(H63/Q63,0) -> 0 | AA63: =IFERROR(O63/R63,0) -> 0 | AB63: =IFERROR(AVERAGEIFS('Business - Dump'!$O:$O,'Business - Dump'!$B:$B,'Portfolio Wise '!$B63,'Business - Dump'!$A:$A,'Portfolio Wise '!$A63),0) -> 0 | AC63: =F63/SUMIFS('Campaign - Dump'!$Q:$Q,'Campaign - Dump'!$A:$A,'Portfolio Wise '!$A63) -> 0 | AD63: =IFERROR(N63/H63,0) -> 0
A64: Jan | B64: Desk Cable Tray | C64: =SUMIFS('Campaign - Dump'!$N:$N,'Campaign - Dump'!$J:$J,'Portfolio Wise '!$B64,'Campaign - Dump'!$A:$A,'Portfolio Wise '!$A64) -> 0 | D64: =SUMIFS('Campaign - Dump'!$O:$O,'Campaign - Dump'!$J:$J,'Portfolio Wise '!$B64,'Campaign - Dump'!$A:$A,'Portfolio Wise '!$A64) -> 0 | E64: =IFERROR(D64/C64,0) -> 0 | F64: =SUMIFS('Campaign - Dump'!$Q:$Q,'Campaign - Dump'!$J:$J,'Portfolio Wise '!$B64,'Campaign - Dump'!$A:$A,'Portfolio Wise '!$A64) -> 0 | G64: =IFERROR(F64/D64,0) -> 0 | H64: =SUMIFS('Campaign - Dump'!$T:$T,'Campaign - Dump'!$J:$J,'Portfolio Wise '!$B64,'Campaign - Dump'!$A:$A,'Portfolio Wise '!$A64) -> 0 | I64: =IFERROR(H64/D64,0) -> 0 | J64: =SUMIFS('Campaign - Dump'!$U:$U,'Campaign - Dump'!$J:$J,'Portfolio Wise '!$B64,'Campaign - Dump'!$A:$A,'Portfolio Wise '!$A64) -> 0 | K64: =IFERROR(F64/J64,0) -> 0 | L64: =IFERROR(J64/F64,0) -> 0 | M64: =IFERROR(J64/H64,0) -> 0 | N64: =IFERROR(Q64-H64,0) -> 17 | O64: =IFERROR(R64-J64,0) -> 22388.39 | P64: =IFERROR(O64/N64,0) -> 1316.9641 | Q64: =SUMIFS('Business - Dump'!$W:$W,'Business - Dump'!$B:$B,'Portfolio Wise '!$B64,'Business - Dump'!$A:$A,'Portfolio Wise '!$A64) -> 17 | R64: =SUMIFS('Business - Dump'!$U:$U,'Business - Dump'!$B:$B,'Portfolio Wise '!$B64,'Business - Dump'!$A:$A,'Portfolio Wise '!$A64)/1.18 -> 22388.39 | S64: =IFERROR(R64/Q64,0) -> 1316.9641 | T64: =IFERROR(F64/R64,0) -> 0 | U64: =IFERROR(R64/F64,0) -> 0 | V64: =SUMIFS('Business - Dump'!$G:$G,'Business - Dump'!$B:$B,'Portfolio Wise '!$B64,'Business - Dump'!$A:$A,'Portfolio Wise '!$A64) -> 299 | W64: =IFERROR(Q64/V64,0) -> 0.056856187 | X64: =IFERROR(N64/Q64,0) -> 1 | Y64: =IFERROR(O64/R64,0) -> 1 | Z64: =IFERROR(H64/Q64,0) -> 0 | AA64: =IFERROR(O64/R64,0) -> 1 | AB64: =IFERROR(AVERAGEIFS('Business - Dump'!$O:$O,'Business - Dump'!$B:$B,'Portfolio Wise '!$B64,'Business - Dump'!$A:$A,'Portfolio Wise '!$A64),0) -> 0.9068 | AC64: =F64/SUMIFS('Campaign - Dump'!$Q:$Q,'Campaign - Dump'!$A:$A,'Portfolio Wise '!$A64) -> 0 | AD64: =IFERROR(N64/H64,0) -> 0
A65: Jan | B65: Extension & Holder | C65: =SUMIFS('Campaign - Dump'!$N:$N,'Campaign - Dump'!$J:$J,'Portfolio Wise '!$B65,'Campaign - Dump'!$A:$A,'Portfolio Wise '!$A65) -> 0 | D65: =SUMIFS('Campaign - Dump'!$O:$O,'Campaign - Dump'!$J:$J,'Portfolio Wise '!$B65,'Campaign - Dump'!$A:$A,'Portfolio Wise '!$A65) -> 0 | E65: =IFERROR(D65/C65,0) -> 0 | F65: =SUMIFS('Campaign - Dump'!$Q:$Q,'Campaign - Dump'!$J:$J,'Portfolio Wise '!$B65,'Campaign - Dump'!$A:$A,'Portfolio Wise '!$A65) -> 0 | G65: =IFERROR(F65/D65,0) -> 0 | H65: =SUMIFS('Campaign - Dump'!$T:$T,'Campaign - Dump'!$J:$J,'Portfolio Wise '!$B65,'Campaign - Dump'!$A:$A,'Portfolio Wise '!$A65) -> 0 | I65: =IFERROR(H65/D65,0) -> 0 | J65: =SUMIFS('Campaign - Dump'!$U:$U,'Campaign - Dump'!$J:$J,'Portfolio Wise '!$B65,'Campaign - Dump'!$A:$A,'Portfolio Wise '!$A65) -> 0 | K65: =IFERROR(F65/J65,0) -> 0 | L65: =IFERROR(J65/F65,0) -> 0 | M65: =IFERROR(J65/H65,0) -> 0 | N65: =IFERROR(Q65-H65,0) -> 7 | O65: =IFERROR(R65-J65,0) -> 12638.136 | P65: =IFERROR(O65/N65,0) -> 1805.4479 | Q65: =SUMIFS('Business - Dump'!$W:$W,'Business - Dump'!$B:$B,'Portfolio Wise '!$B65,'Business - Dump'!$A:$A,'Portfolio Wise '!$A65) -> 7 | R65: =SUMIFS('Business - Dump'!$U:$U,'Business - Dump'!$B:$B,'Portfolio Wise '!$B65,'Business - Dump'!$A:$A,'Portfolio Wise '!$A65)/1.18 -> 12638.136 | S65: =IFERROR(R65/Q65,0) -> 1805.4479 | T65: =IFERROR(F65/R65,0) -> 0 | U65: =IFERROR(R65/F65,0) -> 0 | V65: =SUMIFS('Business - Dump'!$G:$G,'Business - Dump'!$B:$B,'Portfolio Wise '!$B65,'Business - Dump'!$A:$A,'Portfolio Wise '!$A65) -> 637 | W65: =IFERROR(Q65/V65,0) -> 0.010989011 | X65: =IFERROR(N65/Q65,0) -> 1 | Y65: =IFERROR(O65/R65,0) -> 1 | Z65: =IFERROR(H65/Q65,0) -> 0 | AA65: =IFERROR(O65/R65,0) -> 1 | AB65: =IFERROR(AVERAGEIFS('Business - Dump'!$O:$O,'Business - Dump'!$B:$B,'Portfolio Wise '!$B65,'Business - Dump'!$A:$A,'Portfolio Wise '!$A65),0) -> 0.879925 | AC65: =F65/SUMIFS('Campaign - Dump'!$Q:$Q,'Campaign - Dump'!$A:$A,'Portfolio Wise '!$A65) -> 0 | AD65: =IFERROR(N65/H65,0) -> 0
A66: Jan | B66: Standing Table - E4 | C66: =SUMIFS('Campaign - Dump'!$N:$N,'Campaign - Dump'!$J:$J,'Portfolio Wise '!$B66,'Campaign - Dump'!$A:$A,'Portfolio Wise '!$A66) -> 0 | D66: =SUMIFS('Campaign - Dump'!$O:$O,'Campaign - Dump'!$J:$J,'Portfolio Wise '!$B66,'Campaign - Dump'!$A:$A,'Portfolio Wise '!$A66) -> 0 | E66: =IFERROR(D66/C66,0) -> 0 | F66: =SUMIFS('Campaign - Dump'!$Q:$Q,'Campaign - Dump'!$J:$J,'Portfolio Wise '!$B66,'Campaign - Dump'!$A:$A,'Portfolio Wise '!$A66) -> 0 | G66: =IFERROR(F66/D66,0) -> 0 | H66: =SUMIFS('Campaign - Dump'!$T:$T,'Campaign - Dump'!$J:$J,'Portfolio Wise '!$B66,'Campaign - Dump'!$A:$A,'Portfolio Wise '!$A66) -> 0 | I66: =IFERROR(H66/D66,0) -> 0 | J66: =SUMIFS('Campaign - Dump'!$U:$U,'Campaign - Dump'!$J:$J,'Portfolio Wise '!$B66,'Campaign - Dump'!$A:$A,'Portfolio Wise '!$A66) -> 0 | K66: =IFERROR(F66/J66,0) -> 0 | L66: =IFERROR(J66/F66,0) -> 0 | M66: =IFERROR(J66/H66,0) -> 0 | N66: =IFERROR(Q66-H66,0) -> 0 | O66: =IFERROR(R66-J66,0) -> 0 | P66: =IFERROR(O66/N66,0) -> 0 | Q66: =SUMIFS('Business - Dump'!$W:$W,'Business - Dump'!$B:$B,'Portfolio Wise '!$B66,'Business - Dump'!$A:$A,'Portfolio Wise '!$A66) -> 0 | R66: =SUMIFS('Business - Dump'!$U:$U,'Business - Dump'!$B:$B,'Portfolio Wise '!$B66,'Business - Dump'!$A:$A,'Portfolio Wise '!$A66)/1.18 -> 0 | S66: =IFERROR(R66/Q66,0) -> 0 | T66: =IFERROR(F66/R66,0) -> 0 | U66: =IFERROR(R66/F66,0) -> 0 | V66: =SUMIFS('Business - Dump'!$G:$G,'Business - Dump'!$B:$B,'Portfolio Wise '!$B66,'Business - Dump'!$A:$A,'Portfolio Wise '!$A66) -> 0 | W66: =IFERROR(Q66/V66,0) -> 0 | X66: =IFERROR(N66/Q66,0) -> 0 | Y66: =IFERROR(O66/R66,0) -> 0 | Z66: =IFERROR(H66/Q66,0) -> 0 | AA66: =IFERROR(O66/R66,0) -> 0 | AB66: =IFERROR(AVERAGEIFS('Business - Dump'!$O:$O,'Business - Dump'!$B:$B,'Portfolio Wise '!$B66,'Business - Dump'!$A:$A,'Portfolio Wise '!$A66),0) -> 0 | AC66: =F66/SUMIFS('Campaign - Dump'!$Q:$Q,'Campaign - Dump'!$A:$A,'Portfolio Wise '!$A66) -> 0 | AD66: =IFERROR(N66/H66,0) -> 0
A67: Jan | B67: Standing Table - E4 | C67: =SUMIFS('Campaign - Dump'!$N:$N,'Campaign - Dump'!$J:$J,'Portfolio Wise '!$B67,'Campaign - Dump'!$A:$A,'Portfolio Wise '!$A67) -> 0 | D67: =SUMIFS('Campaign - Dump'!$O:$O,'Campaign - Dump'!$J:$J,'Portfolio Wise '!$B67,'Campaign - Dump'!$A:$A,'Portfolio Wise '!$A67) -> 0 | E67: =IFERROR(D67/C67,0) -> 0 | F67: =SUMIFS('Campaign - Dump'!$Q:$Q,'Campaign - Dump'!$J:$J,'Portfolio Wise '!$B67,'Campaign - Dump'!$A:$A,'Portfolio Wise '!$A67) -> 0 | G67: =IFERROR(F67/D67,0) -> 0 | H67: =SUMIFS('Campaign - Dump'!$T:$T,'Campaign - Dump'!$J:$J,'Portfolio Wise '!$B67,'Campaign - Dump'!$A:$A,'Portfolio Wise '!$A67) -> 0 | I67: =IFERROR(H67/D67,0) -> 0 | J67: =SUMIFS('Campaign - Dump'!$U:$U,'Campaign - Dump'!$J:$J,'Portfolio Wise '!$B67,'Campaign - Dump'!$A:$A,'Portfolio Wise '!$A67) -> 0 | K67: =IFERROR(F67/J67,0) -> 0 | L67: =IFERROR(J67/F67,0) -> 0 | M67: =IFERROR(J67/H67,0) -> 0 | N67: =IFERROR(Q67-H67,0) -> 0 | O67: =IFERROR(R67-J67,0) -> 0 | P67: =IFERROR(O67/N67,0) -> 0 | Q67: =SUMIFS('Business - Dump'!$W:$W,'Business - Dump'!$B:$B,'Portfolio Wise '!$B67,'Business - Dump'!$A:$A,'Portfolio Wise '!$A67) -> 0 | R67: =SUMIFS('Business - Dump'!$U:$U,'Business - Dump'!$B:$B,'Portfolio Wise '!$B67,'Business - Dump'!$A:$A,'Portfolio Wise '!$A67)/1.18 -> 0 | S67: =IFERROR(R67/Q67,0) -> 0 | T67: =IFERROR(F67/R67,0) -> 0 | U67: =IFERROR(R67/F67,0) -> 0 | V67: =SUMIFS('Business - Dump'!$G:$G,'Business - Dump'!$B:$B,'Portfolio Wise '!$B67,'Business - Dump'!$A:$A,'Portfolio Wise '!$A67) -> 0 | W67: =IFERROR(Q67/V67,0) -> 0 | X67: =IFERROR(N67/Q67,0) -> 0 | Y67: =IFERROR(O67/R67,0) -> 0 | Z67: =IFERROR(H67/Q67,0) -> 0 | AA67: =IFERROR(O67/R67,0) -> 0 | AB67: =IFERROR(AVERAGEIFS('Business - Dump'!$O:$O,'Business - Dump'!$B:$B,'Portfolio Wise '!$B67,'Business - Dump'!$A:$A,'Portfolio Wise '!$A67),0) -> 0 | AC67: =F67/SUMIFS('Campaign - Dump'!$Q:$Q,'Campaign - Dump'!$A:$A,'Portfolio Wise '!$A67) -> 0 | AD67: =IFERROR(N67/H67,0) -> 0
A68: Jan | B68: Standing Table - M8 | C68: =SUMIFS('Campaign - Dump'!$N:$N,'Campaign - Dump'!$J:$J,'Portfolio Wise '!$B68,'Campaign - Dump'!$A:$A,'Portfolio Wise '!$A68) -> 0 | D68: =SUMIFS('Campaign - Dump'!$O:$O,'Campaign - Dump'!$J:$J,'Portfolio Wise '!$B68,'Campaign - Dump'!$A:$A,'Portfolio Wise '!$A68) -> 0 | E68: =IFERROR(D68/C68,0) -> 0 | F68: =SUMIFS('Campaign - Dump'!$Q:$Q,'Campaign - Dump'!$J:$J,'Portfolio Wise '!$B68,'Campaign - Dump'!$A:$A,'Portfolio Wise '!$A68) -> 0 | G68: =IFERROR(F68/D68,0) -> 0 | H68: =SUMIFS('Campaign - Dump'!$T:$T,'Campaign - Dump'!$J:$J,'Portfolio Wise '!$B68,'Campaign - Dump'!$A:$A,'Portfolio Wise '!$A68) -> 0 | I68: =IFERROR(H68/D68,0) -> 0 | J68: =SUMIFS('Campaign - Dump'!$U:$U,'Campaign - Dump'!$J:$J,'Portfolio Wise '!$B68,'Campaign - Dump'!$A:$A,'Portfolio Wise '!$A68) -> 0 | K68: =IFERROR(F68/J68,0) -> 0 | L68: =IFERROR(J68/F68,0) -> 0 | M68: =IFERROR(J68/H68,0) -> 0 | N68: =IFERROR(Q68-H68,0) -> 13 | O68: =IFERROR(R68-J68,0) -> 199143.22 | P68: =IFERROR(O68/N68,0) -> 15318.709 | Q68: =SUMIFS('Business - Dump'!$W:$W,'Business - Dump'!$B:$B,'Portfolio Wise '!$B68,'Business - Dump'!$A:$A,'Portfolio Wise '!$A68) -> 13 | R68: =SUMIFS('Business - Dump'!$U:$U,'Business - Dump'!$B:$B,'Portfolio Wise '!$B68,'Business - Dump'!$A:$A,'Portfolio Wise '!$A68)/1.18 -> 199143.22 | S68: =IFERROR(R68/Q68,0) -> 15318.709 | T68: =IFERROR(F68/R68,0) -> 0 | U68: =IFERROR(R68/F68,0) -> 0 | V68: =SUMIFS('Business - Dump'!$G:$G,'Business - Dump'!$B:$B,'Portfolio Wise '!$B68,'Business - Dump'!$A:$A,'Portfolio Wise '!$A68) -> 2368 | W68: =IFERROR(Q68/V68,0) -> 0.0054898649 | X68: =IFERROR(N68/Q68,0) -> 1 | Y68: =IFERROR(O68/R68,0) -> 1 | Z68: =IFERROR(H68/Q68,0) -> 0 | AA68: =IFERROR(O68/R68,0) -> 1 | AB68: =IFERROR(AVERAGEIFS('Business - Dump'!$O:$O,'Business - Dump'!$B:$B,'Portfolio Wise '!$B68,'Business - Dump'!$A:$A,'Portfolio Wise '!$A68),0) -> 0.89838 | AC68: =F68/SUMIFS('Campaign - Dump'!$Q:$Q,'Campaign - Dump'!$A:$A,'Portfolio Wise '!$A68) -> 0 | AD68: =IFERROR(N68/H68,0) -> 0
A69: Jan | B69: Video Funnel | C69: =SUMIFS('Campaign - Dump'!$N:$N,'Campaign - Dump'!$J:$J,'Portfolio Wise '!$B69,'Campaign - Dump'!$A:$A,'Portfolio Wise '!$A69) -> 0 | D69: =SUMIFS('Campaign - Dump'!$O:$O,'Campaign - Dump'!$J:$J,'Portfolio Wise '!$B69,'Campaign - Dump'!$A:$A,'Portfolio Wise '!$A69) -> 0 | E69: =IFERROR(D69/C69,0) -> 0 | F69: =SUMIFS('Campaign - Dump'!$Q:$Q,'Campaign - Dump'!$J:$J,'Portfolio Wise '!$B69,'Campaign - Dump'!$A:$A,'Portfolio Wise '!$A69) -> 0 | G69: =IFERROR(F69/D69,0) -> 0 | H69: =SUMIFS('Campaign - Dump'!$T:$T,'Campaign - Dump'!$J:$J,'Portfolio Wise '!$B69,'Campaign - Dump'!$A:$A,'Portfolio Wise '!$A69) -> 0 | I69: =IFERROR(H69/D69,0) -> 0 | J69: =SUMIFS('Campaign - Dump'!$U:$U,'Campaign - Dump'!$J:$J,'Portfolio Wise '!$B69,'Campaign - Dump'!$A:$A,'Portfolio Wise '!$A69) -> 0 | K69: =IFERROR(F69/J69,0) -> 0 | L69: =IFERROR(J69/F69,0) -> 0 | M69: =IFERROR(J69/H69,0) -> 0 | N69: =IFERROR(Q69-H69,0) -> 0 | O69: =IFERROR(R69-J69,0) -> 0 | P69: =IFERROR(O69/N69,0) -> 0 | Q69: =SUMIFS('Business - Dump'!$W:$W,'Business - Dump'!$B:$B,'Portfolio Wise '!$B69,'Business - Dump'!$A:$A,'Portfolio Wise '!$A69) -> 0 | R69: =SUMIFS('Business - Dump'!$U:$U,'Business - Dump'!$B:$B,'Portfolio Wise '!$B69,'Business - Dump'!$A:$A,'Portfolio Wise '!$A69)/1.18 -> 0 | S69: =IFERROR(R69/Q69,0) -> 0 | T69: =IFERROR(F69/R69,0) -> 0 | U69: =IFERROR(R69/F69,0) -> 0 | V69: =SUMIFS('Business - Dump'!$G:$G,'Business - Dump'!$B:$B,'Portfolio Wise '!$B69,'Business - Dump'!$A:$A,'Portfolio Wise '!$A69) -> 0 | W69: =IFERROR(Q69/V69,0) -> 0 | X69: =IFERROR(N69/Q69,0) -> 0 | Y69: =IFERROR(O69/R69,0) -> 0 | Z69: =IFERROR(H69/Q69,0) -> 0 | AA69: =IFERROR(O69/R69,0) -> 0 | AB69: =IFERROR(AVERAGEIFS('Business - Dump'!$O:$O,'Business - Dump'!$B:$B,'Portfolio Wise '!$B69,'Business - Dump'!$A:$A,'Portfolio Wise '!$A69),0) -> 0 | AC69: =F69/SUMIFS('Campaign - Dump'!$Q:$Q,'Campaign - Dump'!$A:$A,'Portfolio Wise '!$A69) -> 0 | AD69: =IFERROR(N69/H69,0) -> 0
A70: Jan | B70: Keyboard Tray | C70: =SUMIFS('Campaign - Dump'!$N:$N,'Campaign - Dump'!$J:$J,'Portfolio Wise '!$B70,'Campaign - Dump'!$A:$A,'Portfolio Wise '!$A70) -> 0 | D70: =SUMIFS('Campaign - Dump'!$O:$O,'Campaign - Dump'!$J:$J,'Portfolio Wise '!$B70,'Campaign - Dump'!$A:$A,'Portfolio Wise '!$A70) -> 0 | E70: =IFERROR(D70/C70,0) -> 0 | F70: =SUMIFS('Campaign - Dump'!$Q:$Q,'Campaign - Dump'!$J:$J,'Portfolio Wise '!$B70,'Campaign - Dump'!$A:$A,'Portfolio Wise '!$A70) -> 0 | G70: =IFERROR(F70/D70,0) -> 0 | H70: =SUMIFS('Campaign - Dump'!$T:$T,'Campaign - Dump'!$J:$J,'Portfolio Wise '!$B70,'Campaign - Dump'!$A:$A,'Portfolio Wise '!$A70) -> 0 | I70: =IFERROR(H70/D70,0) -> 0 | J70: =SUMIFS('Campaign - Dump'!$U:$U,'Campaign - Dump'!$J:$J,'Portfolio Wise '!$B70,'Campaign - Dump'!$A:$A,'Portfolio Wise '!$A70) -> 0 | K70: =IFERROR(F70/J70,0) -> 0 | L70: =IFERROR(J70/F70,0) -> 0 | M70: =IFERROR(J70/H70,0) -> 0 | N70: =IFERROR(Q70-H70,0) -> 0 | O70: =IFERROR(R70-J70,0) -> 0 | P70: =IFERROR(O70/N70,0) -> 0 | Q70: =SUMIFS('Business - Dump'!$W:$W,'Business - Dump'!$B:$B,'Portfolio Wise '!$B70,'Business - Dump'!$A:$A,'Portfolio Wise '!$A70) -> 0 | R70: =SUMIFS('Business - Dump'!$U:$U,'Business - Dump'!$B:$B,'Portfolio Wise '!$B70,'Business - Dump'!$A:$A,'Portfolio Wise '!$A70)/1.18 -> 0 | S70: =IFERROR(R70/Q70,0) -> 0 | T70: =IFERROR(F70/R70,0) -> 0 | U70: =IFERROR(R70/F70,0) -> 0 | V70: =SUMIFS('Business - Dump'!$G:$G,'Business - Dump'!$B:$B,'Portfolio Wise '!$B70,'Business - Dump'!$A:$A,'Portfolio Wise '!$A70) -> 0 | W70: =IFERROR(Q70/V70,0) -> 0 | X70: =IFERROR(N70/Q70,0) -> 0 | Y70: =IFERROR(O70/R70,0) -> 0 | Z70: =IFERROR(H70/Q70,0) -> 0 | AA70: =IFERROR(O70/R70,0) -> 0 | AB70: =IFERROR(AVERAGEIFS('Business - Dump'!$O:$O,'Business - Dump'!$B:$B,'Portfolio Wise '!$B70,'Business - Dump'!$A:$A,'Portfolio Wise '!$A70),0) -> 0 | AC70: =F70/SUMIFS('Campaign - Dump'!$Q:$Q,'Campaign - Dump'!$A:$A,'Portfolio Wise '!$A70) -> 0 | AD70: =IFERROR(N70/H70,0) -> 0
A71: Jan | B71: Footrests | C71: =SUMIFS('Campaign - Dump'!$N:$N,'Campaign - Dump'!$J:$J,'Portfolio Wise '!$B71,'Campaign - Dump'!$A:$A,'Portfolio Wise '!$A71) -> 0 | D71: =SUMIFS('Campaign - Dump'!$O:$O,'Campaign - Dump'!$J:$J,'Portfolio Wise '!$B71,'Campaign - Dump'!$A:$A,'Portfolio Wise '!$A71) -> 0 | E71: =IFERROR(D71/C71,0) -> 0 | F71: =SUMIFS('Campaign - Dump'!$Q:$Q,'Campaign - Dump'!$J:$J,'Portfolio Wise '!$B71,'Campaign - Dump'!$A:$A,'Portfolio Wise '!$A71) -> 0 | G71: =IFERROR(F71/D71,0) -> 0 | H71: =SUMIFS('Campaign - Dump'!$T:$T,'Campaign - Dump'!$J:$J,'Portfolio Wise '!$B71,'Campaign - Dump'!$A:$A,'Portfolio Wise '!$A71) -> 0 | I71: =IFERROR(H71/D71,0) -> 0 | J71: =SUMIFS('Campaign - Dump'!$U:$U,'Campaign - Dump'!$J:$J,'Portfolio Wise '!$B71,'Campaign - Dump'!$A:$A,'Portfolio Wise '!$A71) -> 0 | K71: =IFERROR(F71/J71,0) -> 0 | L71: =IFERROR(J71/F71,0) -> 0 | M71: =IFERROR(J71/H71,0) -> 0 | N71: =IFERROR(Q71-H71,0) -> 0 | O71: =IFERROR(R71-J71,0) -> 0 | P71: =IFERROR(O71/N71,0) -> 0 | Q71: =SUMIFS('Business - Dump'!$W:$W,'Business - Dump'!$B:$B,'Portfolio Wise '!$B71,'Business - Dump'!$A:$A,'Portfolio Wise '!$A71) -> 0 | R71: =SUMIFS('Business - Dump'!$U:$U,'Business - Dump'!$B:$B,'Portfolio Wise '!$B71,'Business - Dump'!$A:$A,'Portfolio Wise '!$A71)/1.18 -> 0 | S71: =IFERROR(R71/Q71,0) -> 0 | T71: =IFERROR(F71/R71,0) -> 0 | U71: =IFERROR(R71/F71,0) -> 0 | V71: =SUMIFS('Business - Dump'!$G:$G,'Business - Dump'!$B:$B,'Portfolio Wise '!$B71,'Business - Dump'!$A:$A,'Portfolio Wise '!$A71) -> 0 | W71: =IFERROR(Q71/V71,0) -> 0 | X71: =IFERROR(N71/Q71,0) -> 0 | Y71: =IFERROR(O71/R71,0) -> 0 | Z71: =IFERROR(H71/Q71,0) -> 0 | AA71: =IFERROR(O71/R71,0) -> 0 | AB71: =IFERROR(AVERAGEIFS('Business - Dump'!$O:$O,'Business - Dump'!$B:$B,'Portfolio Wise '!$B71,'Business - Dump'!$A:$A,'Portfolio Wise '!$A71),0) -> 0 | AC71: =F71/SUMIFS('Campaign - Dump'!$Q:$Q,'Campaign - Dump'!$A:$A,'Portfolio Wise '!$A71) -> 0 | AD71: =IFERROR(N71/H71,0) -> 0
A72: Jan | B72: Single Leg Gas | C72: =SUMIFS('Campaign - Dump'!$N:$N,'Campaign - Dump'!$J:$J,'Portfolio Wise '!$B72,'Campaign - Dump'!$A:$A,'Portfolio Wise '!$A72) -> 0 | D72: =SUMIFS('Campaign - Dump'!$O:$O,'Campaign - Dump'!$J:$J,'Portfolio Wise '!$B72,'Campaign - Dump'!$A:$A,'Portfolio Wise '!$A72) -> 0 | E72: =IFERROR(D72/C72,0) -> 0 | F72: =SUMIFS('Campaign - Dump'!$Q:$Q,'Campaign - Dump'!$J:$J,'Portfolio Wise '!$B72,'Campaign - Dump'!$A:$A,'Portfolio Wise '!$A72) -> 0 | G72: =IFERROR(F72/D72,0) -> 0 | H72: =SUMIFS('Campaign - Dump'!$T:$T,'Campaign - Dump'!$J:$J,'Portfolio Wise '!$B72,'Campaign - Dump'!$A:$A,'Portfolio Wise '!$A72) -> 0 | I72: =IFERROR(H72/D72,0) -> 0 | J72: =SUMIFS('Campaign - Dump'!$U:$U,'Campaign - Dump'!$J:$J,'Portfolio Wise '!$B72,'Campaign - Dump'!$A:$A,'Portfolio Wise '!$A72) -> 0 | K72: =IFERROR(F72/J72,0) -> 0 | L72: =IFERROR(J72/F72,0) -> 0 | M72: =IFERROR(J72/H72,0) -> 0 | N72: =IFERROR(Q72-H72,0) -> 3 | O72: =IFERROR(R72-J72,0) -> 27711.864 | P72: =IFERROR(O72/N72,0) -> 9237.2881 | Q72: =SUMIFS('Business - Dump'!$W:$W,'Business - Dump'!$B:$B,'Portfolio Wise '!$B72,'Business - Dump'!$A:$A,'Portfolio Wise '!$A72) -> 3 | R72: =SUMIFS('Business - Dump'!$U:$U,'Business - Dump'!$B:$B,'Portfolio Wise '!$B72,'Business - Dump'!$A:$A,'Portfolio Wise '!$A72)/1.18 -> 27711.864 | S72: =IFERROR(R72/Q72,0) -> 9237.2881 | T72: =IFERROR(F72/R72,0) -> 0 | U72: =IFERROR(R72/F72,0) -> 0 | V72: =SUMIFS('Business - Dump'!$G:$G,'Business - Dump'!$B:$B,'Portfolio Wise '!$B72,'Business - Dump'!$A:$A,'Portfolio Wise '!$A72) -> 355 | W72: =IFERROR(Q72/V72,0) -> 0.0084507042 | X72: =IFERROR(N72/Q72,0) -> 1 | Y72: =IFERROR(O72/R72,0) -> 1 | Z72: =IFERROR(H72/Q72,0) -> 0 | AA72: =IFERROR(O72/R72,0) -> 1 | AB72: =IFERROR(AVERAGEIFS('Business - Dump'!$O:$O,'Business - Dump'!$B:$B,'Portfolio Wise '!$B72,'Business - Dump'!$A:$A,'Portfolio Wise '!$A72),0) -> 0.8421 | AC72: =F72/SUMIFS('Campaign - Dump'!$Q:$Q,'Campaign - Dump'!$A:$A,'Portfolio Wise '!$A72) -> 0 | AD72: =IFERROR(N72/H72,0) -> 0
A73: Jan | B73: Total Jan | C73: =SUM(C50:C72) -> 3218559 | D73: =SUM(D50:D72) -> 13309 | E73: =IFERROR(D73/C73,0) -> 0.0041350803 | F73: =SUM(F50:F72) -> 268584.18 | G73: =IFERROR(F73/D73,0) -> 20.180643 | H73: =SUM(H50:H72) -> 82 | I73: =IFERROR(H73/D73,0) -> 0.0061612443 | J73: =SUM(J50:J72) -> 1526285 | K73: =IFERROR(F73/J73,0) -> 0.1759725 | L73: =IFERROR(J73/F73,0) -> 5.6827062 | M73: =IFERROR(J73/H73,0) -> 18613.231 | N73: =SUM(N50:N72) -> 113 | O73: =SUM(O50:O72) -> 1718473.2 | P73: =IFERROR(O73/N73,0) -> 15207.727 | Q73: =SUM(Q50:Q72) -> 154 | R73: =SUM(R50:R72) -> 2472068.9 | S73: =IFERROR(R73/Q73,0) -> 16052.395 | T73: =IFERROR(F73/R73,0) -> 0.10864753 | U73: =IFERROR(R73/F73,0) -> 9.2040749 | V73: =SUM(V50:V72) -> 25435 | W73: =IFERROR(Q73/V73,0) -> 0.0060546491 | X73: =IFERROR(N73/Q73,0) -> 0.73376623 | Y73: =IFERROR(O73/R73,0) -> 0.69515587 | Z73: =IFERROR(H73/Q73,0) -> 0.53246753 | AA73: =IFERROR(O73/R73,0) -> 0.69515587 | AB73: =IFERROR(AVERAGEIFS('Business - Dump'!$O:$O,'Business - Dump'!$B:$B,'Portfolio Wise '!$B73,'Business - Dump'!$A:$A,'Portfolio Wise '!$A73),0) -> 0 | AC73: =F73/SUMIFS('Campaign - Dump'!$Q:$Q,'Campaign - Dump'!$A:$A,'Portfolio Wise '!$A73) -> 0.99493538 | AD73: =IFERROR(N73/H73,0) -> 1.3780488
A74: Feb | B74: Sales Day | C74: =SUMIFS('Campaign - Dump'!$N:$N,'Campaign - Dump'!$J:$J,'Portfolio Wise '!$B74,'Campaign - Dump'!$A:$A,'Portfolio Wise '!$A74) -> 326736 | D74: =SUMIFS('Campaign - Dump'!$O:$O,'Campaign - Dump'!$J:$J,'Portfolio Wise '!$B74,'Campaign - Dump'!$A:$A,'Portfolio Wise '!$A74) -> 1437 | E74: =IFERROR(D74/C74,0) -> 0.0043980461 | F74: =SUMIFS('Campaign - Dump'!$Q:$Q,'Campaign - Dump'!$J:$J,'Portfolio Wise '!$B74,'Campaign - Dump'!$A:$A,'Portfolio Wise '!$A74) -> 12329.09 | G74: =IFERROR(F74/D74,0) -> 8.5797425 | H74: =SUMIFS('Campaign - Dump'!$T:$T,'Campaign - Dump'!$J:$J,'Portfolio Wise '!$B74,'Campaign - Dump'!$A:$A,'Portfolio Wise '!$A74) -> 1 | I74: =IFERROR(H74/D74,0) -> 0.00069589422 | J74: =SUMIFS('Campaign - Dump'!$U:$U,'Campaign - Dump'!$J:$J,'Portfolio Wise '!$B74,'Campaign - Dump'!$A:$A,'Portfolio Wise '!$A74) -> 25338.98 | K74: =IFERROR(F74/J74,0) -> 0.48656615 | L74: =IFERROR(J74/F74,0) -> 2.055219 | M74: =IFERROR(J74/H74,0) -> 25338.98 | N74: 0 | O74: 0 | P74: =IFERROR(O74/N74,0) -> 0 | Q74: =SUMIFS('Business - Dump'!$W:$W,'Business - Dump'!$B:$B,'Portfolio Wise '!$B74,'Business - Dump'!$A:$A,'Portfolio Wise '!$A74) -> 0 | R74: =SUMIFS('Business - Dump'!$U:$U,'Business - Dump'!$B:$B,'Portfolio Wise '!$B74,'Business - Dump'!$A:$A,'Portfolio Wise '!$A74)/1.18 -> 0 | S74: =IFERROR(R74/Q74,0) -> 0 | T74: =IFERROR(F74/R74,0) -> 0 | U74: =IFERROR(R74/F74,0) -> 0 | V74: =SUMIFS('Business - Dump'!$G:$G,'Business - Dump'!$B:$B,'Portfolio Wise '!$B74,'Business - Dump'!$A:$A,'Portfolio Wise '!$A74) -> 0 | W74: =IFERROR(Q74/V74,0) -> 0 | X74: =IFERROR(N74/Q74,0) -> 0 | Y74: =IFERROR(O74/R74,0) -> 0 | Z74: =IFERROR(H74/Q74,0) -> 0 | AA74: =IFERROR(O74/R74,0) -> 0 | AB74: =IFERROR(AVERAGEIFS('Business - Dump'!$O:$O,'Business - Dump'!$B:$B,'Portfolio Wise '!$B74,'Business - Dump'!$A:$A,'Portfolio Wise '!$A74),0) -> 0 | AC74: =F74/SUMIFS('Campaign - Dump'!$Q:$Q,'Campaign - Dump'!$A:$A,'Portfolio Wise '!$A74) -> 0.033945243 | AD74: =IFERROR(N74/H74,0) -> 0
A75: Feb | B75: Standing Table | C75: =SUMIFS('Campaign - Dump'!$N:$N,'Campaign - Dump'!$J:$J,'Portfolio Wise '!$B75,'Campaign - Dump'!$A:$A,'Portfolio Wise '!$A75) -> 0 | D75: =SUMIFS('Campaign - Dump'!$O:$O,'Campaign - Dump'!$J:$J,'Portfolio Wise '!$B75,'Campaign - Dump'!$A:$A,'Portfolio Wise '!$A75) -> 0 | E75: =IFERROR(D75/C75,0) -> 0 | F75: =SUMIFS('Campaign - Dump'!$Q:$Q,'Campaign - Dump'!$J:$J,'Portfolio Wise '!$B75,'Campaign - Dump'!$A:$A,'Portfolio Wise '!$A75) -> 0 | G75: =IFERROR(F75/D75,0) -> 0 | H75: =SUMIFS('Campaign - Dump'!$T:$T,'Campaign - Dump'!$J:$J,'Portfolio Wise '!$B75,'Campaign - Dump'!$A:$A,'Portfolio Wise '!$A75) -> 0 | I75: =IFERROR(H75/D75,0) -> 0 | J75: =SUMIFS('Campaign - Dump'!$U:$U,'Campaign - Dump'!$J:$J,'Portfolio Wise '!$B75,'Campaign - Dump'!$A:$A,'Portfolio Wise '!$A75) -> 0 | K75: =IFERROR(F75/J75,0) -> 0 | L75: =IFERROR(J75/F75,0) -> 0 | M75: =IFERROR(J75/H75,0) -> 0 | N75: =IFERROR(Q75-H75,0) -> 0 | O75: =IFERROR(R75-J75,0) -> 0 | P75: =IFERROR(O75/N75,0) -> 0 | Q75: =SUMIFS('Business - Dump'!$W:$W,'Business - Dump'!$B:$B,'Portfolio Wise '!$B75,'Business - Dump'!$A:$A,'Portfolio Wise '!$A75) -> 0 | R75: =SUMIFS('Business - Dump'!$U:$U,'Business - Dump'!$B:$B,'Portfolio Wise '!$B75,'Business - Dump'!$A:$A,'Portfolio Wise '!$A75)/1.18 -> 0 | S75: =IFERROR(R75/Q75,0) -> 0 | T75: =IFERROR(F75/R75,0) -> 0 | U75: =IFERROR(R75/F75,0) -> 0 | V75: =SUMIFS('Business - Dump'!$G:$G,'Business - Dump'!$B:$B,'Portfolio Wise '!$B75,'Business - Dump'!$A:$A,'Portfolio Wise '!$A75) -> 0 | W75: =IFERROR(Q75/V75,0) -> 0 | X75: =IFERROR(N75/Q75,0) -> 0 | Y75: =IFERROR(O75/R75,0) -> 0 | Z75: =IFERROR(H75/Q75,0) -> 0 | AA75: =IFERROR(O75/R75,0) -> 0 | AB75: =IFERROR(AVERAGEIFS('Business - Dump'!$O:$O,'Business - Dump'!$B:$B,'Portfolio Wise '!$B75,'Business - Dump'!$A:$A,'Portfolio Wise '!$A75),0) -> 0 | AC75: =F75/SUMIFS('Campaign - Dump'!$Q:$Q,'Campaign - Dump'!$A:$A,'Portfolio Wise '!$A75) -> 0 | AD75: =IFERROR(N75/H75,0) -> 0
A76: Feb | B76: TABLE TOP | C76: =SUMIFS('Campaign - Dump'!$N:$N,'Campaign - Dump'!$J:$J,'Portfolio Wise '!$B76,'Campaign - Dump'!$A:$A,'Portfolio Wise '!$A76) -> 9317 | D76: =SUMIFS('Campaign - Dump'!$O:$O,'Campaign - Dump'!$J:$J,'Portfolio Wise '!$B76,'Campaign - Dump'!$A:$A,'Portfolio Wise '!$A76) -> 108 | E76: =IFERROR(D76/C76,0) -> 0.011591714 | F76: =SUMIFS('Campaign - Dump'!$Q:$Q,'Campaign - Dump'!$J:$J,'Portfolio Wise '!$B76,'Campaign - Dump'!$A:$A,'Portfolio Wise '!$A76) -> 808.17 | G76: =IFERROR(F76/D76,0) -> 7.4830556 | H76: =SUMIFS('Campaign - Dump'!$T:$T,'Campaign - Dump'!$J:$J,'Portfolio Wise '!$B76,'Campaign - Dump'!$A:$A,'Portfolio Wise '!$A76) -> 0 | I76: =IFERROR(H76/D76,0) -> 0 | J76: =SUMIFS('Campaign - Dump'!$U:$U,'Campaign - Dump'!$J:$J,'Portfolio Wise '!$B76,'Campaign - Dump'!$A:$A,'Portfolio Wise '!$A76) -> 0 | K76: =IFERROR(F76/J76,0) -> 0 | L76: =IFERROR(J76/F76,0) -> 0 | M76: =IFERROR(J76/H76,0) -> 0 | N76: =IFERROR(Q76-H76,0) -> 5 | O76: =IFERROR(R76-J76,0) -> 26228.814 | P76: =IFERROR(O76/N76,0) -> 5245.7627 | Q76: =SUMIFS('Business - Dump'!$W:$W,'Business - Dump'!$B:$B,'Portfolio Wise '!$B76,'Business - Dump'!$A:$A,'Portfolio Wise '!$A76) -> 5 | R76: =SUMIFS('Business - Dump'!$U:$U,'Business - Dump'!$B:$B,'Portfolio Wise '!$B76,'Business - Dump'!$A:$A,'Portfolio Wise '!$A76)/1.18 -> 26228.814 | S76: =IFERROR(R76/Q76,0) -> 5245.7627 | T76: =IFERROR(F76/R76,0) -> 0.030812297 | U76: =IFERROR(R76/F76,0) -> 32.454575 | V76: =SUMIFS('Business - Dump'!$G:$G,'Business - Dump'!$B:$B,'Portfolio Wise '!$B76,'Business - Dump'!$A:$A,'Portfolio Wise '!$A76) -> 724 | W76: =IFERROR(Q76/V76,0) -> 0.0069060773 | X76: =IFERROR(N76/Q76,0) -> 1 | Y76: =IFERROR(O76/R76,0) -> 1 | Z76: =IFERROR(H76/Q76,0) -> 0 | AA76: =IFERROR(O76/R76,0) -> 1 | AB76: =IFERROR(AVERAGEIFS('Business - Dump'!$O:$O,'Business - Dump'!$B:$B,'Portfolio Wise '!$B76,'Business - Dump'!$A:$A,'Portfolio Wise '!$A76),0) -> 0.79495 | AC76: =F76/SUMIFS('Campaign - Dump'!$Q:$Q,'Campaign - Dump'!$A:$A,'Portfolio Wise '!$A76) -> 0.0022251056 | AD76: =IFERROR(N76/H76,0) -> 0
A77: Feb | B77: Brand | C77: =SUMIFS('Campaign - Dump'!$N:$N,'Campaign - Dump'!$J:$J,'Portfolio Wise '!$B77,'Campaign - Dump'!$A:$A,'Portfolio Wise '!$A77) -> 650943 | D77: =SUMIFS('Campaign - Dump'!$O:$O,'Campaign - Dump'!$J:$J,'Portfolio Wise '!$B77,'Campaign - Dump'!$A:$A,'Portfolio Wise '!$A77) -> 3248 | E77: =IFERROR(D77/C77,0) -> 0.0049896842 | F77: =SUMIFS('Campaign - Dump'!$Q:$Q,'Campaign - Dump'!$J:$J,'Portfolio Wise '!$B77,'Campaign - Dump'!$A:$A,'Portfolio Wise '!$A77) -> 100374.47 | G77: =IFERROR(F77/D77,0) -> 30.90347 | H77: =SUMIFS('Campaign - Dump'!$T:$T,'Campaign - Dump'!$J:$J,'Portfolio Wise '!$B77,'Campaign - Dump'!$A:$A,'Portfolio Wise '!$A77) -> 62 | I77: =IFERROR(H77/D77,0) -> 0.01908867 | J77: =SUMIFS('Campaign - Dump'!$U:$U,'Campaign - Dump'!$J:$J,'Portfolio Wise '!$B77,'Campaign - Dump'!$A:$A,'Portfolio Wise '!$A77) -> 1219390.7 | K77: =IFERROR(F77/J77,0) -> 0.082315265 | L77: =IFERROR(J77/F77,0) -> 12.148415 | M77: =IFERROR(J77/H77,0) -> 19667.592 | N77: 0 | O77: 0 | P77: =IFERROR(O77/N77,0) -> 0 | Q77: =SUMIFS('Business - Dump'!$W:$W,'Business - Dump'!$B:$B,'Portfolio Wise '!$B77,'Business - Dump'!$A:$A,'Portfolio Wise '!$A77) -> 0 | R77: =SUMIFS('Business - Dump'!$U:$U,'Business - Dump'!$B:$B,'Portfolio Wise '!$B77,'Business - Dump'!$A:$A,'Portfolio Wise '!$A77)/1.18 -> 0 | S77: =IFERROR(R77/Q77,0) -> 0 | T77: =IFERROR(F77/R77,0) -> 0 | U77: =IFERROR(R77/F77,0) -> 0 | V77: =SUMIFS('Business - Dump'!$G:$G,'Business - Dump'!$B:$B,'Portfolio Wise '!$B77,'Business - Dump'!$A:$A,'Portfolio Wise '!$A77) -> 0 | W77: =IFERROR(Q77/V77,0) -> 0 | X77: =IFERROR(N77/Q77,0) -> 0 | Y77: =IFERROR(O77/R77,0) -> 0 | Z77: =IFERROR(H77/Q77,0) -> 0 | AA77: =IFERROR(O77/R77,0) -> 0 | AB77: =IFERROR(AVERAGEIFS('Business - Dump'!$O:$O,'Business - Dump'!$B:$B,'Portfolio Wise '!$B77,'Business - Dump'!$A:$A,'Portfolio Wise '!$A77),0) -> 0 | AC77: =F77/SUMIFS('Campaign - Dump'!$Q:$Q,'Campaign - Dump'!$A:$A,'Portfolio Wise '!$A77) -> 0.27635744 | AD77: =IFERROR(N77/H77,0) -> 0
A78: Feb | B78: Standing Table - SM3 | C78: =SUMIFS('Campaign - Dump'!$N:$N,'Campaign - Dump'!$J:$J,'Portfolio Wise '!$B78,'Campaign - Dump'!$A:$A,'Portfolio Wise '!$A78) -> 1169623 | D78: =SUMIFS('Campaign - Dump'!$O:$O,'Campaign - Dump'!$J:$J,'Portfolio Wise '!$B78,'Campaign - Dump'!$A:$A,'Portfolio Wise '!$A78) -> 7326 | E78: =IFERROR(D78/C78,0) -> 0.0062635567 | F78: =SUMIFS('Campaign - Dump'!$Q:$Q,'Campaign - Dump'!$J:$J,'Portfolio Wise '!$B78,'Campaign - Dump'!$A:$A,'Portfolio Wise '!$A78) -> 158195.42 | G78: =IFERROR(F78/D78,0) -> 21.593696 | H78: =SUMIFS('Campaign - Dump'!$T:$T,'Campaign - Dump'!$J:$J,'Portfolio Wise '!$B78,'Campaign - Dump'!$A:$A,'Portfolio Wise '!$A78) -> 46 | I78: =IFERROR(H78/D78,0) -> 0.0062790063 | J78: =SUMIFS('Campaign - Dump'!$U:$U,'Campaign - Dump'!$J:$J,'Portfolio Wise '!$B78,'Campaign - Dump'!$A:$A,'Portfolio Wise '!$A78) -> 757954.99 | K78: =IFERROR(F78/J78,0) -> 0.20871348 | L78: =IFERROR(J78/F78,0) -> 4.7912575 | M78: =IFERROR(J78/H78,0) -> 16477.282 | N78: =IFERROR(Q78-H78,0) -> 32 | O78: =IFERROR(R78-J78,0) -> 738909.42 | P78: =IFERROR(O78/N78,0) -> 23090.919 | Q78: =SUMIFS('Business - Dump'!$W:$W,'Business - Dump'!$B:$B,'Portfolio Wise '!$B78,'Business - Dump'!$A:$A,'Portfolio Wise '!$A78) -> 78 | R78: =SUMIFS('Business - Dump'!$U:$U,'Business - Dump'!$B:$B,'Portfolio Wise '!$B78,'Business - Dump'!$A:$A,'Portfolio Wise '!$A78)/1.18 -> 1496864.4 | S78: =IFERROR(R78/Q78,0) -> 19190.569 | T78: =IFERROR(F78/R78,0) -> 0.10568454 | U78: =IFERROR(R78/F78,0) -> 9.4621223 | V78: =SUMIFS('Business - Dump'!$G:$G,'Business - Dump'!$B:$B,'Portfolio Wise '!$B78,'Business - Dump'!$A:$A,'Portfolio Wise '!$A78) -> 13983 | W78: =IFERROR(Q78/V78,0) -> 0.0055782021 | X78: =IFERROR(N78/Q78,0) -> 0.41025641 | Y78: =IFERROR(O78/R78,0) -> 0.49363818 | Z78: =IFERROR(H78/Q78,0) -> 0.58974359 | AA78: =IFERROR(O78/R78,0) -> 0.49363818 | AB78: =IFERROR(AVERAGEIFS('Business - Dump'!$O:$O,'Business - Dump'!$B:$B,'Portfolio Wise '!$B78,'Business - Dump'!$A:$A,'Portfolio Wise '!$A78),0) -> 0.88316667 | AC78: =F78/SUMIFS('Campaign - Dump'!$Q:$Q,'Campaign - Dump'!$A:$A,'Portfolio Wise '!$A78) -> 0.43555379 | AD78: =IFERROR(N78/H78,0) -> 0.69565217
